Workbook

Sheet InfoInicial
A1: ESTA PLANILLA PUEDE SER UTILIZADA SOLAMENTE PARA EL TRABAJO PRACTICO: | E1: 6
G2: Reglas y consideraciones a tener en cuenta antes de entregar para corregir
A3: Tasa porcentual de IVA | B3: 0.21 | G3: 1. TODAS las celdas que tomen datos de otra parte del archivo deben estar linkeadas con una FÓRMULA. No se corregirán TPs con datos escritos como valores (esto vale incluso para la tasa de HD, IG e IVA). Tampoco se aceptarán fórmulas que hagan referencia a otros archivos.
A4: Tasa porcentual de Impuesto a las Ganancias | B4: 0.35
A5: Honorarios al Directorio | B5: 0.078 | C5: Variable sobre Utilidad económica antes de HD e IG
A7: Tiempo de Amortización Activos Fijos: | B7: Se considera una depreciación lineal y un valor residual nulo | G7: 2. TODOS los valores que se ingresen al archivo por primera vez deben tener su respectiva referencia o FUENTE (ej. cálculos auxiliares en otra hoja, links, etc.)
A8: edificios y obras complementarias | B8: 30 | C8: años
A9: instalaciones industriales | B9: 10 | C9: años | G9: 3. Los datos utilizados tienen que tener concordancia con los dimensionamientos anteriores.
A10: máquinas, equipos y accesorios | B10: 10 | C10: años | G10: 4. El SET "A" de verificaciones en la hoja “E-Form” debe estar OK antes de entregar una primer versión para corregir.
A11: rodados y equipos auxiliares | B11: 5 | C11: años
A12: muebles y útiles | B12: 5 | C12: años | G12: 5. El SET "A", “B” y “C” de verificaciones en la hoja “F-Form” debe estar OK antes de la entrega final
A13: Otros Activos y Cargos Diferidos | B13: 5 | C13: años
A14: Imprevistos | B14: 0.097
A16: Nombre del Producto | B16: Válvula mariposa sanitaria de acero inoxidable
A18: Ventas Anuales Promedio | B18: 44800 | C18: en Unidades
A19: Precio Promedio | B19: 110000 | C19: en $
A21: Cantidad de personal total
A22: en Producción | B22: 16 | C22: personas
A23: en Comercialización | B23: 5 | C23: personas
A24: en Administración | B24: 4 | C24: personas
A26: Tamaño de la planta en metros cuadrados | B26: 2500 | C26: m2
A27: Periodo de Instalación | B27: 12 | C27: en meses
A28: Período de Puesta en Marcha | B28: 4 | C28: en meses
A31: Tasa de Cambio | B31: 1300 | C31: $ por cada | D31: 1 | E31: U$S
A34: Tasa de Credito Bancario | B34: 65 | C34: anual
A35: Rubro a financiar | B35: Metalúrgico | G35: Año 6
A36: % sobre el total del Rubro | B36: 50
A38: Dias de Financiación de Proveedores | B38: 30
A39: % sobre Compras | B39: 50
A40: Tasa de financiación | B40: 30 | C40: anual
K234: Miguelito

Sheet E-Inv AF y Am
A1: ESTA PLANILLA PUEDE SER UTILIZADA SOLAMENTE PARA EL TRABAJO PRACTICO | E1: =InfoInicial!E1 -> 6
A3: Inversión Inicial en Activo Fijo | B3: Gasto interno (en $) | D3: Gasto Externo (en $)
B4: Año 0 | C4: Año 1 | D4: Año 0 | E4: Año 1
A6: a) Bienes de Uso
A7: Terreno y sus mejoras | B7: ='C. Aux. - Inv AF y Am'!C60*InfoInicial!B31 -> 211250000 | C7: 0 | D7: 0 | E7: 0
A8: Edificio y obras complementarias | B8: ='C. Aux. - Inv AF y Am'!B90 -> 975000000 | C8: 0 | D8: 0 | E8: 0
A9: Instalaciones industriales | B9: 0 | C9: 0 | D9: 0 | E9: 0
A10: Máquinas operativas
A11: importadas, valor FOB | D11: ='C. Aux. - Inv AF y Am'!D121*InfoInicial!B31 -> 694746000
A12: nacionales, precio en fábrica del proveedor
A13: Gastos conexos a la importación de maquinaria | D13: ='C. Aux. - Inv AF y Am'!C123*InfoInicial!B31 -> 95894500
A14: Transporte y montaje de la maquinaria | B14: ='C. Aux. - Inv AF y Am'!B125 -> 9000000
A15: Rodados y equipos auxiliares | B15: ='C. Aux. - Inv AF y Am'!D39 -> 17123903 | C15: 0 | D15: 0 | E15: 0
A16: Muebles y útiles* | B16: ='C. Aux. - Inv AF y Am'!D22 -> 8033066 | C16: 0 | D16: 0 | E16: 0
A17: Infraestructura en Redes y Telecomunicaciones | B17: ='C. Aux. - Inv AF y Am'!D72*1.5 -> 9528000 | C17: 0 | D17: 0 | E17: 0
A18: Infraestructura en predio propio | B18: ='C. Aux. - Inv AF y Am'!B82*1.5 -> 7687500 | C18: 0 | D18: 0 | E18: 0
A19: Imprevistos | B19: =SUM(B7:B18)*InfoInicial!B14 -> 1.2004938e+08 | D19: =SUM(D7:D18)*InfoInicial!B14 -> 76692128
A21: Total Bienes de uso | B21: =SUM(B7:B19) -> 1.3576718e+09 | D21: =SUM(D7:D19) -> 8.6733263e+08
A23: b) Gastos asimilables o cargos diferidos
A24: Investigaciones y estudios | B24: ='C. Aux. - Inv AF y Am'!C108 -> 32500000
A25: Constitución y organización de la empresa | B25: ='C. Aux. - Inv AF y Am'!B135 -> 1224000
A26: Gastos de Admin. e Ing. En en período de Instalación
A27: Gastos de puesta en marcha (AL AÑO 1) | B27: 0 | C27: ='CÁLCULOS MP'!F104*InfoInicial!B31 -> 3.4546504e+08
A28: Patentes y Licencias | B28: ='C. Aux. - Inv AF y Am'!B105+'C. Aux. - Inv AF y Am'!C99 -> 22282000
A29: Publicidad y Marca | B29: ='C. Aux. - Inv AF y Am'!B51+'C. Aux. - Inv AF y Am'!B52 -> 2120000
A30: Infraestructura en predio ajeno | B30: 0
A31: Imprevistos | B31: =SUM(B24:B30)*InfoInicial!B5 -> 4533828 | C31: =SUM(C24:C30)*InfoInicial!C4 -> 0
A33: Total gastos asimilables o cargos diferidos | B33: =SUM(B24:B31) -> 62659828 | C33: =SUM(C24:C31) -> 3.4546504e+08
A35: c) Total Inversiones iniciales Activo Fijo, sin IVA | B35: =B21+B33 -> 1.4203317e+09 | C35: =C33+C21 -> 3.4546504e+08 | D35: =D33+D21 -> 8.6733263e+08 | E35: =E33+E21 -> 0
A36: d) IVA | B36: =B35*InfoInicial!B3 -> 2.9826965e+08 | C36: =C35*InfoInicial!B3 -> 72547658 | D36: =D35*InfoInicial!B3 -> 1.8213985e+08 | E36: =E35*InfoInicial!B3 -> 0
A38: e) TOTAL INVERSIONES INICIALES ACTIVO FIJO | B38: =B35+B36 -> 1.7186013e+09 | C38: =C35+C36 -> 4.1801269e+08 | D38: =D35+D36 -> 1.0494725e+09 | E38: =E35+E36 -> 0
A39: *Incluye depósito, matafuegos, etc.
A41: Rubro | B41: Inversión | C41: Coeficiente | D41: Alícuotas de amortización | G41: Valor residual
B42: original | D42: Años 1/3 | E42: Años 4/5
A43: Bienes de Uso
A45: Infraestructura en Redes y Telecomunicaciones | B45: =B17 -> 9528000 | G45: =B45 -> 9528000
A46: Infraestructura en predio propio | B46: =B18 -> 7687500 | G46: =B46 -> 7687500
A47: Terreno y sus mejoras | B47: =B7 -> 211250000 | G47: =B47-D47*3-E47*2 -> 211250000
A48: Edificio y obras complementarias | B48: =B8 -> 975000000 | C48: 0.03 | D48: =B48/30 -> 32500000 | E48: =B48/30 -> 32500000 | G48: =B48-D48*5 -> 812500000
A49: Instalaciones industriales | C49: 0.1 | D49: =B49/10 -> 0 | E49: =B49/10 -> 0 | G49: =B49-D49*3-E49*2 -> 0
A50: Máquinas operativas | B50: =SUM(B11:E14) -> 799640500 | C50: 0.1 | D50: =B50/10 -> 79964050 | E50: =B50/10 -> 79964050 | G50: =B50-D50*3-E50*2 -> 399820250
A51: Rodados y equipos auxiliares | B51: =B15 -> 17123903 | C51: 0.2 | D51: =B51/5 -> 3424780.6 | E51: =B51/5 -> 3424780.6 | G51: =B51-D51*3-E51*2 -> 0
A52: Muebles y útiles | B52: =B16 -> 8033066 | C52: 0.2 | D52: =B52/5 -> 1606613.2 | E52: =B52/5 -> 1606613.2 | G52: =B52-D52*3-E52*2 -> 0
A53: Imprevistos | B53: =SUM(B19:D19) -> 1.9674151e+08 | D53: =B53*InfoInicial!B14 -> 19083926 | E53: =B53*InfoInicial!B14 -> 19083926 | G53: =B53-D53*3-E53*2 -> 1.0132188e+08
A54: Subtotal | B54: =SUM(B45:B53) -> 2.2250045e+09 | D54: =SUM(D48:D53) -> 1.3657937e+08 | E54: =SUM(E48:E53) -> 1.3657937e+08 | G54: =SUM(G44:G53) -> 1.5421076e+09
A56: Cargos Diferidos | B56: =SUM(B33:E33) -> 4.0812486e+08 | C56: 0.2 | D56: =B56*C56 -> 81624973 | E56: =B56*C56 -> 81624973 | G56: =B56-D56*3-E56*2 -> 0
A59: Totales, s/IVA | B59: =B54+B56 -> 2.6331293e+09 | D59: =D54+D56 -> 2.1820434e+08 | E59: =E54+E56 -> 2.1820434e+08 | G59: =G54+G56 -> 1.5421076e+09

Sheet C. Aux. - Inv AF y Am
A1: MUEBLES Y ÚTILES
A2: CONCEPTO | B2: CANTIDAD | C2: PRECIO UNITARIO | D2: TOTAL | E2: LINK
A3: Ventiladores | B3: 3 | C3: 134679 | D3: =B3*C3 -> 404037 | E3: https://www.mercadolibre.com.ar/ventilador-industrial-2-en-1-pie-pared-30-pulgadas-hamers-international-por-kacemaster-hi-180/p/MLA28530583#polycard_client=search-nordic&searchVariation=MLA28530583&backend_model=search-backend&wid=MLA1477985933&position=6&search_layout=grid&type=product&tracking_id=71c6694a-933b-4410-b2a0-4ecbe665bfed&sid=search
A4: Cesto de basura | B4: 12 | C4: 29334 | D4: =B4*C4 -> 352008 | E4: https://www.mercadolibre.com.ar/tacho-cesto-basura-residuos-70lt-florida/p/MLA23829534#polycard_client=search-nordic&searchVariation=MLA23829534&wid=MLA2271277652&position=16&search_layout=grid&type=product&tracking_id=af76bd0f-a8eb-4f24-9f07-c4ab71de3243&sid=search
A5: Mesas | B5: 4 | C5: 81299 | D5: =B5*C5 -> 325196 | E5: https://www.mercadolibre.com.ar/mesa-comedor-sala-madera-maciza-moderna-recta-120x80-sajo-tapa-natural/p/MLA35012645#polycard_client=search-nordic&searchVariation=MLA35012645&wid=MLA1418200317&position=4&search_layout=grid&type=product&tracking_id=66e5ed12-2013-47e0-86f6-e4ab8ed83d19&sid=search
A6: Sillas | B6: 16 | C6: 34484 | D6: =B6*C6 -> 551744 | E6: https://articulo.mercadolibre.com.ar/MLA-1124805067-juego-de-comedor-sillas-4-fajas-_JM?searchVariation=174238678815&pdp_filters=price%3A*-100000#polycard_client=search-nordic&searchVariation=174238678815&position=31&search_layout=grid&type=item&tracking_id=e1b67c4c-af20-4307-b6d8-7b5e34a787cd
A7: Vajilla | B7: 2 | C7: 20076 | D7: =B7*C7 -> 40152 | E7: https://www.mercadolibre.com.ar/set-de-vajilla-x-12-durax-plato-forjado-vaso-lunita-color-transparente/p/MLA52843818#polycard_client=search-nordic&searchVariation=MLA52843818&wid=MLA2186178562&position=5&search_layout=grid&type=product&tracking_id=c1110d7d-01ca-4c87-bc00-8ed6602c3c3d&sid=search
A8: Mesada | B8: 1 | C8: 168556 | D8: =B8*C8 -> 168556 | E8: https://www.mercadolibre.com.ar/mesada-cocina-de-acero-inoxidable-160x052-con-bacha-doble/p/MLA37524426#polycard_client=search-nordic&searchVariation=MLA37524426&wid=MLA2085610346&position=4&search_layout=grid&type=product&tracking_id=0932ea22-4e37-446e-a16c-a07cc711af3f&sid=search
A9: Escritorio | B9: 15 | C9: 65999 | D9: =B9*C9 -> 989985 | E9: https://www.mercadolibre.com.ar/escritorio-mesa-de-trabajo-home-collection-melamina-1-cajon-color-nevadoeverest/p/MLA25772158#polycard_client=search-nordic&searchVariation=MLA25772158&wid=MLA1398196809&position=23&search_layout=grid&type=product&tracking_id=a45b7b62-b275-469c-adab-bba7621b39df&sid=search
A10: Cajoneras | B10: 12 | C10: 80999 | D10: =B10*C10 -> 971988 | E10: https://www.mercadolibre.com.ar/chifonier-cajonera-dakar-zero-4-cajones-melamina-color-venezia/p/MLA28697087#polycard_client=search-nordic&searchVariation=MLA28697087&wid=MLA1905637978&position=4&search_layout=grid&type=product&tracking_id=2d4fad02-85af-41e8-9408-0340c14f6097&sid=search
A11: Mesa | B11: 5 | C11: 65999 | D11: =B11*C11 -> 329995 | E11: https://www.mercadolibre.com.ar/escritorio-mesa-de-trabajo-home-collection-melamina-1-cajon-color-nevadoeverest/p/MLA25772158#polycard_client=search-nordic&searchVariation=MLA25772158&wid=MLA1398196809&position=23&search_layout=grid&type=product&tracking_id=a45b7b62-b275-469c-adab-bba7621b39df&sid=search
A12: Sillas ergonómicas | B12: 14 | C12: 72584 | D12: =B12*C12 -> 1016176 | E12: https://www.mercadolibre.com.ar/silla-de-oficina-pc-ejecutiva-escritorio-lumbar-blanca-zhome-color-blanco-material-del-tapizado-malla-z-103-b/p/MLA42445941#polycard_client=search-nordic&searchVariation=MLA42445941&wid=MLA1964272712&position=7&search_layout=grid&type=product&tracking_id=4e62f608-2610-47b0-95af-99312d3e9ea2&sid=search
A13: Pizarras | B13: 2 | C13: 47990 | D13: =B13*C13 -> 95980 | E13: https://www.mercadolibre.com.ar/pizarraspremium-pizarra-blanca-magnetica-multiuso-80x120cm-marco-pvc/p/MLA23839169#polycard_client=search-nordic&searchVariation=MLA23839169&wid=MLA1472131439&position=5&search_layout=grid&type=product&tracking_id=c12a4fc5-bcee-479b-8dbe-ceab27117bf4&sid=search
A14: Inodoros con mochila | B14: 6 | C14: 188516 | D14: =B14*C14 -> 1131096 | E14: https://www.mercadolibre.com.ar/inodoro-corto-ferrum-mochila-asiento-deposito-simple-color-blanco/p/MLA50845595#polycard_client=search-nordic&searchVariation=MLA50845595&wid=MLA2215256670&position=4&search_layout=grid&type=product&tracking_id=baa560b3-be5e-4d43-85fe-06829ed36ee3&sid=search
A15: Lavamanos | B15: 4 | C15: 75241 | D15: =B15*C15 -> 300964 | E15: https://articulo.mercadolibre.com.ar/MLA-1863892946-bacha-roca-loza-de-colgar-1-agujero-con-griferia-monocomando-_JM?searchVariation=181217673610#polycard_client=search-nordic&searchVariation=181217673610&position=57&search_layout=grid&type=item&tracking_id=dea5c3a7-4839-4eaa-9983-bf1998a2dcdd
A16: Lockers | B16: 12 | C16: 612628 | D16: =C16 -> 612628 | E16: https://articulo.mercadolibre.com.ar/MLA-1426467169-lockers-metalicos-16-puertas-con-cerradura-reforzado-_JM?searchVariation=182767673083#is_advertising=true&searchVariation=182767673083&backend_model=search-backend&position=1&search_layout=grid&type=pad&tracking_id=ad2e654e-c51b-451e-8f1d-432ff849d01c&is_advertising=true&ad_domain=VQCATCORE_LST&ad_position=1&ad_click_id=MTNhZGQ4ODEtOTY5OC00M2FlLTljZDctMjkxZDFkMmNhNWU4
A17: Espejos | B17: 4 | C17: 23991 | D17: =B17*C17 -> 95964 | E17: https://articulo.mercadolibre.com.ar/MLA-2009868240-espejo-50-cm-bano-redondo-circular-_JM?searchVariation=186863106697#polycard_client=search-nordic&searchVariation=186863106697&position=38&search_layout=grid&type=item&tracking_id=3b35a17a-d86b-419c-b8e4-f78917b25142
A18: Duchas | B18: 2 | C18: 9390 | D18: =B18*C18 -> 18780 | E18: https://www.mercadolibre.com.ar/flor-ducha-cuadrada-acero-inoxidable-brazo-cano-cromado-color-gris/p/MLA34134266?pdp_filters=item_id:MLA1807778750#wid=MLA1807778750&sid=search&is_advertising=true&searchVariation=MLA34134266&backend_model=search-backend&position=1&search_layout=grid&type=pad&tracking_id=4a4c48dd-1490-41e8-8de7-2a4c12e7156a&is_advertising=true&ad_domain=VQCATCORE_LST&ad_position=1&ad_click_id=NTEzNDE0OTctYjEyMC00MDk1LWFhNGUtZWRlOWE0YmYzZDg1
A19: Mingitorios | B19: 2 | C19: 54625 | D19: =B19*C19 -> 109250 | E19: https://www.mercadolibre.com.ar/mingitorio-oval-piazza-b0601-loza-blanco-urinario-sanitario/p/MLA37737585#polycard_client=search-nordic&searchVariation=MLA37737585&wid=MLA1831629870&position=13&search_layout=grid&type=product&tracking_id=af85aa43-c4f1-4e24-8460-1c5336a15a3a&sid=search
A20: Articulos de libreria | B20: 64 | C20: 98164 | D20: =C20*2 -> 196328 | E20: https://articulo.mercadolibre.com.ar/MLA-1124027479-set-utiles-libreria-articulos-oficina-escritorio-kit-empresa-_JM#polycard_client=search-nordic&position=22&search_layout=grid&type=item&tracking_id=8962efd5-362f-4597-a02d-595a55f1ff39&wid=MLA1124027479&sid=search
A21: Herramientas | B21: 12 | C21: 322239 | D21: =C21 -> 322239 | E21: https://articulo.mercadolibre.com.ar/MLA-789232631-valija-aluminio-187-pz-herramientas-y-tubos-la-mas-completa-_JM?searchVariation=61941586109#polycard_client=search-nordic&searchVariation=61941586109&position=17&search_layout=grid&type=item&tracking_id=edf4c3fc-0536-4f9c-9597-227f1ce3f421
C22: TOTAL | D22: =SUM(D3:D21) -> 8033066
A24: EQUIPOS AUXILIARES
A25: CONCEPTO | B25: CANTIDAD | C25: PRECIO UNITARIO | D25: TOTAL | E25: LINK
A26: Carteles de señalización | B26: 10 | C26: 2831 | D26: =B26*C26 -> 28310 | E26: https://www.mercadolibre.com.ar/cartel-senalizacion-industrial-modelos-22x28-ever-safe-color-matafuego/p/MLA52220717#polycard_client=search-nordic&searchVariation=MLA52220717&wid=MLA2185827974&position=18&search_layout=grid&type=product&tracking_id=0240d003-55c1-4f1e-a8df-7cecd2bb7534&sid=search
A27: Teléfonos | B27: 14 | C27: 21500 | D27: =B27*C27 -> 301000 | E27: https://www.mercadolibre.com.ar/telefono-fijo-de-mesa-pared-cableado-casa-numeros-grandes-libercam-phon-30-color-negro/p/MLA26360634?pdp_filters=item_id:MLA1480424714#wid=MLA1480424714&sid=search&is_advertising=true&searchVariation=MLA26360634&backend_model=search-backend&position=2&search_layout=stack&type=pad&tracking_id=5f679f02-8833-44e3-87db-24b653d43fd9&is_advertising=true&ad_domain=VQCATCORE_LST&ad_position=2&ad_click_id=MTljMDY3OTctY2QwZi00MDMxLTlmZGQtOGY4NjEwZmU1Y2Vh
A28: Matafuegos ABC | B28: 6 | C28: 89179 | D28: =B28*C28 -> 535074 | E28: https://articulo.mercadolibre.com.ar/MLA-620271506-matafuegos-nuevos-polvo-triclase-5-kg-tarjeta-soporte-baliza-_JM?searchVariation=15873553124#is_advertising=true&searchVariation=15873553124&backend_model=search-backend&position=3&search_layout=grid&type=pad&tracking_id=be724187-60f5-4e51-a256-d4c073c9a6c3&is_advertising=true&ad_domain=VQCATCORE_LST&ad_position=3&ad_click_id=YmZkYTZmNTgtNmM0ZS00YWI5LWJjY2ItNjBkNjYwN2Q3NTI0
A29: Luces de emergencia | B29: 4 | C29: 14400 | D29: =B29*C29 -> 57600 | E29: https://articulo.mercadolibre.com.ar/MLA-1974041224-pack-2-luz-de-emergencia-bateria-recargable-60-led-industria-_JM?searchVariation=186391418629#is_advertising=true&searchVariation=186391418629&backend_model=search-backend&position=8&search_layout=grid&type=pad&tracking_id=607661ae-1f9b-4b22-a31d-58361221510b&is_advertising=true&ad_domain=VQCATCORE_LST&ad_position=8&ad_click_id=ZGU1YTM3MjYtMTY0MS00OGIyLTkxZmYtOWZiN2U3YTA0NTVl
A30: Dispenser de agua | B30: 4 | C30: 276749 | D30: =B30*C30 -> 1106996 | E30: https://articulo.mercadolibre.com.ar/MLA-736077407-dispenser-de-agua-frio-calor-conexion-a-red-premium-kit-_JM?searchVariation=188767880075#polycard_client=search-nordic&searchVariation=188767880075&position=21&search_layout=grid&type=item&tracking_id=e6d41f5b-3a42-4d30-9313-a15d92cc5846
A31: Botiquín primeros auxilios | B31: 6 | C31: 16872 | D31: =B31*C31 -> 101232 | E31: https://articulo.mercadolibre.com.ar/MLA-1485501109-botiquin-primeros-auxilios-30-elementos-eversafe-mol-madera-_JM#is_advertising=true&backend_model=search-backend&position=3&search_layout=grid&type=pad&tracking_id=f021687f-ea43-4d0c-9e68-253307cecea9&is_advertising=true&ad_domain=VQCATCORE_LST&ad_position=3&ad_click_id=YjNmYjQyMGMtYjQ4Yi00ZGNlLWI0ODUtNThlMzY0MGY4NjMz
A32: Microondas | B32: 4 | C32: 104799 | D32: =B32*C32 -> 419196 | E32: https://www.mercadolibre.com.ar/microondas-sansei-msarw20uap-rotativo-20l-700w/p/MLA43529502#polycard_client=search_best-seller&tracking_id=78d08ac2-7f3e-437f-9696-aff864c61617&wid=MLA1967730220&sid=search
A33: Heladera | B33: 1 | C33: 388778 | D33: =B33*C33 -> 388778 | E33: https://www.mercadolibre.com.ar/heladera-telefunken-300-lts-con-freezer-blanca-hd300b/p/MLA51643130#polycard_client=search-nordic&searchVariation=MLA51643130&wid=MLA2182060712&position=25&search_layout=stack&type=product&tracking_id=3af9a9a8-30e9-4f5b-b201-36219d10f4ab&sid=search
A34: Cafetera | B34: 4 | C34: 19049 | D34: =B34*C34 -> 76196 | E34: https://www.mercadolibre.com.ar/cafetera-electrica-de-filtro-sansei-casa9118bp-075l-color-negro/p/MLA27351867?pdp_filters=item_id:MLA1551426198#wid=MLA1551426198&sid=search&is_advertising=true&searchVariation=MLA27351867&backend_model=search-backend&position=1&search_layout=stack&type=pad&tracking_id=c94d15dc-6e57-4d25-a555-c3088b34b24d&is_advertising=true&ad_domain=VQCATCORE_LST&ad_position=1&ad_click_id=YjNmMGYxMmUtMTA0Zi00NWVlLWFmZDktZjI3ZjcxODUyOGVk
A35: Aire acondicionado | B35: 5 | C35: 619999 | D35: =B35*C35 -> 3099995 | E35: https://www.mercadolibre.com.ar/aire-acondicionado-sansei-split-ultra-friocalor-inverter-3500w3053fg/p/MLA25265609#polycard_client=search-nordic&searchVariation=MLA25265609&wid=MLA1514533665&position=38&search_layout=stack&type=product&tracking_id=e3aa563b-4da8-4c82-bf92-510c068c34ac&sid=search
A36: Computadoras | B36: 15 | C36: 631904 | D36: =B36*C36 -> 9478560 | E36: https://www.mercadolibre.com.ar/notebook-lenovo-ideapad-slim-156-intel-i3-8gb-ram-256gb-ssd-color-arctic-grey/p/MLA45361885#polycard_client=search-nordic&searchVariation=MLA45361885&wid=MLA2006890214&position=10&search_layout=stack&type=product&tracking_id=b904eb91-8bcb-424e-aba1-4fc7cc598428&sid=search
A37: Impresora | B37: 4 | C37: 163399 | D37: =B37*C37 -> 653596 | E37: https://www.mercadolibre.com.ar/impresora-multifuncion-hp-deskjet-ink-advantage-2875-wifi/p/MLA29022615#polycard_client=search_best-seller&tracking_id=d6d87091-7df5-4e4d-9985-2ee499254c67&wid=MLA1445106795&sid=search
A38: Zorra manual | B38: 2 | C38: 438685 | D38: =B38*C38 -> 877370 | E38: https://www.equustech.com.ar/productos/zorra-25-tn/
C39: TOTAL | D39: =SUM(D26:D38) -> 17123903
A41: zorra eléctrica | B41: 2525828 | C41: https://www.equustech.com.ar/productos/traspaletaelectrica2ton/
A42: zorra manual | B42: 438685 | C42: https://www.equustech.com.ar/productos/zorra-25-tn/
A43: zorra manual x2 | B43: =B42*2 -> 877370
A48: Publicidad y Marca:
B50: AR$ | C50: U$D
A51: Registro de Marca con un asesor | B51: 120000 | D51: https://www.mf-ip.com/?gad_source=1&gad_campaignid=21024858891&gbraid=0AAAAA9TjQnqY5jESBbGMmQJdXGapnuKF6&gclid=CjwKCAjw2vTFBhAuEiwAFaScwmbO-ZhVjzjK_ZmXJqp6LiYD8C8V2-AgQGJeZcJfGHwugVOutYJigBoCihUQAvD_BwE
A52: Pagina Web | B52: 2000000 | D52: Presupuesto SecDev
A53: Participación en Ferias | B53: =C53*InfoInicial!B31 -> 4550000 | C53: 3500 | D53: https://www.thaiscorp.com/seguritec/en/exhibidor/costos
A54: Anuncios en Revistas | B54: =C54*InfoInicial!B31 -> 2210000 | C54: 1700 | D54: https://valve-world-americas.com/advertising/magazine
A57: Terreno y sus Mejoras:
A59: Terreno | B59: Propiedad de 2500 m2 divisible | C59: Precio del m2= 65 dolares
A60: 2500 m2 | B60: AR$ | C60: 162500 | D60: https://terreno.mercadolibre.com.ar/MLA-2005698022-terreno-en-venta-en-parque-industrial-pilar-_JM#polycard_client=search-nordic&search_layout=grid&position=1&type=item&tracking_id=81a66e16-5bc6-4283-a724-70591c0fe4b9
B61: U$D | C61: =C60*InfoInicial!B31 -> 211250000
A63: Infraestructura en Redes y Telecomunicaciones:
A66: Concepto | B66: Supuesto | C66: Costo unitario | D66: Total estimado
A67: Bandejas portacables (360 m líneas) | B67: 120 tramos de 3 m | C67: 19000 | D67: =C67*120 -> 2280000
A68: Cable UTP Cat 6 (720 m) | B68: 3 rollos | C68: 133000 | D68: =C68*3 -> 399000
A69: Switch (24 puertos) | B69: 2 unidades | C69: 74000 | D69: =C69*2 -> 148000
A70: Access Points WiFi (x4) | B70: 4 unidades | C70: 624000 | D70: =C70*4 -> 2496000
A71: Mano de obra (30 bocas) | B71: 30 bocas | C71: 34300 | D71: =C71*30 -> 1029000
C72: Total estimado | D72: =SUM(D67:D71) -> 6352000 | E72: Consideramos un 50% del costo para la mano de obra
A74: Infraestructura en predio propio:
A76: Concepto | B76: Precio (ARS)
A77: Portón corredizo automático (con motor) | B77: =1200000*2 -> 2400000
A78: Iluminación exterior perimetral | B78: 500000
A79: Cartelería y señalización externa | B79: 300000
A80: Instalación eléctrica externa (tablero, jabalina, etc.) | B80: 350000
A81: Bases de hormigón para maquinas | B81: 1575000
A82: Total estimado | B82: =SUM(B77:B81) -> 5125000 | C82: Consideramos un 50% del costo para la mano de obra
A83: Total estimado + mano de obra | B83: =B82*1.5 -> 7687500
A85: Edificio y Obras Complementarias:
B87: AR$ | C87: U$D
A88: Valor del m2 de Construcción | B88: =C88*InfoInicial!B31 -> 780000 | C88: 600 | D88: https://tradenews.com.ar/el-costo-de-la-construccion-de-depositos-de-clase-a-ronda-los-us600-el-metro-cuadrado/
A89: m2 Total | B89: 1250
B90: =B89*B88 -> 975000000
A92: Costo de Licencias (normas API):
A94: Tarifario: | B94: https://www.api.org/products-and-services/individual-certification-programs/schedules-and-fees?utm_source=chatgpt.com#tab-fees
B96: U$ | C96: AR$
A97: Costo de Certificacion: | B97: 1070 | C97: =B97*InfoInicial!B31 -> 1391000
A98: Certificaciones necesarias: | B98: 2
A99: Costo Total: | B99: =B97*B98 -> 2140 | C99: =B99*InfoInicial!B31 -> 2782000
A101: Costo certificacion ISO:
A103: Tarifario | B103: https://www.enlacetecno.com.ar/el-precio-de-la-calidad-cuanto-cuesta-certificarse-en-una-norma-iso-y-por-que-vale-la-pena/
A104: Costo U$D | B104: Costo AR$
A105: 15000 | B105: =A105*InfoInicial!B31 -> 19500000
A107: Costo de estudio de prefactibilidad: | B107: Costo U$D | C107: Costo AR$
B108: 25000 | C108: =B108*InfoInicial!B31 -> 32500000
A111: Costo Maquinaria:
A113: maquina | B113: cantidad | C113: precio unitario | D113: precio total
A114: Torno CNC | B114: 6 | C114: 14950 | D114: =B114*C114 -> 89700
A115: Brazo robótico de soldadura | B115: 1 | C115: 18800 | D115: =B115*C115 -> 18800
A116: Brazo robótico de pulido | B116: 5 | C116: 69000 | D116: =B116*C116 -> 345000
A117: Banco de pruebas | B117: 3 | C117: 22000 | D117: =B117*C117 -> 66000
A118: Sierra de cinta | B118: 2 | C118: 2960 | D118: =B118*C118 -> 5920
A119: Posicionador de piezas | B119: 1 | C119: 7000 | D119: =B119*C119 -> 7000
C120: TOTAL | D120: =SUM(D113:D119) -> 532420 | E120: Flete + carga al medio | F120: 2000
C121: VALOR FOB | D121: =D120+F120 -> 534420
A123: Gasto conexo (seguro, flete, derechos de importacion) | C123: 73765
A125: Montaje de maquinaria | B125: =SUM(B114:B119)*500000 -> 9000000
A128: Constitución de la Empresa:
A130: Honorarios Profesionales (escriban+contador) | B130: 600000
A131: Inscripción IGJ | B131: 4000
...

Sheet E-Costos
A3: ESTA PLANILLA PUEDE SER UTILIZADA SOLAMENTE PARA EL TRABAJO PRACTICO: | E3: =InfoInicial!E1 -> 6
A4: COSTO TOTAL DE PRODUCCION
B5: Gastos en el Area de Producción
A6: Rubros | B6: Año 1 | C6: Año 2 | D6: Año 3 | E6: Año 4 | F6: Año 5
A7: Materia prima | B7: =('CÁLCULOS MP'!F102)*InfoInicial!B31 -> 1.4898176e+09 | C7: =+'CÁLCULOS MP'!$B$78*InfoInicial!$B$31 -> 1.4444621e+09 | D7: =+'CÁLCULOS MP'!$B$78*InfoInicial!$B$31 -> 1.4444621e+09 | E7: =+'CÁLCULOS MP'!$B$78*InfoInicial!$B$31 -> 1.4444621e+09 | F7: =+'CÁLCULOS MP'!$B$78*InfoInicial!$B$31 -> 1.4444621e+09
A8: Mano de obra directa | B8: ='AUX - COSTO DE PRODUC'!B17 -> 1.2909486e+08 | C8: ='AUX - COSTO DE PRODUC'!$B$12 -> 1.4343874e+08 | D8: ='AUX - COSTO DE PRODUC'!$B$12 -> 1.4343874e+08 | E8: ='AUX - COSTO DE PRODUC'!$B$12 -> 1.4343874e+08 | F8: ='AUX - COSTO DE PRODUC'!$B$12 -> 1.4343874e+08
A9: Gastos de fabricación:
A10: Amortizaciones | B10: ='AUX - COSTO DE PRODUC'!$B$40 -> 1.4929805e+08 | C10: ='AUX - COSTO DE PRODUC'!$B$40 -> 1.4929805e+08 | D10: ='AUX - COSTO DE PRODUC'!$B$40 -> 1.4929805e+08 | E10: ='AUX - COSTO DE PRODUC'!$B$37 -> 1.4929805e+08 | F10: ='AUX - COSTO DE PRODUC'!$B$37 -> 1.4929805e+08
A11: Personal indirecto | B11: ='AUX - COSTO DE PRODUC'!$D$51 -> 136015992 | C11: ='AUX - COSTO DE PRODUC'!$D$51 -> 136015992 | D11: ='AUX - COSTO DE PRODUC'!$D$51 -> 136015992 | E11: ='AUX - COSTO DE PRODUC'!$D$51 -> 136015992 | F11: ='AUX - COSTO DE PRODUC'!$D$51 -> 136015992
A12: Materiales | B12: ='AUX - COSTO DE PRODUC'!$F$59 -> 58465765 | C12: ='AUX - COSTO DE PRODUC'!$G$59 -> 57988971 | D12: ='AUX - COSTO DE PRODUC'!$G$59 -> 57988971 | E12: ='AUX - COSTO DE PRODUC'!$G$59 -> 57988971 | F12: ='AUX - COSTO DE PRODUC'!$G$59 -> 57988971
A13: Energía eléctrica | B13: ='C. Aux. Costos'!B165 -> 47167836 | C13: ='C. Aux. Costos'!E157 -> 44809444 | D13: ='C. Aux. Costos'!E157 -> 44809444 | E13: ='C. Aux. Costos'!E157 -> 44809444 | F13: ='C. Aux. Costos'!E157 -> 44809444
A14: Combustibles | B14: 0 | C14: 0 | D14: 0 | E14: 0 | F14: 0
A15: Redes y Telecomunicaciones | B15: 0 | C15: 0 | D15: 0 | E15: 0 | F15: 0
A16: Tasas e impuestos | B16: ='C. Aux. Costos'!B60 -> 21937500 | C16: ='C. Aux. Costos'!B60 -> 21937500 | D16: ='C. Aux. Costos'!B60 -> 21937500 | E16: ='C. Aux. Costos'!B60 -> 21937500 | F16: ='C. Aux. Costos'!B60 -> 21937500
A17: Seguridad e Higiene | B17: 0 | C17: 0 | D17: 0 | E17: 0 | F17: 0
A18: Tratamiento de efluentes y subproductos | B18: 0 | C18: 0 | D18: 0 | E18: 0 | F18: 0
A19: Seguros | B19: ='C. Aux. Costos'!$E$263*0.9+'C. Aux. Costos'!$F$269 -> 24990084 | C19: ='C. Aux. Costos'!$E$263*0.9+'C. Aux. Costos'!$G$269 -> 24990084 | D19: ='C. Aux. Costos'!$E$263*0.9+'C. Aux. Costos'!$G$269 -> 24990084 | E19: ='C. Aux. Costos'!$E$263*0.9+'C. Aux. Costos'!$G$269 -> 24990084 | F19: ='C. Aux. Costos'!$E$263*0.9+'C. Aux. Costos'!$G$269 -> 24990084
A20: *libre para insertar costos adicionales*
A21: *libre para insertar costos adicionales*
A22: Imprevistos | B22: =SUM(B7:B16)*InfoInicial!$B$14 -> 1.9708436e+08 | C22: =SUM(C7:C16)*InfoInicial!$B$14 -> 1.9380123e+08 | D22: =SUM(D7:D16)*InfoInicial!$B$14 -> 1.9380123e+08 | E22: =SUM(E7:E16)*InfoInicial!$B$14 -> 1.9380123e+08 | F22: =SUM(F7:F16)*InfoInicial!$B$14 -> 1.9380123e+08
A23: Gastos Total de Producción | B23: =SUM(B7:B22) -> 2.253872e+09 | C23: =SUM(C7:C22) -> 2.2167421e+09 | D23: =SUM(D7:D22) -> 2.2167421e+09 | E23: =SUM(E7:E22) -> 2.2167421e+09 | F23: =SUM(F7:F22) -> 2.2167421e+09
A25: % Gasto Constante | B25: =(B10+B11+B16+B22)/B23 -> 0.22376422 | C25: =(C10+C11+C16+C22)/C23 -> 0.22603115 | D25: =(D10+D11+D16+D22)/D23 -> 0.22603115 | E25: =(E10+E11+E16+E22)/E23 -> 0.22603115 | F25: =(F10+F11+F16+F22)/F23 -> 0.22603115
A26: % Gasto Variable | B26: =(B7+B8+B12+B13)/B23 -> 0.76514816 | C26: =(C7+C8+C12+C13)/C23 -> 0.76269551 | D26: =(D7+D8+D12+D13)/D23 -> 0.76269551 | E26: =(E7+E8+E12+E13)/E23 -> 0.76269551 | F26: =(F7+F8+F12+F13)/F23 -> 0.76269551
B28: Gastos a activar
B29: Mercadería en Curso y Semielaborada | G29: Puesta en marcha
A30: Rubros | B30: Año 1 | C30: Año 2 | D30: Año 3 | E30: Año 4 | F30: Año 5 | G30: Año 1
A31: Materia prima | B31: ='CÁLCULOS MP'!$F$107*InfoInicial!$B$31 -> 25600511 | C31: ='CÁLCULOS MP'!F107*InfoInicial!B31 -> 25600511 | D31: ='C. Aux. Costos'!$C$215 -> 25600511 | E31: ='C. Aux. Costos'!$C$215 -> 25600511 | F31: ='C. Aux. Costos'!$C$215 -> 25600511 | G31: ='CÁLCULOS MP'!F104*InfoInicial!B31 -> 3.4546504e+08
A32: Mano de obra directa | B32: ='C. Aux. Costos'!$C$217 -> 2542195.5 | C32: ='C. Aux. Costos'!$C$217 -> 2542195.5 | D32: ='C. Aux. Costos'!$C$217 -> 2542195.5 | E32: ='C. Aux. Costos'!$C$217 -> 2542195.5 | F32: ='C. Aux. Costos'!$C$217 -> 2542195.5 | G32: =B8-'AUX - COSTO DE PRODUC'!B19 -> 12128257
A33: Gastos de fabricación:
A34: Amortizaciones | B34: ='C. Aux. Costos'!B189 -> 2084275.6 | C34: ='C. Aux. Costos'!B190 -> 1740277 | D34: ='C. Aux. Costos'!B190 -> 1740277 | E34: ='C. Aux. Costos'!B191 -> 1740277 | F34: ='C. Aux. Costos'!B191 -> 1740277 | G34: 0
A35: Personal indirecto | B35: ='C. Aux. Costos'!C208 -> 997150.3 | C35: ='C. Aux. Costos'!B208 -> 1005986.7 | D35: ='C. Aux. Costos'!B208 -> 1005986.7 | E35: ='C. Aux. Costos'!B208 -> 1005986.7 | F35: ='C. Aux. Costos'!B208 -> 1005986.7 | G35: 0
A36: Materiales | B36: ='C. Aux. Costos'!A215*SUM('AUX - COSTO DE PRODUC'!H54:H57) -> 1254338.6 | C36: ='C. Aux. Costos'!$A$215*SUM('AUX - COSTO DE PRODUC'!$I$54:$I$57) -> 1027751 | D36: ='C. Aux. Costos'!$A$215*SUM('AUX - COSTO DE PRODUC'!$I$54:$I$57) -> 1027751 | E36: ='C. Aux. Costos'!$A$215*SUM('AUX - COSTO DE PRODUC'!$I$54:$I$57) -> 1027751 | F36: ='C. Aux. Costos'!$A$215*SUM('AUX - COSTO DE PRODUC'!$I$54:$I$57) -> 1027751 | G36: ='AUX - COSTO DE PRODUC'!B60*B36 -> 125433.86
A37: Energía eléctrica | B37: ='C. Aux. Costos'!B172 -> 417982.83 | C37: ='C. Aux. Costos'!E164 -> 417982.83 | D37: ='C. Aux. Costos'!E164 -> 417982.83 | E37: ='C. Aux. Costos'!E164 -> 417982.83 | F37: ='C. Aux. Costos'!E164 -> 417982.83 | G37: ='C. Aux. Costos'!E168 -> 8146717
A38: Combustibles | B38: 0 | C38: 0 | D38: 0 | E38: 0 | F38: 0
A39: Redes y Telecomunicaciones | B39: 0 | C39: 0 | D39: 0 | E39: 0 | F39: 0
A40: Tasas e impuestos | B40: ='C. Aux. Costos'!D237 -> 192693.93 | C40: ='C. Aux. Costos'!D232 -> 194401.51 | D40: ='C. Aux. Costos'!D232 -> 194401.51 | E40: ='C. Aux. Costos'!D232 -> 194401.51 | F40: ='C. Aux. Costos'!D232 -> 194401.51
A41: Otros rubros
A42: Imprevistos | B42: =SUM(B31:B40)*InfoInicial!$B$14 -> 3209647.4 | C42: =SUM(C31:C40)*InfoInicial!$B$14 -> 3155323.3 | D42: =SUM(D31:D40)*InfoInicial!$B$14 -> 3155323.3 | E42: =SUM(E31:E40)*InfoInicial!$B$14 -> 3155323.3 | F42: =SUM(F31:F40)*InfoInicial!$B$14 -> 3155323.3
A43: Total gastos a activar | B43: =SUM(B31:B42) -> 36298795 | C43: =SUM(C31:C42) -> 35684429 | D43: =SUM(D31:D42) -> 35684429 | E43: =SUM(E31:E42) -> 35684429 | F43: =SUM(F31:F42) -> 35684429 | G43: =SUM(G31:G42) -> 3.6586544e+08
B45: Costo en el Area de Producción
B46: Año 1 | C46: Año 2 | D46: Año 3 | E46: Año 4 | F46: Año 5
A47: Gastos Total de Producción | B47: =B23+B43+G43 -> 2.6560363e+09 | C47: =C23+C43 -> 2.2524265e+09 | D47: =D23+D43 -> 2.2524265e+09 | E47: =E23+E43 -> 2.2524265e+09 | F47: =F23+F43 -> 2.2524265e+09
A48: Menos:
A49: Gasto de puesta en marcha | B49: =G43 -> 3.6586544e+08 | C49: 0 | D49: 0 | E49: 0 | F49: 0
A50: Variación Mercadería en proceso | B50: =B43 -> 36298795 | C50: =B43-C43 -> 614366.31 | D50: =C43-D43 -> 0 | E50: =D43-E43 -> 0 | F50: =F42-E42 -> 0
A51: Costo de producción anual | B51: =B47-B49 -> 2.2901708e+09 | C51: =C47-C50 -> 2.2518122e+09 | D51: =D47-D50 -> 2.2524265e+09 | E51: =E47-E50 -> 2.2524265e+09 | F51: =F47-F50 -> 2.2524265e+09
A52: Costo de prod. Unitario Promedio | B52: =B51/'C. Aux. Costos'!O7 -> 62479.084 | C52: =C51/'C. Aux. Costos'!$P$7 -> 50263.664 | D52: =D51/'C. Aux. Costos'!$P$7 -> 50277.378 | E52: =E51/'C. Aux. Costos'!$P$7 -> 50277.378 | F52: =F51/'C. Aux. Costos'!$P$7 -> 50277.378
A54: % Gasto Constante | B54: =1-B55 -> 0.28822033 | C54: =1-C55 -> 0.23736923 | D54: =1-D55 -> 0.23730449 | E54: =1-E55 -> 0.23730449 | F54: =1-F55 -> 0.23730449
A55: % Gasto Variable | B55: =((B47*B26)-B49-B50)/B51 -> 0.71177967 | C55: =((C47*C26)-C49-C50)/C51 -> 0.76263077 | D55: =((D47*D26)-D49-D50)/D51 -> 0.76269551 | E55: =((E47*E26)-E49-E50)/E51 -> 0.76269551 | F55: =((F47*F26)-F49-F50)/F51 -> 0.76269551
B58: Gastos en el Area de Administración
A59: Rubros | B59: Año 1 | C59: Año 2 | D59: Año 3 | E59: Año 4 | F59: Año 5
A60: Personal | B60: ='C. Aux. Costos'!$E$41 -> 93450288 | C60: ='C. Aux. Costos'!$E$41 -> 93450288 | D60: ='C. Aux. Costos'!$E$41 -> 93450288 | E60: ='C. Aux. Costos'!$E$41 -> 93450288 | F60: ='C. Aux. Costos'!$E$41 -> 93450288
A61: Amortizaciones de A. Fijo | B61: ='C. Aux. Costos'!$D$98 -> 10910217 | C61: ='C. Aux. Costos'!$D$98 -> 10910217 | D61: ='C. Aux. Costos'!$D$98 -> 10910217 | E61: ='C. Aux. Costos'!$D$98 -> 10910217 | F61: ='C. Aux. Costos'!$D$98 -> 10910217
A62: Materiales | B62: ='C. Aux. Costos'!B71 -> 4248014.4 | C62: ='C. Aux. Costos'!$D$71 -> 4248014.4 | D62: ='C. Aux. Costos'!$D$71 -> 4248014.4 | E62: ='C. Aux. Costos'!$D$71 -> 4248014.4 | F62: ='C. Aux. Costos'!$D$71 -> 4248014.4
A63: Electricidad | B63: ='C. Aux. Costos'!B165*0.05 -> 2358391.8 | C63: ='C. Aux. Costos'!$E$157*0.05 -> 2240472.2 | D63: ='C. Aux. Costos'!$E$157*0.05 -> 2240472.2 | E63: ='C. Aux. Costos'!$E$157*0.05 -> 2240472.2 | F63: ='C. Aux. Costos'!$E$157*0.05 -> 2240472.2
A64: Combustible | B64: 0 | C64: 0 | D64: 0 | E64: 0 | F64: 0
A65: Redes y Telecomunicaciones | B65: ='C. Aux. Costos'!$C$9/2 -> 166740 | C65: ='C. Aux. Costos'!$C$9/2 -> 166740 | D65: ='C. Aux. Costos'!$C$9/2 -> 166740 | E65: ='C. Aux. Costos'!$C$9/2 -> 166740 | F65: ='C. Aux. Costos'!$C$9/2 -> 166740
A66: Tasas e impuestos | B66: ='C. Aux. Costos'!$E$244 -> 1218750 | C66: ='C. Aux. Costos'!$E$244 -> 1218750 | D66: ='C. Aux. Costos'!$E$244 -> 1218750 | E66: ='C. Aux. Costos'!$E$244 -> 1218750 | F66: ='C. Aux. Costos'!$E$244 -> 1218750
A67: Cámaras y Seguridad | B67: 0 | C67: 0 | D67: 0 | E67: 0 | F67: 0
A68: Gastos Varios | B68: ='C. Aux. Costos'!C83 -> 54386901 | C68: ='C. Aux. Costos'!$D$83 -> 24386901 | D68: ='C. Aux. Costos'!$D$83 -> 24386901 | E68: ='C. Aux. Costos'!$D$83 -> 24386901 | F68: ='C. Aux. Costos'!$D$83 -> 24386901
A69: Seguros | B69: ='C. Aux. Costos'!$E$263*0.05 -> 1200348.3 | C69: ='C. Aux. Costos'!$E$263*0.05 -> 1200348.3 | D69: ='C. Aux. Costos'!$E$263*0.05 -> 1200348.3 | E69: ='C. Aux. Costos'!$E$263*0.05 -> 1200348.3 | F69: ='C. Aux. Costos'!$E$263*0.05 -> 1200348.3
A70: *libre para insertar costos adicionales*
A71: Imprevistos | B71: =SUM(B60:B69)*InfoInicial!$B$14 -> 16290146 | C71: =SUM(C60:C69)*InfoInicial!$B$14 -> 13368708 | D71: =SUM(D60:D69)*InfoInicial!$B$14 -> 13368708 | E71: =SUM(E60:E69)*InfoInicial!$B$14 -> 13368708 | F71: =SUM(F60:F69)*InfoInicial!$B$14 -> 13368708
A73: Costo total de Admistración | B73: =SUM(B60:B71) -> 1.842298e+08 | C73: =SUM(C60:C71) -> 1.5119044e+08 | D73: =SUM(D60:D71) -> 1.5119044e+08 | E73: =SUM(E60:E71) -> 1.5119044e+08 | F73: =SUM(F60:F71) -> 1.5119044e+08
A75: % Gasto Constante | B75: =(B71+B69+B68+B66+B65+B63+B62+B61+B60)/B73 -> 1 | C75: =(C71+C69+C68+C66+C65+C63+C62+C61+C60)/C73 -> 1 | D75: =(D71+D69+D68+D66+D65+D63+D62+D61+D60)/D73 -> 1 | E75: =(E71+E69+E68+E66+E65+E63+E62+E61+E60)/E73 -> 1 | F75: =(F71+F69+F68+F66+F65+F63+F62+F61+F60)/F73 -> 1
A76: % Gasto Variable | B76: =0/B73 -> 0 | C76: =0/C73 -> 0 | D76: =0/D73 -> 0 | E76: =0/E73 -> 0 | F76: =0/F73 -> 0
B79: Gastos en el Area de Comercialización
A80: Rubros | B80: Año 1 | C80: Año 2 | D80: Año 3 | E80: Año 4 | F80: Año 5
A81: Personal (incluye comisiones) | B81: ='C. Aux. Costos'!$E$42 -> 75249200 | C81: ='C. Aux. Costos'!$E$42 -> 75249200 | D81: ='C. Aux. Costos'!$E$42 -> 75249200 | E81: ='C. Aux. Costos'!$E$42 -> 75249200 | F81: ='C. Aux. Costos'!$E$42 -> 75249200
A82: Amortizaciones de A. Fijo | B82: ='C. Aux. Costos'!$D$99 -> 10910217 | C82: ='C. Aux. Costos'!$D$99 -> 10910217 | D82: ='C. Aux. Costos'!$D$99 -> 10910217 | E82: ='C. Aux. Costos'!$D$99 -> 10910217 | F82: ='C. Aux. Costos'!$D$99 -> 10910217
A83: Materiales | B83: ='C. Aux. Costos'!C71 -> 39827960 | C83: ='C. Aux. Costos'!$E$71 -> 48095960 | D83: ='C. Aux. Costos'!$E$71 -> 48095960 | E83: ='C. Aux. Costos'!$E$71 -> 48095960 | F83: ='C. Aux. Costos'!$E$71 -> 48095960
A84: Energía Eléctrica | B84: ='C. Aux. Costos'!B165*0.05 -> 2358391.8 | C84: ='C. Aux. Costos'!$E$157*0.05 -> 2240472.2 | D84: ='C. Aux. Costos'!$E$157*0.05 -> 2240472.2 | E84: ='C. Aux. Costos'!$E$157*0.05 -> 2240472.2 | F84: ='C. Aux. Costos'!$E$157*0.05 -> 2240472.2
A85: Combustible | B85: 0 | C85: 0 | D85: 0 | E85: 0 | F85: 0
A86: Redes y Telecomunicaciones | B86: ='C. Aux. Costos'!$C$9/2 -> 166740 | C86: ='C. Aux. Costos'!$C$9/2 -> 166740 | D86: ='C. Aux. Costos'!$C$9/2 -> 166740 | E86: ='C. Aux. Costos'!$C$9/2 -> 166740 | F86: ='C. Aux. Costos'!$C$9/2 -> 166740
A87: Logística y Distribución | B87: ='C. Aux. Costos'!D105 -> 29225600 | C87: ='C. Aux. Costos'!$E$105 -> 35840000 | D87: ='C. Aux. Costos'!$E$105 -> 35840000 | E87: ='C. Aux. Costos'!$E$105 -> 35840000 | F87: ='C. Aux. Costos'!$E$105 -> 35840000
A88: Tasas e impuestos | B88: ='C. Aux. Costos'!$E$250 -> 161959550 | C88: ='C. Aux. Costos'!$F$250 -> 198338750 | D88: ='C. Aux. Costos'!$F$250 -> 198338750 | E88: ='C. Aux. Costos'!$F$250 -> 198338750 | F88: ='C. Aux. Costos'!$F$250 -> 198338750
A89: Gastos Vários | B89: ='C. Aux. Costos'!$C$91 -> 10772460 | C89: ='C. Aux. Costos'!$C$91 -> 10772460 | D89: ='C. Aux. Costos'!$C$91 -> 10772460 | E89: ='C. Aux. Costos'!$C$91 -> 10772460 | F89: ='C. Aux. Costos'!$C$91 -> 10772460
A90: Seguros | B90: ='C. Aux. Costos'!$E$263*0.05 -> 1200348.3 | C90: ='C. Aux. Costos'!$E$263*0.05 -> 1200348.3 | D90: ='C. Aux. Costos'!$E$263*0.05 -> 1200348.3 | E90: ='C. Aux. Costos'!$E$263*0.05 -> 1200348.3 | F90: ='C. Aux. Costos'!$E$263*0.05 -> 1200348.3
A91: *libre para insertar costos adicionales*
A92: Imprevistos | B92: =SUM(B81:B90)*InfoInicial!$B$14 -> 32172035 | C92: =SUM(C81:C90)*InfoInicial!$B$14 -> 37132972 | D92: =SUM(D81:D90)*InfoInicial!$B$14 -> 37132972 | E92: =SUM(E81:E90)*InfoInicial!$B$14 -> 37132972 | F92: =SUM(F81:F90)*InfoInicial!$B$14 -> 37132972
A94: Costo total de Comercialización | B94: =SUM(B81:B92) -> 3.638425e+08 | C94: =SUM(C81:C92) -> 4.1994712e+08 | D94: =SUM(D81:D92) -> 4.1994712e+08 | E94: =SUM(E81:E92) -> 4.1994712e+08 | F94: =SUM(F81:F92) -> 4.1994712e+08
A96: % Gasto Constante | B96: =(B92+B90+B89+B86+B84+B83+B82+B81+'C. Aux. Costos'!E247+'C. Aux. Costos'!E248)/B94 -> 0.47788838 | C96: =(C92+C90+C89+C86+C84+C83+C82+C81+'C. Aux. Costos'!$F$247+'C. Aux. Costos'!$F$248)/C94 -> 0.44526349 | D96: =(D92+D90+D89+D86+D84+D83+D82+D81+'C. Aux. Costos'!$F$247+'C. Aux. Costos'!$F$248)/D94 -> 0.44526349 | E96: =(E92+E90+E89+E86+E84+E83+E82+E81+'C. Aux. Costos'!$F$247+'C. Aux. Costos'!$F$248)/E94 -> 0.44526349 | F96: =(F92+F90+F89+F86+F84+F83+F82+F81+'C. Aux. Costos'!$F$247+'C. Aux. Costos'!$F$248)/F94 -> 0.44526349
A97: % Gasto Variable | B97: =(B87+'C. Aux. Costos'!E249)/B94 -> 0.52211162 | C97: =(C87+'C. Aux. Costos'!$F$249)/C94 -> 0.55473651 | D97: =(D87+'C. Aux. Costos'!$F$249)/D94 -> 0.55473651 | E97: =(E87+'C. Aux. Costos'!$F$249)/E94 -> 0.55473651 | F97: =(F87+'C. Aux. Costos'!$F$249)/F94 -> 0.55473651
A100: COSTO TOTAL Y RESULTADO A NIVEL ECONOMICO
B101: Año 1 | C101: Año 2 | D101: Año 3 | E101: Año 4 | F101: Año 5
A102: Venta anual, en Unidades Producto 1 | B102: ='C. Aux. Costos'!O4 -> 36532 | C102: ='C. Aux. Costos'!P4 -> 44800 | D102: ='C. Aux. Costos'!P4 -> 44800 | E102: ='C. Aux. Costos'!P4 -> 44800 | F102: ='C. Aux. Costos'!P4 -> 44800
A103: Precio de venta Producto 1 | B103: ='C. Aux. Costos'!R2 -> 110000 | C103: ='C. Aux. Costos'!R2 -> 110000 | D103: ='C. Aux. Costos'!R2 -> 110000 | E103: ='C. Aux. Costos'!R2 -> 110000 | F103: ='C. Aux. Costos'!R2 -> 110000
A104: Venta anual, en Unidades Producto 2
A105: Precio de venta Producto 2
A106: Venta anual, en Unidades Subproducto
A107: Precio de venta Subproducto
A108: *agregar adicionales si hace falta*
A109: *agregar adicionales si hace falta*
A110: VENTAS ANUALES | B110: ='C. Aux. Costos'!O5 -> 4018520000 | C110: ='C. Aux. Costos'!P5 -> 4928000000 | D110: ='C. Aux. Costos'!P5 -> 4928000000 | E110: ='C. Aux. Costos'!P5 -> 4928000000 | F110: ='C. Aux. Costos'!P5 -> 4928000000
A112: Consumo de materia prima | B112: =B7 -> 1.4898176e+09 | C112: =C7 -> 1.4444621e+09 | D112: =D7 -> 1.4444621e+09 | E112: =E7 -> 1.4444621e+09 | F112: =F7 -> 1.4444621e+09
A113: Mano de obra directa | B113: =B8 -> 1.2909486e+08 | C113: =C8 -> 1.4343874e+08 | D113: =D8 -> 1.4343874e+08 | E113: =E8 -> 1.4343874e+08 | F113: =F8 -> 1.4343874e+08
A114: Gastos de fabricación | B114: =SUM(B10:B21) -> 4.3787523e+08 | C114: =SUM(C10:C21) -> 4.3504004e+08 | D114: =SUM(D10:D21) -> 4.3504004e+08 | E114: =SUM(E10:E21) -> 4.3504004e+08 | F114: =SUM(F10:F21) -> 4.3504004e+08
A116: Gastos de Producción | B116: =SUM(B112:B114) -> 2.0567877e+09 | C116: =SUM(C112:C114) -> 2.0229409e+09 | D116: =SUM(D112:D114) -> 2.0229409e+09 | E116: =SUM(E112:E114) -> 2.0229409e+09 | F116: =SUM(F112:F114) -> 2.0229409e+09
A118: Menos:
A119: Puesta en marcha | B119: =G43 -> 3.6586544e+08
...

Sheet C. Aux. Costos
A2: m3 de agua consumidos en producción: | B2: =2.5*350*8/1000 -> 7 | O2: PLAN DE VENTAS | Q2: P= | R2: 110000
A3: m3 de agua consumidos por empleados: | B3: 254 | O3: AÑO 1 | P3: AÑO 2 | Q3: AÑO 3 | R3: AÑO 4 | S3: AÑO 5
N4: cantidad ventas | O4: 36532 | P4: 44800 | Q4: 44800 | R4: 44800 | S4: 44800
A5: 1250 m2 + 7m alto | B5: =1250*7 -> 8750 | N5: P*Q | O5: =$R$2*O4 -> 4018520000 | P5: =$R$2*P4 -> 4928000000 | Q5: =$R$2*Q4 -> 4928000000 | R5: =$R$2*R4 -> 4928000000 | S5: =$R$2*S4 -> 4928000000
A6: Descripcion | B6: Precio | C6: Gasto Total | D6: Link
A7: Precio Agua ($/m3) | B7: 1141.87 | C7: =B7*(B3+B2) -> 298028.07 | D7: https://www.aysa.com.ar/tramites/Conoce-tu-factura | N7: PRODUCCION | O7: 36655 | P7: 44800 | Q7: 44800 | R7: 44800 | S7: 44800
A8: Precio gas ($/m3) | B8: 217 | C8: =B8*B5 -> 1898750
A9: Precio internet y linea | B9: 27790 | C9: =B9*12 -> 333480 | D9: https://www.telecom.com.ar/web/productos/internet | E9: Se divide equitativamente entre administración y comercialización
A10: TOTAL SERVICIOS MENSUAL | C10: =SUM(C7:C9) -> 2530258.1
A13: SUELDOS | B13: Basico/Mes | C13: Contribuciones | D13: Cantidad | E13: Total | F13: Aguinaldo
A14: Director general | B14: 3120000 | C14: ='C. Aux. Costos'!J30/100*B14 -> 929760 | D14: 1 | E14: =C14+B14 -> 4049760 | F14: =B14*D14 -> 3120000 | G14: Sueldo de director general divido en las 3 areas para calcular costos de cada area
A15: Personal de portería y seguridad | B15: 1008000 | C15: =0.258*B15 -> 260064 | D15: 2 | E15: =C15+B15 -> 1268064 | F15: =B15*D15 -> 2016000
A16: Personal de limpieza | B16: 785000 | C16: =0.258*B16 -> 202530 | D16: 3 | E16: =C16+B16 -> 987530 | F16: =B16*D16 -> 2355000
A17: Gerente Administrativo | B17: 2580000 | C17: =0.258*B17 -> 665640 | D17: 1 | E17: =C17+B17 -> 3245640 | F17: =B17*D17 -> 2580000
A18: Contador | B18: 1400000 | C18: =0.258*B18 -> 361200 | D18: 1 | E18: =C18+B18 -> 1761200 | F18: =B18*D18 -> 1400000
A19: Encargado de rrhh | B19: 1580000 | C19: =0.258*B19 -> 407640 | D19: 1 | E19: =C19+B19 -> 1987640 | F19: =B19*D19 -> 1580000
A20: Analista de compras | B20: 1890000 | C20: =0.258*B20 -> 487620 | D20: 1 | E20: =C20+B20 -> 2377620 | F20: =B20*D20 -> 1890000
A21: Gerente Comercial | B21: 2600000 | C21: =0.258*B21 -> 670800 | D21: 1 | E21: =C21+B21 -> 3270800 | F21: =B21*D21 -> 2600000
A22: Ejecutivo de ventas | B22: 1230000 | C22: =0.258*B22 -> 317340 | D22: 2 | E22: =C22+B22 -> 1547340 | F22: =B22*D22 -> 2460000
A23: Responsable logistica | B23: 2000000 | C23: =0.258*B23 -> 516000 | D23: 1 | E23: =C23+B23 -> 2516000 | F23: =B23*D23 -> 2000000
A24: Encargado posventa | B24: 1230000 | C24: =0.258*B24 -> 317340 | D24: 1 | E24: =C24+B24 -> 1547340 | F24: =B24*D24 -> 1230000
A25: Peones de carga y decarga - Depósito | B25: 945600 | C25: =0.258*B25 -> 243964.8 | D25: 2 | E25: =C25+B25 -> 1189564.8 | F25: =B25*D25 -> 1891200
A26: Gerente de produccion | B26: 2580000 | C26: =0.258*B26 -> 665640 | D26: 1 | E26: =C26+B26 -> 3245640 | F26: =B26*D26 -> 2580000
... A28: Responsable de prog de maquinas | B28: 950000 | C28: =0.258*B28 -> 245100 | D28: 1 | E28: =C28+B28 -> 1195100 | F28: =B28*D28 -> 950000
A29: Responsable de HSE y calidad | B29: 1450000 | C29: =0.258*B29 -> 374100 | D29: 1 | E29: =C29+B29 -> 1824100 | F29: =B29*D29 -> 1450000 | H29: Contribuciones | I29: ART | J29: Total
A30: Encargado de mantenimiento | B30: 1500000 | C30: =0.258*B30 -> 387000 | D30: 1 | E30: =C30+B30 -> 1887000 | F30: =B30*D30 -> 1500000 | H30: =16+2+6+1.5+0.3 -> 25.8 | I30: 4 | J30: =I30+H30 -> 29.8
A37: TOTAL | B37: =SUM(B14:B30) -> 27716600 | C37: =SUM(C14:C30) -> 7275682.8
C39: Aguinaldo | D39: Sueldo Anual | E39: Total
A40: Producción | B40: =SUM(D26:D30) -> 16 | C40: =SUM(F26:F30)+F14/3 -> 17936000 | D40: =(SUM(E26:E30)+E14/3)*12 -> 127124448 | E40: =C40+D40 -> 145060448
A41: Administración | B41: =SUM(D17:D20) -> 4 | C41: =SUM(F17:F20)+F14/3 -> 8490000 | D41: =(SUM(E27:E37)+E17/3)*12 -> 84960288 | E41: =C41+D41 -> 93450288
A42: Comercial | B42: =SUM(D21:D24) -> 5 | C42: =SUM(F21:F24)+F14/3 -> 9330000 | D42: =(SUM(E28:E38)+E18/3)*12 -> 65919200 | E42: =C42+D42 -> 75249200
A43: Total Personal | B43: =SUM(B40:B42) -> 25 | C43: =SUM(C40:C42) -> 35756000 | D43: =SUM(D40:D42) -> 278003936 | E43: =C43+D43 -> 313759936
B45: Salarios Promedio Bumeran | C45: https://www.bumeran.com.ar/salarios
B46: Salarios Reportados | C46: cuantogano.com/sueldos/logistica.html
A48: MANO OBRA DIRECTA:
A49: Operarios (12) + cargas y aguinaldo
A51: Amortizaciones | C51: años 1/3 | D51: Años 4/5
A52: Alicuota Anual | C52: ='E-Inv AF y Am'!D54 -> 1.3657937e+08 | D52: ='E-Inv AF y Am'!E54 -> 1.3657937e+08
A53: Area de producción le corresponde de todos los rubros: | C53: 0.9
A55: Tasas e impuestos PRODUCCIÓN:
A57: Tasa municipal anual | B57: 0.015 | C57: Del valor del inmueble. Corresponde al 90% del area de produccion
A58: Impuesto inmobiliario anual | B58: 0.01 | C58: Del valor del inmueble. Corresponde al 90% del area de produccion
A60: Gasto anual | B60: ='E-Inv AF y Am'!B48*(B58+B57)*C53 -> 21937500
A64: Materiales COMERCIALIZACION y ADMINISTRACION:
B66: Año 1 | D66: Año 2 al 5
A67: Materiales | B67: ADMIN | C67: COMER | D67: ADMIN | E67: COMER
A68: Papelería e Utiles | B68: =D41*0.03 -> 2548808.6 | C68: =D42*0.03 -> 1977576 | D68: =B68 -> 2548808.6 | E68: =C68 -> 1977576
A69: Artículos de Tocador y Limpieza | B69: =D41*0.02 -> 1699205.8 | C69: =D42*0.02 -> 1318384 | D69: =B69 -> 1699205.8 | E69: =C69 -> 1318384
A70: Embalaje | B70: 0 | C70: =1000*'C. Aux. Inv AT'!D5 -> 36532000 | D70: 0 | E70: ='C. Aux. Inv AT'!E5*1000 -> 44800000
A71: Total | B71: =SUM(B68:B70) -> 4248014.4 | C71: =SUM(C68:C70) -> 39827960 | D71: =SUM(D68:D70) -> 4248014.4 | E71: =SUM(E68:E70) -> 48095960
A73: Para articulos de limpieza se toma el 2% de los sueldos de cada sector
A74: Para la papelería e útiles se tomará un 3% de los sueldos de cada sector
A75: Para el empaque se considera un gasto de $1000 por válvula
A77: Gastos Vários Administración:
C78: Año 1 | D78: Año 2 al 5
A79: Implementacion ERP | B79: 30000000 | C79: =B79 -> 30000000 | D79: 0
A80: Mantenimiento ERP | B80: 2000000 | C80: =B80*12 -> 24000000 | D80: =C80 -> 24000000
A81: Capacitaciones | B81: =50000*B41 -> 200000 | C81: =B81 -> 200000 | D81: =C81 -> 200000 | E81: $50.000 por empleado
A82: Viáticos | B82: =0.002*E41 -> 186900.58 | C82: =B82 -> 186900.58 | D82: =C82 -> 186900.58 | E82: 0,2% del salario
B83: Total | C83: =SUM(C79:C82) -> 54386901 | D83: =SUM(D79:D82) -> 24386901
A85: Gastos Vários Comercializacion:
C86: Año 1 | D86: Año 2 al 5
A87: Capacitaciones | B87: =50000*B42 -> 250000 | C87: =B87 -> 250000 | D87: =C87 -> 250000 | E87: $50.000 por empleado
A88: Viáticos | B88: =0.05*E42 -> 3762460 | C88: =B88 -> 3762460 | D88: =C88 -> 3762460 | E88: 5% del salario (potenciales viajes aéreos)
A89: Participación en Ferias | B89: =3500*InfoInicial!B31 -> 4550000 | C89: =B89 -> 4550000 | D89: =C89 -> 4550000 | E89: https://www.thaiscorp.com/seguritec/en/exhibidor/costos?utm_source=chatgpt.com
A90: Anuncios en Revistas | B90: =1700*InfoInicial!B31 -> 2210000 | C90: =B90 -> 2210000 | D90: =C90 -> 2210000 | E90: https://valve-world-americas.com/advertising/magazine/?utm_source=chatgpt.com
B91: Total | C91: =SUM(C87:C90) -> 10772460 | D91: =SUM(D87:D90) -> 10772460
A94: Imputaciones de amortizaciones de Activo Fijo por Sector:
B96: Sector | C96: Alicuota | D96: Amortizacion
B97: Producción | C97: 0.9 | D97: ='E-Inv AF y Am'!$D$59*C97 -> 1.9638391e+08
B98: Administracion | C98: 0.05 | D98: ='E-Inv AF y Am'!$D$59*C98 -> 10910217
B99: Comercializacion | C99: 0.05 | D99: ='E-Inv AF y Am'!$D$59*C99 -> 10910217
A101: Costos de logística y distribución:
C102: Cuota | D102: Año 1 | E102: Año 2 al 5
B103: Gestión de inventarios | C103: 0.005 | D103: =C103*O5 -> 20092600 | E103: =C103*P5 -> 24640000 | F103: Consideramos un 0,5% de las ventas anuales
B104: Fletes | C104: =12500/50 -> 250 | D104: =C104*O4 -> 9133000 | E104: =C104*P4 -> 11200000 | F104: Consideramos el precio del flete dividido una cantidad promedio de 50 valvulas por flete
C105: Total | D105: =D104+D103 -> 29225600 | E105: =E104+E103 -> 35840000
F106: https://www.fletpack.com.ar/precios.html
A110: Consumo energético:
B112: consumo | D112: cantidad | E112: potencia | F112: consumo anual
A113: Ventiladores | B113: 0.2 | C113: kwh | D113: 3 | E113: =B113*D113 -> 0.6 | F113: =B113*A132 -> 404.8 | G113: kwh/año
A114: Teléfonos | B114: 0.04 | C114: kwh | D114: 14 | E114: =B114*D114 -> 0.56 | F114: =B114*A133 -> 20.24 | G114: kwh/año
A115: Dispenser de agua | B115: 0.01 | C115: kwh | D115: 4 | E115: =B115*D115 -> 0.04 | F115: =B115*A131 -> 87.6 | G115: kwh/año
A116: Microondas | B116: 1 | C116: kwh | D116: 4 | E116: =B116*D116 -> 4 | F116: =B116*A133 -> 506 | G116: kwh/año
A117: Heladera | B117: 0.04 | C117: kwh | D117: 1 | E117: =B117*D117 -> 0.04 | F117: =B117*A131 -> 350.4 | G117: kwh/año
A118: Cafetera | B118: 0.9 | C118: kwh | D118: 4 | E118: =B118*D118 -> 3.6 | F118: =B118*A133 -> 455.4 | G118: kwh/año
A119: Aire acondicionado | B119: 2 | C119: kwh | D119: 5 | E119: =B119*D119 -> 10 | F119: =B119*A131 -> 17520 | G119: kwh/año
A120: Computadoras | B120: 2.2 | C120: kwh | D120: 15 | E120: =B120*D120 -> 33 | F120: =B120*A133 -> 1113.2 | G120: kwh/año
A121: Impresora | B121: 0.3 | C121: kwh | D121: 4 | E121: =B121*D121 -> 1.2 | F121: =B121*A133 -> 151.8 | G121: kwh/año
A123: Torno CNC | B123: 24 | C123: kwh | D123: 6 | E123: =B123*D123 -> 144 | F123: =E123*$A$131 -> 1261440 | G123: kwh/año
A124: Brazo robotico soldadura | B124: 1.25 | C124: kwh | D124: 1 | E124: =B124*D124 -> 1.25 | F124: =E124*$A$131 -> 10950 | G124: kwh/año
A125: Brazo robotico pulido | B125: 1 | C125: kwh | D125: 5 | E125: =B125*D125 -> 5 | F125: =E125*$A$131 -> 43800 | G125: kwh/año
A126: Banco de pruebas | B126: 2.2 | C126: kwh | D126: 3 | E126: =B126*D126 -> 6.6 | F126: =E126*$A$131 -> 57816 | G126: kwh/año
A127: Sierra de cinta | B127: 2 | C127: kwh | D127: 2 | E127: =B127*D127 -> 4 | F127: =E127*$A$131 -> 35040 | G127: kwh/año
A128: Posicionador | B128: 1 | C128: kwh | D128: 1 | E128: =B128*D128 -> 1 | F128: =E128*$A$131 -> 8760 | G128: kwh/año
E129: =SUM(E114:E128) -> 214.29 | F129: =SUM(F113:F128) -> 1438415.4 | G129: kwh/año
A131: 8760 | B131: hs/año
A132: 2024 | B132: hs/año - 8hs diarias | G132: Cargo fijo | H132: 135686.3 | J132: =H132 -> 135686.3
A133: 506 | B133: hs/año - promedio | G133: Costo potencia contratada | H133: 14305.11 | I133: 200 | J133: =H133*I133 -> 2861022
G134: Costo potencia adquirida | H134: 6391.09 | I134: =C138 -> 681.06792 | J134: =H134*I134 -> 4352766.4
...

Sheet AUX - COSTO DE PRODUC
A1: MANO DE OBRA
A2: cant de operarios | B2: 12
A3: JORNAL | B3: ='C. Aux. Costos'!B27/8/30 -> 3616.6667 | C3: $/hr
A4: CARGAS SOCIALES | B4: 25,8% Sobre el jornal básico
A5: adicionales (aguinaldos, premios, posibles horas extra) | B5: 50% sobre el básico
A7: horas trabajadas al año | B7: 1880 | C7: horas/año
A9: Costo por hora | B9: =B3+B3*0.258+B3*0.5 -> 6358.1 | C9: $/hr
A11: AÑOS RÉGIMEN
A12: TOTAL MdO | B12: =B7*B9*B2 -> 1.4343874e+08
A13: $/PT | B13: =B12/44800 -> 3201.7575
A15: AÑO 1 | B15: PRODUCCION AÑO 1 | C15: 36532
A17: Estimamos un 90% del total de MdO anual en régimen | B17: =B12*0.9 -> 1.2909486e+08
A19: MANO DE OBRA NETA | B19: =C15*B13 -> 1.169666e+08
A20: Volumen de MC y SE | B20: 794 | C20: PT
A21: MANO DE OBRA EN MC Y SE | B21: =B13*B20 -> 2542195.5
A24: TOTAL MDO AÑO 1 ESPERADO: | B24: =B19+B21 -> 1.195088e+08
A25: EXCESO DE MDO POR PEM: | B25: =B17-B19 -> 12128257
A28: GASTOS DE FABRICACIÓN
A29: AMORTIZACIONES DEL ÁREA DE FABRICACIÓN
A30: Máquinas operativas | B30: 1
A31: RODADOS Y EQUIPOS AUX | B31: 0
A32: MUEBLES Y ÚTILES | B32: 0.15
A33: IMPREVISTOS | B33: 0
A34: CARGOS DIFERIDOS | B34: ='E-Inv AF y Am'!C33/'E-Inv AF y Am'!B56 -> 0.84646898
A36: AÑOS 4/5
A37: Imputación anual | B37: ='E-Inv AF y Am'!E50+$B$32*'E-Inv AF y Am'!E52+$B$34*'E-Inv AF y Am'!E56 -> 1.4929805e+08
A39: AÑOS 1/3
A40: Imputación anual | B40: ='E-Inv AF y Am'!D50+$B$32*'E-Inv AF y Am'!D52+$B$34*'E-Inv AF y Am'!D56 -> 1.4929805e+08
A42: MANO DE OBRA INDIRECTA | B42: SALARIO MENSUAL (Con Cargas sociales) | C42: ASIGNACIÓN A PRODUCCIÓN | D42: TOTALES
A43: DIRECTOR GENERAL (1/3) | B43: ='C. Aux. Costos'!E14 -> 4049760 | C43: =1/3 -> 0.33333333 | D43: =C43*B43*12 -> 16199040
A44: GERENTE DE PRODUCCIÓN | B44: ='C. Aux. Costos'!E26 -> 3245640 | C44: 1 | D44: =C44*B44*12 -> 38947680
A45: RESPONSABLE DE PROGRAMACIÓN | B45: ='C. Aux. Costos'!E28 -> 1195100 | C45: 1 | D45: =C45*B45*12 -> 14341200
A46: RESPONSABLE CALIDAD Y SeH | B46: ='C. Aux. Costos'!E29 -> 1824100 | C46: 1 | D46: =C46*B46*12 -> 21889200
A47: ENCARGADO DE MANTENIMIENTO | B47: ='C. Aux. Costos'!E30 -> 1887000 | C47: 1 | D47: =C47*B47*12 -> 22644000
A48: PORTERÍA Y VIGILANCIA | B48: ='C. Aux. Costos'!E15*'C. Aux. Costos'!D15 -> 2536128 | C48: =1/3 -> 0.33333333 | D48: =C48*B48*12 -> 10144512
A49: PERSONAL DE LIMPIEZA | B49: ='C. Aux. Costos'!E16*'C. Aux. Costos'!D16 -> 2962590 | C49: =1/3 -> 0.33333333 | D49: =C49*B49*12 -> 11850360
C51: TOTAL | D51: =SUM(D43:D49) -> 136015992
A53: GASTOS EN MATERIALES DE FABRICACIÓN | D53: Total de la base año 1 | E53: Total base años regimen | F53: total año 1 | G53: total años regimen | H53: ESPECÍFICOS AÑO 1 | I53: ESPECÍFICOS REGIMEN
A54: Materiales para el mantenimiento | B54: 0.01 | C54: Del valor de los BdU que requieren mantenimiento | D54: ='E-Inv AF y Am'!D11+'E-Inv AF y Am'!D13+'E-Inv AF y Am'!B14+'E-Inv AF y Am'!B16*0.15+'E-Inv AF y Am'!B17/3+'E-Inv AF y Am'!B18/3 -> 8.0658396e+08 | E54: =D54 -> 8.0658396e+08 | F54: =D54*B54 -> 8065839.6 | G54: =E54*B54 -> 8065839.6 | H54: =F54/'CÁLCULOS MP'!$B$89 -> 217.94265 | I54: =G54/'CÁLCULOS MP'!$B$90 -> 180.04106
A55: Repuestos | B55: 0.016 | C55: valor de maquinaria | D55: ='E-Inv AF y Am'!D11+'E-Inv AF y Am'!D13 -> 790640500 | E55: =D55 -> 790640500 | F55: =D55*B55 -> 12650248 | G55: =E55*B55 -> 12650248 | H55: =F55/'CÁLCULOS MP'!$B$89 -> 341.81545 | I55: =G55/'CÁLCULOS MP'!$B$90 -> 282.37161
A56: Materiales en producción | B56: 0.02 | C56: Gasto en MP | D56: ='E-Costos'!B7 -> 1.4898176e+09 | E56: ='E-Costos'!C7 -> 1.4444621e+09 | F56: =D56*B56 -> 29796351 | G56: =E56*B56 -> 28889242 | H56: =F56/'CÁLCULOS MP'!$B$89 -> 805.11096 | I56: =G56/'CÁLCULOS MP'!$B$90 -> 644.84915
A57: Materiales usados por el personal | B57: 0.03 | C57: del gasto del personal en el área de producción | D57: ='E-Costos'!B8+'E-Costos'!B11 -> 2.6511085e+08 | E57: ='E-Costos'!C8+'E-Costos'!C11 -> 279454728 | F57: =D57*B57 -> 7953325.6 | G57: =E57*B57 -> 8383641.8 | H57: =F57/'CÁLCULOS MP'!$B$89 -> 214.90247 | I57: =G57/'CÁLCULOS MP'!$B$90 -> 187.13486
E59: TOTAL | F59: =SUM(F54:F57) -> 58465765 | G59: =SUM(G54:G57) -> 57988971
A60: PARA LA PEM CONSIDERAMOS UN % DE: | B60: 0.1 | C60: A APLICAR SOBRE LOS MATERIALES DEL AÑO 1

Sheet CÁLCULOS MP
G1: Tipo de cambio | H1: =InfoInicial!B31 -> 1300
A2: Componente | B2: Material | C2: COSTO | D2: um | E2: Uso en | F2: Link
A3: Barra de Acero Inoxidable 304 d28,6 | B3: Acero Inoxidable 304 | C3: =(125775/50)/H1 -> 1.935 | D3: USD/KG | E3: Maneta | F3: https://www.famiq.com.ar/producto/?sub-familia%5B%5D=barras-redondas&sub-familia%5B%5D=barras-cuadradas&sub-familia%5B%5D=barras-hexagonales&nodo=3&bloqueHome=1&caracteristica_calidad=304-304l&caracteristica_diametro-mm%5B%5D=28-6&tipoCatalogo=normal&caracteristica_forma=redonda
A4: Perno con Cabezal para Palanca | B4: Acero Inoxidable 304 | D4: USD/UN | E4: Palanca maneta | F4: https://articulo.mercadolibre.com.ar/MLA-2127138792-perno-de-carro-de-acero-inoxidable-x-2-pulgadas-color-50-_JM#polycard_client=search-nordic&search_layout=stack&position=6&type=item&tracking_id=c9927400-b1e2-4bb3-9053-b564420e0969
A5: Barra de Acero Inoxidable 304 d9,52 | B5: Acero Inoxidable 304 | C5: =6/1.5 -> 4 | D5: USD/KG | E5: Palanca maneta | F5: https://www.famiq.com.ar/producto/?sub-familia=barras-redondas&nodo=S155&caracteristica_diametro-mm%5B%5D=9-52&caracteristica_calidad=304-304l&tipoCatalogo=resumen
A6: Resorte Maneta | B6: Acero Inoxidable 302 | C6: =(12000/4)/H1 -> 2.3076923 | D6: USD/UN | E6: Maneta | F6: https://www.mercadolibre.com.ar/resortes-acero-inoxidable-8mm-x-36-mm-alamb-06-pack-x-4-un/up/MLAU2133390517#polycard_client=search-nordic&wid=MLA1454465469&search_layout=stack&position=9&type=product&tracking_id=4c9ff310-1477-44f8-ab8d-150edac1f232&sid=search
A7: Casquilo de Maneta | B7: Acero Inoxidable 304 | C7: =3.68/2 -> 1.84 | D7: USD/UN | E7: Maneta | F7: https://www.famiq.com.ar/producto/?nombreEs=CASQUILLO%20PARA%20MANETA%202%20POSICIONES%20NACIONAL%20304%2025.4%20a%20101.6%20mm&sub-familia=repuestos-de-valvulas-mariposa&tipoCatalogo=resumen
A8: Tapón Plástico Maneta | B8: PTFE con base EPDM | C8: =1.3*1.16/2 -> 0.754 | D8: USD/UN | E8: Maneta | F8: https://repuestos.caldereriamanzano.net/producto/tapon-para-maneta-de-valvula-ref-014736/?add-to-cart=5490
A9: Tapón de Buje | B9: PTFE con base EPDM | C9: 0.27 | D9: usd/un | F9: Consultado en Famiq | G9: 6133
A10: Buje Plástico para Clapeta | B10: PEEK (Polieter Éter Cetona) | C10: 0.27 | D10: USD/UN | F10: Consultado en Famiq | G10: 6141
A11: Forja de Tapa para Válvula | B11: Acero Inoxidable 304 | C11: 4 | D11: USD/KG | F11: Consultado en Famiq | G11: 3042
A12: Junta O-Ring | B12: Vitón(FMK) | C12: =6/2 -> 3 | D12: USD/UN | F12: https://www.famiq.com.ar/producto/?nombreEs=313224&sub-familia=junta-valvula-mariposa-mecanizada&tipoCatalogo=resumen
A13: Bulones 304 (Allen 6mm) | B13: Acero Inoxidable 304 | C13: =46.42/100/2 -> 0.2321 | D13: USD/UN | F13: https://www.famiq.com.ar/producto/?nombreEs=300468&sub-familia=allen-metricos-cabeza-cilindrica&tipoCatalogo=resumen
A14: Bulones 304 (Tuerca 6mm) | B14: Acero Inoxidable 305 | C14: =73.37/500/2 -> 0.07337 | D14: USD/UN | F14: https://www.famiq.com.ar/producto/?nombreEs=322124&sub-familia=tuercas-metricas&tipoCatalogo=resumen
A15: Arandelas 304 | B15: Acero Inoxidable 304 | C15: =52.61/200/2 -> 0.131525 | D15: USD/UN | F15: https://www.famiq.com.ar/producto/?nombreEs=300667&sub-familia=arandelas-planas&tipoCatalogo=resumen
A16: Forja de Clapeta | B16: Acero Inoxidable 304 | C16: 3 | D16: USD/KG | F16: Consultado en Famiq | G16: 8395
A18: TODOS NUESTROS DESPERDICIOS SON NO RECUPERABLES | D18: A LOS PRECIOS CONSULTADOS EN FAMIQ DESCONTAMOS UN MARGEN APROXIMADO DE 50% PARA MP Y DEL 100% PARA REPUESTOS
A20: CONSUMOS MP EN AÑOS EN RÉGIMEN
A21: FORJA PARA CUERPO
A22: Sección operativa | B22: Alimentacion (KG) | C22: Agregado | D22: Desperdicios | F22: Producción (KG)
D23: Recuperable | E23: No recuperable
A24: Mecanizado de cuerpo | B24: 67968.61 | C24: - | D24: - | E24: 0.15 | F24: 57773.32
A25: Rebabado de cuerpo | B25: 57773.32 | C25: - | D25: - | E25: 0.003 | F25: 44800/0,98*1.8*0.7=57600
A27: MP | C27: PRECIO UNIT (USD/KG) | D27: NECESIDAD | E27: TOTAL ANUAL
A28: Forja de Tapa para Válvula | B28: Acero Inoxidable 304 | C28: 4 | D28: =B24 -> 67968.61 | E28: =D28*C28 -> 271874.44 | F28: USD
A30: FORJA PARA CLAPETA
A31: Sección operativa | B31: Alimentacion (KG) | C31: Agregado | D31: Desperdicios | F31: Producción (KG)
D32: Recuperable | E32: No recuperable
A33: Mecanizado de forja y clapeta | B33: 4889.23 | C33: - | D33: - | E33: 0.15 | F33: 4155.84
A34: Pulido de clapeta | B34: 4122.53 | C34: - | D34: - | E34: 0.002 | F34: 4114.29
A36: MP | C36: PRECIO UNIT (USD/KG) | D36: NECESIDAD | E36: TOTAL ANUAL
A37: Forja de Clapeta | B37: Acero Inoxidable 304 | C37: 3 | D37: =B33 -> 4889.23 | E37: =D37*C37 -> 14667.69 | F37: USD
A39: BARRA PARA MANETA
A40: Sección operativa | B40: Alimentacion (KG) | C40: Agregado | D40: Desperdicios | F40: Producción (KG)
D41: Recuperable | E41: No recuperable
A42: Corte de barra | B42: 10569.508 | E42: 0.02 | F42: 10358.12
A43: Mecanizado de maneta | B43: 10358.12 | C43: - | D43: - | E43: 0.2 | F43: 8286.49
A44: Armado de maneta | B44: 8286.49 | C44: - | D44: - | E44: - | F44: 8286.49
A45: Soldadura de maneta | B45: 8286.49 | C45: - | D45: - | E45: - | F45: 8286.49
A46: Desbaste de maneta | B46: 8286.49 | C46: - | D46: - | E46: 0.005 | F46: 8245.06
A47: Pulido de maneta | B47: 8245.06 | C47: - | D47: - | E47: 0.002 | F47: 8228.57
A49: MP | C49: PRECIO UNIT (USD/KG) | D49: NECESIDAD | E49: TOTAL ANUAL
A50: Barra de Acero Inoxidable 304 d28,6 | B50: Acero Inoxidable 304 | C50: 6 | D50: =B42 -> 10569.508 | E50: =D50*C50 -> 63417.046 | F50: USD
A52: BARRA PARA EJE
A53: Sección operativa | B53: Alimentacion (KG) | C53: Agregado | D53: Desperdicios | F53: Producción (KG)
D54: Recuperable | E54: No recuperable
A55: Corte de barra | B55: 9898.0331 | E55: 0.02 | F55: 9700.07
A56: Mecanizado de eje | B56: 9700.07 | C56: - | D56: - | E56: 0.15 | F56: 8245.06
A57: Pulido de eje | B57: 8245.06 | C57: - | D57: - | E57: 0.002 | F57: 8228.57
A59: MP | C59: PRECIO UNIT (USD/KG) | D59: NECESIDAD | E59: TOTAL ANUAL
A60: Barra de Acero Inoxidable 304 d9,52 | B60: Acero Inoxidable 304 | C60: 6 | D60: =B55 -> 9898.0331 | E60: =D60*C60 -> 59388.198 | F60: USD
E64: USO NECESIDADES ANUALES NETAS PARA ESTAS PIEZAS YA QUE INCLUSO SI SON DESCARTADAS POR EL CC, SE PUEDE DESARMAR LA VÁLVULA Y REUTILIZARSE. Si la pieza estuviera defectuosa se reclamaría al proveedor
A65: Nivel | B65: Componente | C65: Material | D65: Cantidad | E65: Necesidad anual según plan de ventas | F65: costo unitario | G65: COSTO TOTAL ANUAL
A66: 3 | B66: Perno con Cabezal para Palanca | C66: Acero Inoxidable 304 | D66: 1 | E66: 44800 | F66: =C3 -> 1.935 | G66: =F66*E66 -> 86688
A67: 2 | B67: Resorte Maneta | C67: Acero Inoxidable 302 | D67: 1 | E67: 44800 | F67: =C6 -> 2.3076923 | G67: =F67*E67 -> 103384.62
A68: 2 | B68: Casquilo de Maneta | C68: Acero Inoxidable 304 | D68: 1 | E68: 44800 | F68: =C7 -> 1.84 | G68: =F68*E68 -> 82432
A69: 2 | B69: Tapón Plástico Maneta | C69: PTFE con base EPDM | D69: 1 | E69: 44800 | F69: =C8 -> 0.754 | G69: =F69*E69 -> 33779.2
A70: 2 | B70: Etiqueta Maneta | D70: 1 | E70: 44800 | F70: =0 -> 0 | G70: =F70*E70 -> 0
A71: 2 | B71: Tapón de Buje | C71: PTFE con base EPDM | D71: 2 | E71: 89600 | F71: =C9 -> 0.27 | G71: =F71*E71 -> 24192
A72: 2 | B72: Buje Plástico para Clapeta | C72: PEEK (Polieter Éter Cetona) | D72: 2 | E72: 89600 | F72: =C10 -> 0.27 | G72: =F72*E72 -> 24192
A73: 2 | B73: Junta O-Ring | C73: Vitón(FMK) | D73: 2 | E73: 89600 | F73: =C12 -> 3 | G73: =F73*E73 -> 268800
A74: 2 | B74: Bulones 304 | C74: Acero Inoxidable 304 | D74: 4 | E74: 179200 | F74: =C13+C14 -> 0.30547 | G74: =F74*E74 -> 54740.224
A75: 2 | B75: Arandelas 304 | C75: Acero Inoxidable 304 | D75: 4 | E75: 179200 | F75: =C15 -> 0.131525 | G75: =F75*E75 -> 23569.28
A76: 2 | B76: Etiqueta Tapa | D76: 1 | E76: 44800 | F76: 0 | G76: =F76*E76 -> 0
A78: TOTAL MP: | B78: =E28+E37+E50+E60+SUM(G66:G76) -> 1111124.7
A80: DESPERDICIOS RECUPERABLES: | C80: 0
A81: DESPERDICIOS NO RECUPERABLES Y VENDIBLES: | C81: =B24-57600+B33-F34+B42-F47+B55-F57 -> 15153.951 | D81: KG | F81: https://supraciclaje.com/precios-hoy/
F82: Precio aprox de chatarra acero inox
A83: ingreso por chatarra años en régimen | C83: =C81*F83 -> 7576.9754 | D83: USD | F83: 0.5 | G83: USD/KG
A86: CONSUMOS MP EN AÑO 1 | E86: COSTO específico MP
E87: =B78/B90 -> 24.80189 | F87: USD
A88: Producción por año
A89: Producción Año 1 | B89: 37009 | C89: unid
A90: Producción Año 2 - n | B90: 44800 | C90: unid
A92: Stock promedio PT | B92: 447 | C92: unidades
A94: Ventas por año
A95: Año 1 | B95: 36532
A96: Año 2 - n | B96: 44800
A98: Materia prima consumida para año 1
A99: Consumo MP para mercadería en curso | B99: 794 | E99: CONSUMO NORMAL MP AÑO 1 = PRODUCCIÓN AÑO 1 * COSTO UNIT MP
A100: Consumo MP en PPM | B100: 10714.6 | E100: =E87*B89 -> 917893.17 | F100: USD
A101: Consumo MP resto del año | B101: 34698.1
A102: Consumo MP año 1 | B102: =SUM(B99:B101) -> 46206.7 | C102: (mc, ppm, produc, etc) | E102: CONSUMO REAL AÑO 1: | F102: =(B102)*E87 -> 1146013.5 | G102: USD
A103: Volumen producción año 1 | B103: 37009
A104: Desperdicios no recuperables año 1 | B104: 8404 | E104: CONSUMO EN EXCESO POR PEM: | F104: =B100*E87 -> 265742.34 | G104: USD | H104: ESTO SE MANDA AL AF
E106: CONSUMO POR GEN. STOCK DE PT | F106: 0 | H106: Ya está contemplado en el volumen de produccion del año 1
A107: Para el año 2 - n: | E107: CONSUMO POR GEN. STOCK DE MC Y SE: | F107: =B99*E87 -> 19692.701 | G107: USD | H107: PERO NO VA AL COSTO DE PRODUCCIÓN
A109: Materia prima consumida para año 2 - n | E109: USO DEL STOCK DE AÑO 0: | F109: 0 | G109: USD | H109: no se considera para el costo el uso del stock
A110: Volumen de producción | B110: 44.800 u
A111: Consumo mp | B111: 53.204 u eq PT
A112: Desperdicios no recuperables | B112: 8.404 u EQ pt | G112: lo de la PEM viene en inversión de AT
G113: ademas, el stock de PT no va aparte, ya esta considerado en el hecho de que producís 36655 cuando vendes36178

Sheet E-InvAT
A1: ESTA PLANILLA PUEDE SER UTILIZADA SOLAMENTE PARA EL TRABAJO PRACTICO: | E1: =InfoInicial!E1 -> 6
A3: INVERSIONES EN ACTIVO DE TRABAJO
A4: Rubros | B4: Año 0 | C4: Año 1 | D4: Año 2 | E4: Año 3 | F4: Año 4 | G4: Año 5
A5: 1. Activo de Trabajo: (valor contable)
A6: a) Disponibilidad Mínima en Caja y Bancos: | B6: =C6*0.8 -> 63673280 | C6: ='C. Aux. Inv AT'!D6*0.02 -> 79591600 | D6: ='C. Aux. Inv AT'!E6*0.02 -> 89600000 | E6: ='C. Aux. Inv AT'!F6*0.02 -> 89600000 | F6: ='C. Aux. Inv AT'!G6*0.02 -> 89600000 | G6: ='C. Aux. Inv AT'!H6*0.02 -> 89600000
A7: b) Crédito por Ventas: | C7: ='C. Aux. Inv AT'!D6*30/365 -> 3.2708877e+08 | D7: ='C. Aux. Inv AT'!E6*30/365 -> 3.6821918e+08 | E7: ='C. Aux. Inv AT'!F6*30/365 -> 3.6821918e+08 | F7: ='C. Aux. Inv AT'!G6*30/365 -> 3.6821918e+08 | G7: ='C. Aux. Inv AT'!H6*30/365 -> 3.6821918e+08
A9: c) Bienes de cambio:
A10: Stock de materias prima: | B10: ='C. Aux. Inv AT'!C15 -> 3.4547793e+08 | C10: ='C. Aux. Inv AT'!D15 -> 4.8679663e+08 | D10: ='C. Aux. Inv AT'!E15 -> 4.8679663e+08 | E10: ='C. Aux. Inv AT'!F15 -> 4.8679663e+08 | F10: ='C. Aux. Inv AT'!G15 -> 4.8679663e+08 | G10: ='C. Aux. Inv AT'!H15 -> 4.8679663e+08
A11: Stock de materiales: | C11: ='C. Aux. Inv AT'!D23 -> 32905880 | D11: ='C. Aux. Inv AT'!E23 -> 33356484 | E11: ='C. Aux. Inv AT'!F23 -> 33356484 | F11: ='C. Aux. Inv AT'!G23 -> 33356484 | G11: ='C. Aux. Inv AT'!H23 -> 33356484
A12: Mercadería en curso y semielaborada | C12: ='E-Costos'!B43 -> 36298795 | D12: ='E-Costos'!C43 -> 35684429 | E12: ='E-Costos'!D43 -> 35684429 | F12: ='E-Costos'!E43 -> 35684429 | G12: ='E-Costos'!F43 -> 35684429
A13: Stock de elaborados: | C13: ='C. Aux. Inv AT'!D30 -> 21531998 | D13: ='C. Aux. Inv AT'!E30 -> 21545443 | E13: ='C. Aux. Inv AT'!F30 -> 21538902 | F13: ='C. Aux. Inv AT'!G30 -> 21538902 | G13: ='C. Aux. Inv AT'!H30 -> 21538902
A15: d) Total Activo de Trabajo, sin IVA: | B15: =SUM(B5:B14) -> 4.0915121e+08 | C15: =SUM(C5:C14) -> 9.8421367e+08 | D15: =SUM(D5:D14) -> 1.0352022e+09 | E15: =SUM(E5:E14) -> 1.0351956e+09 | F15: =SUM(F5:F14) -> 1.0351956e+09 | G15: =SUM(G5:G14) -> 1.0351956e+09
A16: 2. Menos:
A17: Amortizaciones en Mercadería en proceso | C17: ='E-Costos'!B34 -> 2084275.6 | D17: ='E-Costos'!C34 -> 1740277 | E17: ='E-Costos'!D34 -> 1740277 | F17: ='E-Costos'!E34 -> 1740277 | G17: ='E-Costos'!F34 -> 1740277
A18: Amortizaciones en Stock de elaborado | C18: ='C. Aux. Inv AT'!D40 -> 1897402.5 | D18: ='C. Aux. Inv AT'!E40 -> 1571095 | E18: ='C. Aux. Inv AT'!F40 -> 1571095 | F18: ='C. Aux. Inv AT'!G40 -> 1571095 | G18: ='C. Aux. Inv AT'!H40 -> 1571095
A19: Utilidades en Crédito por ventas | C19: =C7*'E-Costos'!B143 -> 89626648 | D19: =D7*'E-Costos'!C143 -> 1.0448391e+08 | E19: =E7*'E-Costos'!D143 -> 1.0451231e+08 | F19: =F7*'E-Costos'!E143 -> 1.0451202e+08 | G19: =G7*'E-Costos'!F143 -> 1.0451202e+08
A20: Amortizaciones en Crédito por ventas | C20: =('E-Inv AF y Am'!$D$59-C18-C17)*30/365 -> 17607342 | D20: =('E-Inv AF y Am'!$D$59-D18-D17)*30/365 -> 17662436 | E20: =('E-Inv AF y Am'!$D$59-E18-E17)*30/365 -> 17662436 | F20: =('E-Inv AF y Am'!$E$59-F18-F17)*30/365 -> 17662436 | G20: =('E-Inv AF y Am'!$E$59-G18-G17)*30/365 -> 17662436
A22: 3. Inversiones en Activo de Trabajo, sin IVA | B22: =B15-SUM(B17:B20) -> 4.0915121e+08 | C22: =C15-SUM(C17:C20) -> 8.72998e+08 | D22: =D15-SUM(D17:D20) -> 9.0974445e+08 | E22: =E15-SUM(E17:E20) -> 9.097095e+08 | F22: =F15-SUM(F17:F20) -> 9.0970979e+08 | G22: =G15-SUM(G17:G20) -> 9.0970979e+08
A24: 4. Incrementos de Activo de Trabajo | B24: =B15 -> 4.0915121e+08 | C24: =C15-B15 -> 5.7506245e+08 | D24: =D15-C15 -> 50988494 | E24: =E15-D15 -> -6541.3555 | F24: =F15-E15 -> 0 | G24: =G15-F15 -> 0
A25: Incrementos de Inversión en Activo de Trabajo | B25: =B22 -> 4.0915121e+08 | C25: =C22-B22 -> 4.6384678e+08 | D25: =D22-C22 -> 36746447 | E25: =E22-D22 -> -34947.426 | F25: =F22-E22 -> 292.91913 | G25: =G22-F22 -> 0
A27: 5. Incrementos IVA sobre Inversiones
A28: Crédito por Ventas
A29: Bienes de cambio:
A30: Stock de materia prima | B30: =B10*InfoInicial!B3 -> 72550366 | C30: =(C10-B10)*InfoInicial!B3 -> 29676925 | D30: =(D10-C10)*InfoInicial!C3 -> 0 | E30: =(E10-D10)*InfoInicial!D3 -> 0 | F30: =(F10-E10)*InfoInicial!E3 -> 0 | G30: =(G10-F10)*InfoInicial!F3 -> 0
A31: Stock de materiales | C31: =C11*InfoInicial!$B$3 -> 6910234.8 | D31: =(D11-C11)*InfoInicial!$B$3 -> 94626.725 | E31: =(E11-D11)*InfoInicial!$B$3 -> 0 | F31: =(F11-E11)*InfoInicial!$B$3 -> 0 | G31: =(G11-F11)*InfoInicial!$B$3 -> 0
A32: Mercadería en proceso | C32: =C12*InfoInicial!$B$3 -> 7622747 | D32: =(D12-C12)*InfoInicial!$B$3 -> -129016.92 | E32: =(E12-D12)*InfoInicial!$B$3 -> 0 | F32: =(F12-E12)*InfoInicial!$B$3 -> 0 | G32: =(G12-F12)*InfoInicial!$B$3 -> 0
A33: Stock de elaborados | C33: =C13*InfoInicial!$B$3 -> 4521719.5 | D33: =(D13-C13)*InfoInicial!$B$3 -> 2823.5777 | E33: =(E13-D13)*InfoInicial!$B$3 -> -1373.6847 | F33: =(F13-E13)*InfoInicial!$B$3 -> 0 | G33: =(G13-F13)*InfoInicial!$B$3 -> 0
A34: Total incrementos IVA sobre inversiones | B34: =SUM(B30:B33) -> 72550366 | C34: =SUM(C30:C33) -> 48731627 | D34: =SUM(D30:D33) -> -31566.622 | E34: =SUM(E30:E33) -> -1373.6847 | F34: =SUM(F30:F33) -> 0 | G34: =SUM(G30:G33) -> 0
A36: 6. Incrementos Inversiones en Activo de Trabajo | B36: =B34+B25 -> 4.8170158e+08 | C36: =C34+C25 -> 5.1257841e+08 | D36: =D34+D25 -> 36714881 | E36: =E34+E25 -> -36321.111 | F36: =F34+F25 -> 292.91913 | G36: =G34+G25 -> 0

Sheet C. Aux. Inv AT
B2: Plan de Ventas:
B4: Año | C4: 0 | D4: 1 | E4: 2 | F4: 3 | G4: 4 | H4: 5
B5: Cantidades | C5: 0 | D5: 36532 | E5: 44800 | F5: 44800 | G5: 44800 | H5: 44800
B6: Ingresos | C6: 0 | D6: 3979580000 | E6: 4480000000 | F6: 4480000000 | G6: 4480000000 | H6: 4480000000
B8: Para la disponibilidad minima de caja y bancos se tomara el 2% de los ingresos esperados por el plan de ventas y, para el año 0, el 80% de la disponibilidad del año 1
B10: La materia prima y los materiales se valuan a precio de mercado:
B12: Año | C12: 0 | D12: 1 | E12: 2 | F12: 3 | G12: 4 | H12: 5
B13: Stock Promedio MP | C13: 10715 | D13: 15098 | E13: 15098 | F13: 15098 | G13: 15098 | H13: 15098
B14: Precio Unitario | C14: ='CÁLCULOS MP'!$E$87*InfoInicial!$B$31 -> 32242.458 | D14: ='CÁLCULOS MP'!$E$87*InfoInicial!$B$31 -> 32242.458 | E14: ='CÁLCULOS MP'!$E$87*InfoInicial!$B$31 -> 32242.458 | F14: ='CÁLCULOS MP'!$E$87*InfoInicial!$B$31 -> 32242.458 | G14: ='CÁLCULOS MP'!$E$87*InfoInicial!$B$31 -> 32242.458 | H14: ='CÁLCULOS MP'!$E$87*InfoInicial!$B$31 -> 32242.458
B15: Total | C15: =C13*C14 -> 3.4547793e+08 | D15: =D13*D14 -> 4.8679663e+08 | E15: =E13*E14 -> 4.8679663e+08 | F15: =F13*F14 -> 4.8679663e+08 | G15: =G13*G14 -> 4.8679663e+08 | H15: =H13*H14 -> 4.8679663e+08
B17: Para el stock de materiales se estima el consumo de 6 meses para el area de producción y de 1 mes para las áreas de administración y comercialización
B19: Año | C19: 0 | D19: 1 | E19: 2 | F19: 3 | G19: 4 | H19: 5
B20: Producción | D20: ='AUX - COSTO DE PRODUC'!F59/2 -> 29232882 | E20: ='AUX - COSTO DE PRODUC'!$G$59/2 -> 28994486 | F20: ='AUX - COSTO DE PRODUC'!$G$59/2 -> 28994486 | G20: ='AUX - COSTO DE PRODUC'!$G$59/2 -> 28994486 | H20: ='AUX - COSTO DE PRODUC'!$G$59/2 -> 28994486
B21: Comercialización | D21: ='C. Aux. Costos'!C71/12 -> 3318996.7 | E21: ='C. Aux. Costos'!$E$71/12 -> 4007996.7 | F21: ='C. Aux. Costos'!$E$71/12 -> 4007996.7 | G21: ='C. Aux. Costos'!$E$71/12 -> 4007996.7 | H21: ='C. Aux. Costos'!$E$71/12 -> 4007996.7
B22: Administración | D22: ='C. Aux. Costos'!B71/12 -> 354001.2 | E22: ='C. Aux. Costos'!$D$71/12 -> 354001.2 | F22: ='C. Aux. Costos'!$D$71/12 -> 354001.2 | G22: ='C. Aux. Costos'!$D$71/12 -> 354001.2 | H22: ='C. Aux. Costos'!$D$71/12 -> 354001.2
B23: Total | D23: =SUM(D20:D22) -> 32905880 | E23: =SUM(E20:E22) -> 33356484 | F23: =SUM(F20:F22) -> 33356484 | G23: =SUM(G20:G22) -> 33356484 | H23: =SUM(H20:H22) -> 33356484
B25: La mercaderia en curso y SE y el stock de elaborados se evalua a costo de producción:
B27: Año | C27: 0 | D27: 1 | E27: 2 | F27: 3 | G27: 4 | H27: 5
B28: Costo de prod. unit. | D28: ='E-Costos'!B124 -> 45140.456 | E28: ='E-Costos'!C124 -> 45168.644 | F28: ='E-Costos'!D124 -> 45154.93 | G28: ='E-Costos'!E124 -> 45154.93 | H28: ='E-Costos'!F124 -> 45154.93
B29: Stock promedio PT | D29: 477 | E29: 477 | F29: 477 | G29: 477 | H29: 477
B30: Costo Stock prom. PT | D30: =D28*D29 -> 21531998 | E30: =E28*E29 -> 21545443 | F30: =F28*F29 -> 21538902 | G30: =G28*G29 -> 21538902 | H30: =H28*H29 -> 21538902
B32: Para las amortizaciones:
B34: Año | C34: 0 | D34: 1 | E34: 2 | F34: 3 | G34: 4 | H34: 5
B35: Alicuota Amort. Prod | D35: ='AUX - COSTO DE PRODUC'!$B$40 -> 1.4929805e+08 | E35: ='AUX - COSTO DE PRODUC'!$B$40 -> 1.4929805e+08 | F35: ='AUX - COSTO DE PRODUC'!$B$40 -> 1.4929805e+08 | G35: ='AUX - COSTO DE PRODUC'!$B$37 -> 1.4929805e+08 | H35: ='AUX - COSTO DE PRODUC'!$B$37 -> 1.4929805e+08
B36: Amort. Merc en Proc y SE | D36: ='E-Costos'!B34 -> 2084275.6 | E36: ='E-Costos'!C34 -> 1740277 | F36: ='E-Costos'!D34 -> 1740277 | G36: ='E-Costos'!E34 -> 1740277 | H36: ='E-Costos'!F34 -> 1740277
B37: Amort. Prod. Realiz. | D37: =D35-D36 -> 1.4721377e+08 | E37: =E35-E36 -> 1.4755777e+08 | F37: =F35-F36 -> 1.4755777e+08 | G37: =G35-G36 -> 1.4755777e+08 | H37: =H35-H36 -> 1.4755777e+08
B38: Producción | D38: 37009 | E38: 44800 | F38: 44800 | G38: 44800 | H38: 44800
B39: Amort. Prod. Realiz. Unit. | D39: =D37/D38 -> 3977.7831 | E39: =E37/E38 -> 3293.7003 | F39: =F37/F38 -> 3293.7003 | G39: =G37/G38 -> 3293.7003 | H39: =H37/H38 -> 3293.7003
B40: Amort. Stock PT | D40: =D39*D29 -> 1897402.5 | E40: =E39*E29 -> 1571095 | F40: =F39*F29 -> 1571095 | G40: =G39*G29 -> 1571095 | H40: =H39*H29 -> 1571095

Sheet E-Cal Inv.
A1: ESTA PLANILLA PUEDE SER UTILIZADA SOLAMENTE PARA EL TRABAJO PRACTICO: | G1: =InfoInicial!E1 -> 6
A3: Calendario de Inversiones
A4: Rubros | B4: Año 0: Preinversion | C4: Año 0: Instalación | D4: Año 1 | E4: Año 2 | F4: Año 3 | G4: Año 4 | H4: Año 5 | I4: Totales
A5: Inversiones en Activo Fijo
A6: Bienes de uso | C6: ='E-Inv AF y Am'!B21+'E-Inv AF y Am'!D21 -> 2.2250045e+09 | I6: =SUM(B6:H6) -> 2.2250045e+09
A7: Asimilables | B7: ='E-Inv AF y Am'!B24 -> 32500000 | C7: ='E-Inv AF y Am'!B33-'E-Inv AF y Am'!B24 -> 30159828 | D7: ='E-Inv AF y Am'!C33 -> 3.4546504e+08 | I7: =SUM(B7:H7) -> 4.0812486e+08
A8: Subtotal Activo Fijo | B8: =B7 -> 32500000 | C8: =C6+C7 -> 2.2551643e+09 | D8: =D7 -> 3.4546504e+08 | I8: =SUM(B8:H8) -> 2.6331293e+09
A10: Inversiones en A. de Trabajo
A11: Disp. mínimas C y B | C11: ='E-InvAT'!B6 -> 63673280 | D11: ='E-InvAT'!C6-'E-InvAT'!C11 -> 46685720 | E11: ='E-InvAT'!D6-'E-InvAT'!C6 -> 10008400 | I11: =SUM(B11:H11) -> 1.203674e+08
A12: Crédito por ventas | D12: ='E-InvAT'!C7-'E-InvAT'!C19-'E-InvAT'!C20 -> 2.1985478e+08 | E12: ='E-InvAT'!D7-'E-InvAT'!D19-'E-InvAT'!D20 -> 2.4607284e+08 | F12: ='E-InvAT'!E7-'E-InvAT'!E19-'E-InvAT'!E20 -> 2.4604443e+08 | G12: ='E-InvAT'!F7-'E-InvAT'!F19-'E-InvAT'!F20 -> 2.4604472e+08 | H12: ='E-InvAT'!G7-'E-InvAT'!G19-'E-InvAT'!G20 -> 2.4604472e+08 | I12: =SUM(B12:H12) -> 1.2040615e+09
A13: Bienes de cambio: | I13: =SUM(B13:H13) -> 0
A14: Stock de Materia Prima | C14: ='E-InvAT'!B10 -> 3.4547793e+08 | D14: ='E-InvAT'!C10-'E-InvAT'!B10 -> 1.4131869e+08 | E14: ='E-InvAT'!D10-'E-InvAT'!C10 -> 0 | F14: ='E-InvAT'!E10-'E-InvAT'!D10 -> 0 | G14: ='E-InvAT'!F10-'E-InvAT'!E10 -> 0 | H14: ='E-InvAT'!G10-'E-InvAT'!F10 -> 0 | I14: =SUM(B14:H14) -> 4.8679663e+08
A15: Stock de Materiales | D15: ='E-InvAT'!C11 -> 32905880 | E15: ='E-InvAT'!D11-'E-InvAT'!C11 -> 450603.45 | F15: ='E-InvAT'!E11-'E-InvAT'!D11 -> 0 | G15: ='E-InvAT'!F11-'E-InvAT'!E11 -> 0 | H15: ='E-InvAT'!G11-'E-InvAT'!F11 -> 0 | I15: =SUM(B15:H15) -> 33356484
A16: Mercadería en proceso | D16: ='E-InvAT'!C12 -> 36298795 | E16: ='E-InvAT'!D12-'E-InvAT'!C12 -> -614366.31 | F16: ='E-InvAT'!E12-'E-InvAT'!D12 -> 0 | G16: ='E-InvAT'!F12-'E-InvAT'!E12 -> 0 | H16: ='E-InvAT'!G12-'E-InvAT'!F12 -> 0 | I16: =SUM(B16:H16) -> 35684429
A17: Stock de Elaborados | D17: ='E-InvAT'!C13 -> 21531998 | E17: ='E-InvAT'!D13-'E-InvAT'!C13 -> 13445.608 | F17: ='E-InvAT'!E13-'E-InvAT'!D13 -> -6541.3555 | G17: ='E-InvAT'!F13-'E-InvAT'!E13 -> 0 | H17: ='E-InvAT'!G13-'E-InvAT'!F13 -> 0 | I17: =SUM(B17:H17) -> 21538902
A18: Subtotal Activo Trabajo | C18: =SUM(C11:C17) -> 4.0915121e+08 | D18: =SUM(D11:D17) -> 4.9859586e+08 | E18: =SUM(E11:E17) -> 2.5593092e+08 | F18: =SUM(F11:F17) -> 2.4603789e+08 | G18: =SUM(G11:G17) -> 2.4604472e+08 | H18: =SUM(H11:H17) -> 2.4604472e+08 | I18: =SUM(B18:H18) -> 1.9018053e+09
I19: =SUM(B19:H19) -> 0
A20: IVA: | I20: =SUM(B20:H20) -> 0
A21: por inversión A. Fijo | B21: =B8*InfoInicial!$B$3 -> 6825000 | C21: =C8*InfoInicial!$B$3 -> 4.735845e+08 | D21: =D8*InfoInicial!$B$3 -> 72547658 | E21: =E8*InfoInicial!$B$3 -> 0 | F21: =F8*InfoInicial!$B$3 -> 0 | G21: =G8*InfoInicial!$B$3 -> 0 | H21: =H8*InfoInicial!$B$3 -> 0 | I21: =SUM(B21:H21) -> 5.5295716e+08
A22: por inversión A. T. | C22: ='E-InvAT'!B34 -> 72550366 | D22: ='E-InvAT'!C34 -> 48731627 | E22: ='E-InvAT'!D34 -> -31566.622 | F22: ='E-InvAT'!E34 -> -1373.6847 | G22: ='E-InvAT'!F34 -> 0 | H22: ='E-InvAT'!G34 -> 0 | I22: =SUM(B22:H22) -> 1.2124905e+08
A23: Subtotal IVA Inversión | B23: =SUM(B21:B22) -> 6825000 | C23: =SUM(C21:C22) -> 5.4613487e+08 | D23: =SUM(D21:D22) -> 1.2127928e+08 | E23: =SUM(E21:E22) -> -31566.622 | F23: =SUM(F21:F22) -> -1373.6847 | G23: =SUM(G21:G22) -> 0 | H23: =SUM(H21:H22) -> 0 | I23: =SUM(B23:H23) -> 6.7420621e+08
I24: =SUM(B24:H24) -> 0
A25: Inversiones Totales | B25: =B8+B18+B23 -> 39325000 | C25: =C8+C18+C23 -> 3.2104504e+09 | D25: =D8+D18+D23 -> 9.6534018e+08 | E25: =E8+E18+E23 -> 2.5589935e+08 | F25: =F8+F18+F23 -> 2.4603651e+08 | G25: =G8+G18+G23 -> 2.4604472e+08 | H25: =H8+H18+H23 -> 2.4604472e+08 | I25: =SUM(B25:H25) -> 5.2091409e+09
C34: inversion en cred x vta = | E34: Valor contable - Utilidad - amortiz totales
E36: Valor contable = | F36: Ventas anuales/dias año * plazo credito

Sheet E-IVA 
A1: ESTA PLANILLA PUEDE SER UTILIZADA SOLAMENTE PARA EL TRABAJO PRACTICO: | G1: =InfoInicial!E1 -> 6
A2: IVA plan de Explotación, Cancelación del Credito Fiscal y pago al Fisco por IVA
B3: TOTALES PARA LAS TRES AREAS
A4: Rubros | B4: Año 0 | C4: Año 1 | D4: Año 2 | E4: Año 3 | F4: Año 4 | G4: Año 5
A5: Rubros que abonan IVA
A6: Materia Prima | C6: ='E-Costos'!B112*InfoInicial!$B$3 -> 3.1286169e+08 | D6: ='E-Costos'!C112*InfoInicial!$B$3 -> 3.0333704e+08 | E6: ='E-Costos'!D112*InfoInicial!$B$3 -> 3.0333704e+08 | F6: ='E-Costos'!E112*InfoInicial!$B$3 -> 3.0333704e+08 | G6: ='E-Costos'!F112*InfoInicial!$B$3 -> 3.0333704e+08
A7: Materiales | C7: ='E-Costos'!B12*InfoInicial!$B$3 -> 12277811 | D7: ='E-Costos'!C12*InfoInicial!$B$3 -> 12177684 | E7: ='E-Costos'!D12*InfoInicial!$B$3 -> 12177684 | F7: ='E-Costos'!E12*InfoInicial!$B$3 -> 12177684 | G7: ='E-Costos'!F12*InfoInicial!$B$3 -> 12177684
A8: Energía eléctrica | C8: ='E-Costos'!B13*InfoInicial!$B$3 -> 9905245.5 | D8: ='E-Costos'!C13*InfoInicial!$B$3 -> 9409983.2 | E8: ='E-Costos'!D13*InfoInicial!$B$3 -> 9409983.2 | F8: ='E-Costos'!E13*InfoInicial!$B$3 -> 9409983.2 | G8: ='E-Costos'!F13*InfoInicial!$B$3 -> 9409983.2
A9: Combustibles | C9: =('E-Costos'!B14)*InfoInicial!$B$3 -> 0 | D9: ='E-Costos'!C14*InfoInicial!$B$3 -> 0 | E9: ='E-Costos'!D14*InfoInicial!$B$3 -> 0 | F9: ='E-Costos'!E14*InfoInicial!$B$3 -> 0 | G9: ='E-Costos'!F14*InfoInicial!$B$3 -> 0
A10: Seguros | C10: =('E-Costos'!B19)*InfoInicial!$B$3 -> 5247917.5 | D10: =('E-Costos'!C19)*InfoInicial!$B$3 -> 5247917.5 | E10: =('E-Costos'!D19)*InfoInicial!$B$3 -> 5247917.5 | F10: =('E-Costos'!E19)*InfoInicial!$B$3 -> 5247917.5 | G10: =('E-Costos'!F19)*InfoInicial!$B$3 -> 5247917.5
A11: Varios | C11: 0 | D11: 0 | E11: 0 | F11: 0 | G11: 0
A12: Subtotal | C12: =SUM(C6:C11) -> 3.4029266e+08 | D12: =SUM(D6:D11) -> 3.3017263e+08 | E12: =SUM(E6:E11) -> 3.3017263e+08 | F12: =SUM(F6:F11) -> 3.3017263e+08 | G12: =SUM(G6:G11) -> 3.3017263e+08
A13: Menos: Puesta en marcha | C13: =('E-Costos'!G31+'E-Costos'!G36+'E-Costos'!G37)*InfoInicial!B3 -> 74284809 | D13: 0 | E13: 0 | F13: 0 | G13: 0
A14: (s/mano de obra directa)
A15: Merc. en proceso | C15: =('E-Costos'!B31+'E-Costos'!B36+'E-Costos'!B37)*InfoInicial!$B$3 -> 5727294.9 | D15: =('E-Costos'!C31+'E-Costos'!C36+'E-Costos'!C37)*InfoInicial!$B$3-C15 -> -47583.402 | E15: =('E-Costos'!C31+'E-Costos'!C36+'E-Costos'!C37)*InfoInicial!$B$3-('E-Costos'!C31+'E-Costos'!C36+'E-Costos'!C37)*InfoInicial!$B$3 -> 0 | F15: =('E-Costos'!D31+'E-Costos'!D36+'E-Costos'!D37)*InfoInicial!$B$3-('E-Costos'!D31+'E-Costos'!D36+'E-Costos'!D37)*InfoInicial!$B$3 -> 0 | G15: =('E-Costos'!E31+'E-Costos'!E36+'E-Costos'!E37)*InfoInicial!$B$3-('E-Costos'!E31+'E-Costos'!E36+'E-Costos'!E37)*InfoInicial!$B$3 -> 0
A16: Stock elaborados | C16: ='CÁLCULOS MP'!B92*('E-Costos'!B7+'E-Costos'!B12+'E-Costos'!B13+'E-Costos'!B19)/'CÁLCULOS MP'!B89*InfoInicial!B3 -> 4110103.5 | D16: ='CÁLCULOS MP'!B92*('E-Costos'!C7+'E-Costos'!C12+'E-Costos'!C13+'E-Costos'!C19)/'CÁLCULOS MP'!B90*InfoInicial!B3-C16 -> -815747.16 | E16: ='CÁLCULOS MP'!$B$92*('E-Costos'!D7+'E-Costos'!D12+'E-Costos'!D13+'E-Costos'!D19)/'CÁLCULOS MP'!$B$90*InfoInicial!$B$3-'CÁLCULOS MP'!$B$92*('E-Costos'!C7+'E-Costos'!C12+'E-Costos'!C13+'E-Costos'!C19)/'CÁLCULOS MP'!$B$90*InfoInicial!$B$3 -> 0 | F16: ='CÁLCULOS MP'!$B$92*('E-Costos'!E7+'E-Costos'!E12+'E-Costos'!E13+'E-Costos'!E19)/'CÁLCULOS MP'!$B$90*InfoInicial!$B$3-'CÁLCULOS MP'!$B$92*('E-Costos'!D7+'E-Costos'!D12+'E-Costos'!D13+'E-Costos'!D19)/'CÁLCULOS MP'!$B$90*InfoInicial!$B$3 -> 0 | G16: ='CÁLCULOS MP'!$B$92*('E-Costos'!F7+'E-Costos'!F12+'E-Costos'!F13+'E-Costos'!F19)/'CÁLCULOS MP'!$B$90*InfoInicial!$B$3-'CÁLCULOS MP'!$B$92*('E-Costos'!E7+'E-Costos'!E12+'E-Costos'!E13+'E-Costos'!E19)/'CÁLCULOS MP'!$B$90*InfoInicial!$B$3 -> 0
A17: Total Area Producción | C17: =C12-C13-C15-C16 -> 2.5617046e+08 | D17: =D12-D13-D15-D16 -> 3.3103596e+08 | E17: =E12-E13-E15-E16 -> 3.3017263e+08 | F17: =F12-F13-F15-F16 -> 3.3017263e+08 | G17: =G12-G13-G15-G16 -> 3.3017263e+08
A18: Total Area Administración | C18: =('E-Costos'!B62+'E-Costos'!B63+'E-Costos'!B64+'E-Costos'!B69)*InfoInicial!$B$3 -> 1639418.4 | D18: =('E-Costos'!C62+'E-Costos'!C63+'E-Costos'!C64+'E-Costos'!C69)*InfoInicial!$B$3 -> 1614655.3 | E18: =('E-Costos'!D62+'E-Costos'!D63+'E-Costos'!D64+'E-Costos'!D69)*InfoInicial!$B$3 -> 1614655.3 | F18: =('E-Costos'!E62+'E-Costos'!E63+'E-Costos'!E64+'E-Costos'!E69)*InfoInicial!$B$3 -> 1614655.3 | G18: =('E-Costos'!F62+'E-Costos'!F63+'E-Costos'!F64+'E-Costos'!F69)*InfoInicial!$B$3 -> 1614655.3
A19: Total Area Comercialización | C19: =('E-Costos'!B83+'E-Costos'!B84+'E-Costos'!B85+'E-Costos'!B90)*InfoInicial!$B$3 -> 9111207 | D19: =('E-Costos'!C83+'E-Costos'!C84+'E-Costos'!C85+'E-Costos'!C90)*InfoInicial!$B$3 -> 10822724 | E19: =('E-Costos'!D83+'E-Costos'!D84+'E-Costos'!D85+'E-Costos'!D90)*InfoInicial!$B$3 -> 10822724 | F19: =('E-Costos'!E83+'E-Costos'!E84+'E-Costos'!E85+'E-Costos'!E90)*InfoInicial!$B$3 -> 10822724 | G19: =('E-Costos'!F83+'E-Costos'!F84+'E-Costos'!F85+'E-Costos'!F90)*InfoInicial!$B$3 -> 10822724
A21: IVA total abonado por insumos | C21: =SUM(C17:C19) -> 2.6692108e+08 | D21: =SUM(D17:D19) -> 3.4347334e+08 | E21: =SUM(E17:E19) -> 3.4261001e+08 | F21: =SUM(F17:F19) -> 3.4261001e+08 | G21: =SUM(G17:G19) -> 3.4261001e+08
A22: IVA total cobrado por ventas | C22: ='C. Aux. Costos'!O5*InfoInicial!$B$3 -> 843889200 | D22: ='C. Aux. Costos'!P5*InfoInicial!$B$3 -> 1034880000 | E22: ='C. Aux. Costos'!Q5*InfoInicial!$B$3 -> 1034880000 | F22: ='C. Aux. Costos'!R5*InfoInicial!$B$3 -> 1034880000 | G22: ='C. Aux. Costos'!S5*InfoInicial!$B$3 -> 1034880000
A23: a) IVA diferencia | C23: =C22-C21 -> 5.7696812e+08 | D23: =D22-D21 -> 6.9140666e+08 | E23: =E22-E21 -> 6.9226999e+08 | F23: =F22-F21 -> 6.9226999e+08 | G23: =G22-G21 -> 6.9226999e+08
A25: b) Crédito Fiscal Anterior | B25: 0 | C25: =B27 -> 5.5295987e+08 | D25: =C27 -> 97271035 | E25: =D27 -> 0 | F25: =E27 -> 0 | G25: =F27 -> 0
A26: c) Crédito Fiscal del Año | B26: =SUM('E-Cal Inv.'!B23:C23) -> 5.5295987e+08 | C26: ='E-Cal Inv.'!D23 -> 1.2127928e+08 | D26: ='E-Cal Inv.'!E23 -> -31566.622 | E26: ='E-Cal Inv.'!F23 -> -1373.6847 | F26: ='E-Cal Inv.'!G23 -> 0 | G26: ='E-Cal Inv.'!H23 -> 0
A27: d) Crédito Fiscal Final Año | B27: =B26-B25 -> 5.5295987e+08 | C27: =+IF(C25+C26<=C23,0,C25+C26-C23) -> 97271035 | D27: =+IF(D25+D26<=D23,0,D25+D26-D23) -> 0 | E27: =+IF(E25+E26<=E23,0,E25+E26-E23) -> 0 | F27: =+IF(F25+F26<=F23,0,F25+F26-F23) -> 0 | G27: =+IF(G25+G26<=G23,0,G25+G26-G23) -> 0
A28: e) Recuepro de Credito Fiscal | B28: 0 | C28: =IF(C25+C26>=C23,C23,C25+C26) -> 5.7696812e+08 | D28: =IF(D25+D26>=D23,D23,D25+D26) -> 97239468 | E28: =IF(E25+E26>=E23,E23,E25+E26) -> -1373.6847 | F28: =IF(F25+F26>=F23,F23,F25+F26) -> 0 | G28: =IF(G25+G26>=G23,G23,G25+G26) -> 0
A30: Pago al Fisco por IVA | C30: =IF(C25+C26>=C23,0,C23-C25-C26) -> 0 | D30: =IF(D25+D26>=D23,0,D23-D25-D26) -> 5.941672e+08 | E30: =IF(E25+E26>=E23,0,E23-E25-E26) -> 6.9227137e+08 | F30: =IF(F25+F26>=F23,0,F23-F25-F26) -> 6.9226999e+08 | G30: =IF(G25+G26>=G23,0,G23-G25-G26) -> 6.9226999e+08

Sheet E-Form
A1: ESTA PLANILLA PUEDE SER UTILIZADA SOLAMENTE PARA EL TRABAJO PRACTICO: | G1: =InfoInicial!E1 -> 6
A2: Formulación del Proyecto a Nivel Económico
A3: Año | B3: Inversión en Activo Fijo | C3: Inversión en Activo de Trabajo | D3: Credito Fiscal | E3: Honorarios al Directorio | F3: Impuesto a las Ganancias | G3: Total Egresos | H3: Utilidad Economica Antes HD e IG | I3: Amortizaciones | J3: Cobro Credito Fiscal | K3: Total Ingresos | L3: Saldo Anual | M3: Saldo Acumulado
A4: 0 | B4: ='E-Cal Inv.'!B8+'E-Cal Inv.'!C8 -> 2.2876643e+09 | C4: ='E-InvAT'!B25 -> 4.0915121e+08 | D4: ='E-IVA '!B26 -> 5.5295987e+08 | E4: 0 | F4: 0 | G4: =SUM(B4:F4) -> 3.2497754e+09 | H4: 0 | I4: 0 | J4: 0 | K4: 0 | L4: =K4-G4 -> -3.2497754e+09 | M4: =L4 -> -3.2497754e+09
A5: 1 | B5: ='E-Cal Inv.'!D8 -> 3.4546504e+08 | C5: ='E-InvAT'!C25 -> 4.6384678e+08 | D5: ='E-IVA '!C26 -> 1.2127928e+08 | E5: =H5*InfoInicial!$B$5 -> 1.4331379e+08 | F5: =(H5-E5)*InfoInicial!$B$4 -> 5.9291487e+08 | G5: =SUM(B5:F5) -> 1.6668198e+09 | H5: ='E-Costos'!B138 -> 1.8373563e+09 | I5: ='E-Inv AF y Am'!D59 -> 2.1820434e+08 | J5: ='E-IVA '!C28 -> 5.7696812e+08 | K5: =SUM(H5:J5) -> 2.6325287e+09 | L5: =K5-G5 -> 9.6570898e+08 | M5: =L5+M4 -> -2.2840664e+09
A6: 2 | B6: ='E-Cal Inv.'!E8 -> 0 | C6: ='E-InvAT'!D25 -> 36746447 | D6: ='E-IVA '!D26 -> -31566.622 | E6: =H6*InfoInicial!$B$5 -> 1.8199691e+08 | F6: =(H6-E6)*InfoInicial!$B$4 -> 7.5295389e+08 | G6: =SUM(B6:F6) -> 9.7166569e+08 | H6: ='E-Costos'!C138 -> 2.3332938e+09 | I6: ='E-Inv AF y Am'!D59 -> 2.1820434e+08 | J6: ='E-IVA '!D28 -> 97239468 | K6: =SUM(H6:J6) -> 2.6487376e+09 | L6: =K6-G6 -> 1.6770719e+09 | M6: =L6+M5 -> -6.0699453e+08
A7: 3 | B7: ='E-Cal Inv.'!F8 -> 0 | C7: ='E-InvAT'!E25 -> -34947.426 | D7: ='E-IVA '!E26 -> -1373.6847 | E7: =H7*InfoInicial!$B$5 -> 1.8204639e+08 | F7: =(H7-E7)*InfoInicial!$B$4 -> 7.531586e+08 | G7: =SUM(B7:F7) -> 9.3516867e+08 | H7: ='E-Costos'!D138 -> 2.3339281e+09 | I7: ='E-Inv AF y Am'!D59 -> 2.1820434e+08 | J7: ='E-IVA '!E28 -> -1373.6847 | K7: =SUM(H7:J7) -> 2.5521311e+09 | L7: =K7-G7 -> 1.6169624e+09 | M7: =L7+M6 -> 1.0099679e+09
A8: 4 | B8: ='E-Cal Inv.'!G8 -> 0 | C8: ='E-InvAT'!F25 -> 292.91913 | D8: ='E-IVA '!F26 -> 0 | E8: =H8*InfoInicial!$B$5 -> 1.8204588e+08 | F8: =(H8-E8)*InfoInicial!$B$4 -> 7.5315649e+08 | G8: =SUM(B8:F8) -> 9.3520266e+08 | H8: ='E-Costos'!E138 -> 2.3339216e+09 | I8: ='E-Inv AF y Am'!E59 -> 2.1820434e+08 | J8: ='E-IVA '!F28 -> 0 | K8: =SUM(H8:J8) -> 2.5521259e+09 | L8: =K8-G8 -> 1.6169232e+09 | M8: =L8+M7 -> 2.6268911e+09
A9: 5 | B9: =-('E-Inv AF y Am'!G59) -> -1.5421076e+09 | C9: =-('E-InvAT'!G22-'E-InvAT'!G25) -> -9.0970979e+08 | D9: ='E-IVA '!G26 -> 0 | E9: =H9*InfoInicial!$B$5 -> 1.8204588e+08 | F9: =(H9-E9)*InfoInicial!$B$4 -> 7.5315649e+08 | G9: =SUM(B9:F9) -> -1.516615e+09 | H9: ='E-Costos'!F138 -> 2.3339216e+09 | I9: ='E-Inv AF y Am'!E59 -> 2.1820434e+08 | J9: ='E-IVA '!G28 -> 0 | K9: =SUM(H9:J9) -> 2.5521259e+09 | L9: =K9-G9 -> 4.068741e+09 | M9: =L9+M8 -> 6.6956321e+09
A11: Suma. | B11: =SUM(B4:B9) -> 1.0910217e+09 | C11: =SUM(C4:C9) -> 0 | D11: =SUM(D4:D9) -> 6.7420621e+08 | E11: =SUM(E4:E9) -> 8.7144886e+08 | F11: =SUM(F4:F9) -> 3.6053403e+09 | G11: =SUM(G2:G9) -> 6.2420171e+09 | H11: =SUM(H4:H9) -> 1.1172421e+10 | I11: =SUM(I4:I9) -> 1.0910217e+09 | J11: =SUM(J4:J9) -> 6.7420621e+08 | K11: =SUM(K4:K9) -> 1.2937649e+10 | L11: =K11-G11 -> 6.6956321e+09 | M11: =M9 -> 6.6956321e+09
C13: Beneficio Neto | D13: =M9 -> 6.6956321e+09
C14: Periodo de Recupero de la Inversión | D14: =4+(-M7/L8) -> 3.3753767 | E14: en años
C15: TIR | D15: =IRR(L4:L9) -> 0.40919869
L16: Verificaciones
L17: Set A
L18: Amortizaciones | M18: =IF(ROUND(B11,3)=ROUND(I11,3),"OK","MAL") -> OK
L19: IVA | M19: =IF(ROUND(D11,3)=ROUND(J11,3),"OK","MAL") -> OK
L20: AT | M20: =IF(ROUND(C11,3)=0,"OK","MAL") -> OK
L21: BN Proyecto | M21: =IF(ROUND((H11-F11-E11),3)=ROUND(L11,3),IF(ROUND(L11,3)=ROUND(M9,3),"OK","MAL"),"MAL") -> OK

Sheet F-CRes
A1: ESTA PLANILLA PUEDE SER UTILIZADA SOLAMENTE PARA EL TRABAJO PRACTICO: | F1: =InfoInicial!E1 -> 6
A2: CUADRO DE RESULTADOS PROFORMA
A3: Rubros | B3: Año 1 | C3: Año 2 | D3: Año 3 | E3: Año 4 | F3: Año 5 | G3: Totales
A4: Ventas netas | B4: ='E-Costos'!B110 -> 4018520000 | C4: ='E-Costos'!C110 -> 4928000000 | D4: ='E-Costos'!D110 -> 4928000000 | E4: ='E-Costos'!E110 -> 4928000000 | F4: ='E-Costos'!F110 -> 4928000000 | G4: =SUM(B4:F4) -> 23730520000
A5: (-) Costo de producción de lo Vendido | B5: ='E-Costos'!B129 -> 1.6330914e+09 | C5: ='E-Costos'!C129 -> 2.0235687e+09 | D5: ='E-Costos'!D129 -> 2.0229343e+09 | E5: ='E-Costos'!E129 -> 2.0229409e+09 | F5: ='E-Costos'!F129 -> 2.0229409e+09 | G5: =SUM(B5:F5) -> 9.7254762e+09
A6: Resultado operativo | B6: =B4-B5 -> 2.3854286e+09 | C6: =C4-C5 -> 2.9044313e+09 | D6: =D4-D5 -> 2.9050657e+09 | E6: =E4-E5 -> 2.9050591e+09 | F6: =F4-F5 -> 2.9050591e+09 | G6: =SUM(B6:F6) -> 1.4005044e+10
A7: Menos:
A8: Gastos de Administración | B8: ='E-Costos'!B131 -> 1.842298e+08 | C8: ='E-Costos'!C131 -> 1.5119044e+08 | D8: ='E-Costos'!D131 -> 1.5119044e+08 | E8: ='E-Costos'!E131 -> 1.5119044e+08 | F8: ='E-Costos'!F131 -> 1.5119044e+08 | G8: =SUM(B8:F8) -> 7.8899155e+08
A9: Gastos de Comercialización | B9: ='E-Costos'!B132 -> 3.638425e+08 | C9: ='E-Costos'!C132 -> 4.1994712e+08 | D9: ='E-Costos'!D132 -> 4.1994712e+08 | E9: ='E-Costos'!E132 -> 4.1994712e+08 | F9: ='E-Costos'!F132 -> 4.1994712e+08 | G9: =SUM(B9:F9) -> 2.043631e+09
A10: Gastos Financieros | B10: ='C. Aux. F-CRes'!E3 -> 1.2211289e+09 | C10: ='C. Aux. F-CRes'!E4 -> 9.3587317e+08 | D10: ='C. Aux. F-CRes'!E5 -> 6.506175e+08 | E10: ='C. Aux. F-CRes'!E6 -> 2.852708e+08 | F10: ='C. Aux. F-CRes'!E7 -> 2.852708e+08 | G10: =SUM(B10:F10) -> 3.3781611e+09
A11: RESULTADO (a/Hon. e Imp.) | B11: =B6-B8-B9-B10 -> 6.1622743e+08 | C11: =C6-C8-C9-C10 -> 1.3974206e+09 | D11: =D6-D8-D9-D10 -> 1.6833106e+09 | E11: =E6-E8-E9-E10 -> 2.0486508e+09 | F11: =F6-F8-F9-F10 -> 2.0486508e+09 | G11: =SUM(B11:F11) -> 7.7942601e+09
A12: Menos: Honorarios al Direct. | B12: =B11*InfoInicial!$B$5 -> 48065740 | C12: =C11*InfoInicial!$B$5 -> 1.0899881e+08 | D12: =D11*InfoInicial!$B$5 -> 1.3129823e+08 | E12: =E11*InfoInicial!$B$5 -> 1.5979476e+08 | F12: =F11*InfoInicial!$B$5 -> 1.5979476e+08 | G12: =SUM(B12:F12) -> 6.0795229e+08
A13: Menos: Impuesto a la Ganancia | B13: =(B11-B12)*InfoInicial!$B$4 -> 1.9885659e+08 | C13: =(C11-C12)*InfoInicial!$B$4 -> 4.5094762e+08 | D13: =(D11-D12)*InfoInicial!$B$4 -> 5.4320433e+08 | E13: =(E11-E12)*InfoInicial!$B$4 -> 6.610996e+08 | F13: =(F11-F12)*InfoInicial!$B$4 -> 6.610996e+08 | G13: =SUM(B13:F13) -> 2.5152077e+09
A14: RESULTADO (d/Hon. e Imp.) | B14: =B11-B12-B13 -> 3.693051e+08 | C14: =C11-C12-C13 -> 8.3747415e+08 | D14: =D11-D12-D13 -> 1.008808e+09 | E14: =E11-E12-E13 -> 1.2277564e+09 | F14: =F11-F12-F13 -> 1.2277564e+09 | G14: =SUM(B14:F14) -> 4.6711001e+09

Sheet C. Aux. F-CRes
A1: Gasto financiero
A2: Año | B2: Amortizacion Int. Preoperativos | C2: Intereses C No Renovables | D2: Intereses C Renovable | E2: Total | G2: Gasto operativo | H2: ='F-Cred'!B21 -> 4.5421481e+08
A3: 1 | B3: =H2/3 -> 1.5140494e+08 | C3: ='C. Aux. F. Cred'!G21 -> 7.8445312e+08 | D3: ='C. Aux. F. Cred'!E42 -> 2.852708e+08 | E3: =SUM(B3:D3) -> 1.2211289e+09 | G3: Amortizacion de los gastos preoperativos en 3 cuotas
A4: 2 | B4: =H2/3 -> 1.5140494e+08 | C4: ='C. Aux. F. Cred'!G23 -> 4.9919744e+08 | D4: ='C. Aux. F. Cred'!E44 -> 2.852708e+08 | E4: =SUM(B4:D4) -> 9.3587317e+08 | G4: 3
A5: 3 | B5: =H2/3 -> 1.5140494e+08 | C5: ='C. Aux. F. Cred'!G25 -> 2.1394176e+08 | D5: ='C. Aux. F. Cred'!E46 -> 2.852708e+08 | E5: =SUM(B5:D5) -> 6.506175e+08
A6: 4 | C6: ='C. Aux. F. Cred'!G27 -> 0 | D6: ='C. Aux. F. Cred'!E48 -> 2.852708e+08 | E6: =SUM(B6:D6) -> 2.852708e+08
A7: 5 | D7: ='C. Aux. F. Cred'!E50 -> 2.852708e+08 | E7: =SUM(B7:D7) -> 2.852708e+08
A8: Total | B8: =SUM(B3:B7) -> 4.5421481e+08 | C8: =SUM(C3:C7) -> 1.4975923e+09 | D8: =SUM(D3:D7) -> 1.426354e+09 | E8: =SUM(E3:E7) -> 3.3781611e+09

Sheet F-Cred
A1: ESTA PLANILLA PUEDE SER UTILIZADA SOLAMENTE PARA EL TRABAJO PRACTICO: | F1: =InfoInicial!E1 -> 6
A2: PRIMERA ESTRUCTURA FINANCIERA
A3: Rubros | B3: Total Inversión | D3: Créditos | F3: Capital Propio
A4: Inversión | B4: monto | C4: % | D4: monto | E4: % | F4: monto | G4: %
A5: Activo Fijo | B5: ='E-Cal Inv.'!I8 -> 2.6331293e+09 | C5: =B5/B8 -> 0.50548246 | D5: ='C. Aux. F. Cred'!C4 -> 1.3165647e+09 | E5: =D5/B8 -> 0.25274123 | F5: =B5-D5 -> 1.3165647e+09 | G5: =F5/F8 -> 0.44755635
A6: Activo de Trabajo | B6: ='E-Cal Inv.'!I18 -> 1.9018053e+09 | C6: =B6/B8 -> 0.36509002 | D6: ='C. Aux. F. Cred'!F4 -> 9.5090266e+08 | E6: =D6/B8 -> 0.18254501 | F6: =B6-D6 -> 9.5090266e+08 | G6: =F6/F8 -> 0.32325227
A7: IVA | B7: ='E-Cal Inv.'!I23 -> 6.7420621e+08 | C7: =B7/B8 -> 0.12942753 | F7: =B7-D7 -> 6.7420621e+08 | G7: =F7/F8 -> 0.22919138
A8: Totales | B8: =SUM(B5:B7) -> 5.2091409e+09 | C8: =SUM(C5:C7) -> 1 | D8: =SUM(D5:D7) -> 2.2674673e+09 | E8: =SUM(E5:E7) -> 0.43528624 | F8: =SUM(F5:F7) -> 2.9416735e+09 | G8: =SUM(G5:G7) -> 1
A10: CUADRO RESUMEN DE CREDITOS
A11: día/mes/año | B11: deuda | C11: amortización | D11: interés | E11: amortización | F11: deuda | G11: interés | I11: gasto
C12: semestral | D12: semestral | E12: anual | F12: prom. anual | G12: anual | H12: kd | I12: bancario
A13: 1/10/año -1 | B13: ='C. Aux. F. Cred'!C16 -> 1.3165647e+09 | G13: ='C. Aux. F. Cred'!G18 -> 4.2788352e+08 | I13: ='C. Aux. F. Cred'!H16 -> 26331293
A14: 31/12/año -1 | B14: ='C. Aux. F. Cred'!C17 -> 1.3165647e+09 | D14: ='C. Aux. F. Cred'!E17 -> 4.2788352e+08
A21: gastos preoperativos: | B21: =D21+I21 -> 4.5421481e+08 | C21: =SUM(C13:C20) -> 0 | D21: =SUM(D13:D20) -> 4.2788352e+08 | E21: =SUM(E13:E20) -> 0 | F21: =SUM(F13:F20) -> 0 | G21: =SUM(G13:G20) -> 4.2788352e+08 | H21: =SUM(H13:H20) -> 0 | I21: =SUM(I13:I20) -> 26331293
A22: ='C. Aux. F. Cred'!B19 -> 01/01 Año 1 | B22: ='C. Aux. F. Cred'!C19 -> 1.3165647e+09
A23: ='C. Aux. F. Cred'!B20 -> 30/06 Año 1 | B23: ='C. Aux. F. Cred'!C20+'C. Aux. F. Cred'!C41 -> 2.0480399e+09 | C23: ='C. Aux. F. Cred'!D20 -> 2.1942745e+08 | D23: ='C. Aux. F. Cred'!E20+'C. Aux. F. Cred'!D41 -> 5.7051892e+08
A24: ='C. Aux. F. Cred'!B21 -> 31/12 Año 1 | B24: ='C. Aux. F. Cred'!C21+'C. Aux. F. Cred'!C42 -> 1.8286124e+09 | C24: ='C. Aux. F. Cred'!D21 -> 2.1942745e+08 | D24: ='C. Aux. F. Cred'!E21+'C. Aux. F. Cred'!D42 -> 4.99205e+08 | E24: =SUM(C23:C24) -> 4.3885489e+08 | F24: =D23+D24 -> 1.0697239e+09 | G24: =D23+D24 -> 1.0697239e+09 | H24: =G24/F24 -> 1
A25: ='C. Aux. F. Cred'!B22 -> 30/06 Año 2 | B25: ='C. Aux. F. Cred'!C22+'C. Aux. F. Cred'!C43 -> 1.609185e+09 | C25: ='C. Aux. F. Cred'!D22 -> 2.1942745e+08 | D25: ='C. Aux. F. Cred'!E22+'C. Aux. F. Cred'!D43 -> 4.2789108e+08
A26: ='C. Aux. F. Cred'!B23 -> 31/12 Año 2 | B26: ='C. Aux. F. Cred'!C23+'C. Aux. F. Cred'!C44 -> 1.3897576e+09 | C26: ='C. Aux. F. Cred'!D23 -> 2.1942745e+08 | D26: ='C. Aux. F. Cred'!E23+'C. Aux. F. Cred'!D44 -> 3.5657716e+08 | E26: =SUM(C25:C26) -> 4.3885489e+08 | F26: =D25+D26 -> 7.8446824e+08 | G26: =D25+D26 -> 7.8446824e+08 | H26: =G26/F26 -> 1
A27: ='C. Aux. F. Cred'!B24 -> 30/06 Año 3 | B27: ='C. Aux. F. Cred'!C24+'C. Aux. F. Cred'!C45 -> 1.1703301e+09 | C27: ='C. Aux. F. Cred'!D24 -> 2.1942745e+08 | D27: ='C. Aux. F. Cred'!E24+'C. Aux. F. Cred'!D45 -> 2.8526324e+08
A28: ='C. Aux. F. Cred'!B25 -> 31/12 Año 3 | B28: ='C. Aux. F. Cred'!C25+'C. Aux. F. Cred'!C46 -> 9.5090266e+08 | C28: ='C. Aux. F. Cred'!D25 -> 2.1942745e+08 | D28: ='C. Aux. F. Cred'!E25+'C. Aux. F. Cred'!D46 -> 2.1394932e+08 | E28: =SUM(C27:C28) -> 4.3885489e+08 | F28: =D27+D28 -> 4.9921256e+08 | G28: =D27+D28 -> 4.9921256e+08 | H28: =G28/F28 -> 1
A29: ='C. Aux. F. Cred'!B47 -> 30/06 Año 4 | B29: ='C. Aux. F. Cred'!C47 -> 9.5090266e+08 | C29: ='C. Aux. F. Cred'!D26 -> 0 | D29: ='C. Aux. F. Cred'!D47 -> 1.426354e+08
A30: ='C. Aux. F. Cred'!B48 -> 31/12 Año 4 | B30: ='C. Aux. F. Cred'!C48 -> 9.5090266e+08 | D30: ='C. Aux. F. Cred'!D48 -> 1.426354e+08 | E30: =SUM(C29:C30) -> 0 | F30: =D29+D30 -> 2.852708e+08 | G30: =D29+D30 -> 2.852708e+08 | H30: =G30/F30 -> 1
A31: ='C. Aux. F. Cred'!B49 -> 30/06 Año 5 | B31: ='C. Aux. F. Cred'!C49 -> 9.5090266e+08 | D31: ='C. Aux. F. Cred'!D49 -> 1.426354e+08
A32: ='C. Aux. F. Cred'!B50 -> 31/12 Año 5 | B32: ='C. Aux. F. Cred'!C50 -> 9.5090266e+08 | D32: ='C. Aux. F. Cred'!D50 -> 1.426354e+08 | E32: =SUM(C31:C32) -> 0 | F32: =D31+D32 -> 2.852708e+08 | G32: =D31+D32 -> 2.852708e+08 | H32: =G32/F32 -> 1
A54: Totales: | C54: =SUM(C22:C31) -> 1.3165647e+09 | D54: =SUM(D23:D32) -> 2.9239463e+09 | E54: =SUM(E22:E32) -> 1.3165647e+09 | F54: =SUM(F22:F32) -> 2.9239463e+09 | G54: =SUM(G22:G32) -> 2.9239463e+09 | I54: ='C. Aux. F. Cred'!H28 -> 26331293

Sheet C. Aux. F. Cred
B2: Activo Fijo | C2: ='F-Cred'!B5 -> 2.6331293e+09 | E2: Activo de trabajo | F2: ='F-Cred'!B6 -> 1.9018053e+09
B3: % a financiar: | C3: 0.5 | E3: % a financiar: | F3: 0.5
B4: Total a financiar: | C4: =C2*C3 -> 1.3165647e+09 | E4: Total a financiar: | F4: =F2*F3 -> 9.5090266e+08
B8: Máquinaria operativa: crédito no renovable
B9: Amortización: 6 cuotas semestrales, sistema alemán. Periodo de gracia: 6 meses.
B10: Interes: | C10: 0.65 | D10: anual
B11: Comisiones y gastos bancarios: | D11: 0.02
B13: Servicio de crédito: Maquinaria operativa
B14: día/mes/año | C14: Deuda | D14: Amortización semestral | E14: Interés semestral | F14: Amortización anual | G14: Interés anual | H14: Gasto bancario | I14: Cuota
B16: 1/6 Año -1 | C16: =C4 -> 1.3165647e+09 | H16: =C17*D11 -> 26331293
B17: 31/12 Año -1 | C17: =C4 -> 1.3165647e+09 | E17: =C17*C10*6/12 -> 4.2788352e+08
B18: Gastos preoperativos | E18: =E17 -> 4.2788352e+08 | G18: =E18 -> 4.2788352e+08 | H18: =H16 -> 26331293 | I18: =G18+H18 -> 4.5421481e+08
B19: 01/01 Año 1 | C19: =C17 -> 1.3165647e+09
B20: 30/06 Año 1 | C20: =C19-D20 -> 1.0971372e+09 | D20: =$C$17/6 -> 2.1942745e+08 | E20: =C19*$C$10/2 -> 4.2788352e+08 | I20: =D20+E20 -> 6.4731096e+08
B21: 31/12 Año 1 | C21: =C20-D21 -> 8.7770978e+08 | D21: =$C$17/6 -> 2.1942745e+08 | E21: =C20*$C$10/2 -> 3.565696e+08 | F21: =D20+D21 -> 4.3885489e+08 | G21: =E20+E21 -> 7.8445312e+08 | I21: =D21+E21 -> 5.7599704e+08
B22: 30/06 Año 2 | C22: =C21-D22 -> 6.5828234e+08 | D22: =$C$17/6 -> 2.1942745e+08 | E22: =C21*$C$10/2 -> 2.8525568e+08 | I22: =D22+E22 -> 5.0468312e+08
B23: 31/12 Año 2 | C23: =C22-D23 -> 4.3885489e+08 | D23: =$C$17/6 -> 2.1942745e+08 | E23: =C22*$C$10/2 -> 2.1394176e+08 | F23: =D23+D22 -> 4.3885489e+08 | G23: =E22+E23 -> 4.9919744e+08 | I23: =D23+E23 -> 4.333692e+08
B24: 30/06 Año 3 | C24: =C23-D24 -> 2.1942745e+08 | D24: =$C$17/6 -> 2.1942745e+08 | E24: =C23*$C$10/2 -> 1.4262784e+08 | I24: =D24+E24 -> 3.6205528e+08
B25: 31/12 Año 3 | C25: =C24-D25 -> 0 | D25: =$C$17/6 -> 2.1942745e+08 | E25: =C24*$C$10/2 -> 71313920 | F25: =D25+D24 -> 4.3885489e+08 | G25: =E25+E24 -> 2.1394176e+08 | I25: =D25+E25 -> 2.9074136e+08
B28: Totales | D28: =SUM(D20:D27) -> 1.3165647e+09 | E28: =SUM(E20:E27) -> 1.4975923e+09 | F28: =SUM(F20:F27) -> 1.3165647e+09 | G28: =SUM(G20:G27) -> 1.4975923e+09 | H28: =H18 -> 26331293
B31: Materia prima: Crédito renovable
B32: No hay período de gracia.
B33: Tasa anual de pago semestral vencido, sistema alemán.
B34: Comisiones y gastos bancarios: nulos
B35: Interes: | C35: 0.3 | D35: anual | E35: =C35*F4 -> 2.852708e+08
B36: Se requieren 5 créditos de 12 meses.
B38: Servicio de crédito: Materia prima
B39: día/mes/año | C39: deuda | D39: interés | E39: interés
D40: semestral | E40: anual
B41: 30/06 Año 1 | C41: =$F$4 -> 9.5090266e+08 | D41: =$E$35/2 -> 1.426354e+08
B42: 31/12 Año 1 | C42: =$F$4 -> 9.5090266e+08 | D42: =$E$35/2 -> 1.426354e+08 | E42: =D41+D42 -> 2.852708e+08
B43: 30/06 Año 2 | C43: =$F$4 -> 9.5090266e+08 | D43: =$E$35/2 -> 1.426354e+08
B44: 31/12 Año 2 | C44: =$F$4 -> 9.5090266e+08 | D44: =$E$35/2 -> 1.426354e+08 | E44: =D43+D44 -> 2.852708e+08
B45: 30/06 Año 3 | C45: =$F$4 -> 9.5090266e+08 | D45: =$E$35/2 -> 1.426354e+08
B46: 31/12 Año 3 | C46: =$F$4 -> 9.5090266e+08 | D46: =$E$35/2 -> 1.426354e+08 | E46: =D45+D46 -> 2.852708e+08
B47: 30/06 Año 4 | C47: =$F$4 -> 9.5090266e+08 | D47: =$E$35/2 -> 1.426354e+08
B48: 31/12 Año 4 | C48: =$F$4 -> 9.5090266e+08 | D48: =$E$35/2 -> 1.426354e+08 | E48: =D47+D48 -> 2.852708e+08
B49: 30/06 Año 5 | C49: =$F$4 -> 9.5090266e+08 | D49: =$E$35/2 -> 1.426354e+08
B50: 31/12 Año 5 | C50: =$F$4 -> 9.5090266e+08 | D50: =$E$35/2 -> 1.426354e+08 | E50: =D50+D49 -> 2.852708e+08

Sheet F-2 Estructura
A1: ESTA PLANILLA PUEDE SER UTILIZADA SOLAMENTE PARA EL TRABAJO PRACTICO: | D1: =InfoInicial!E1 -> 6
A2: SEGUNDA ESTRUCTURA FINANCIERA
A3: Rubros | B3: Año 0 | C3: Año 1 | D3: Totales
A4: a) Inversión y calendario de activo fijo: incrementos
A6: Bienes de uso | B6: ='E-Cal Inv.'!C6 -> 2.2250045e+09 | C6: ='E-Cal Inv.'!D6 -> 0 | D6: =SUM(B6:C6) -> 2.2250045e+09
A7: Cargos diferidos: | B7: ='E-Cal Inv.'!B7+'E-Cal Inv.'!C7+'F-Cred'!G21+'F-Cred'!I21 -> 5.1687464e+08 | C7: ='E-Cal Inv.'!D7 -> 3.4546504e+08 | D7: =SUM(B7:C7) -> 8.6233968e+08
A8: Totales de activo fijo, sin IVA | B8: =SUM(B6:B7) -> 2.7418791e+09 | C8: =SUM(C6:C7) -> 3.4546504e+08 | D8: =SUM(B8:C8) -> 3.0873442e+09
A9: IVA | B9: =B8*0.21 -> 5.7579461e+08 | C9: =C8*0.21 -> 72547658 | D9: =SUM(B9:C9) -> 6.4834227e+08
A10: Totales de activo fijo, con IVA | B10: =B8+B9 -> 3.3176737e+09 | C10: =C8+C9 -> 4.1801269e+08 | D10: =SUM(B10:C10) -> 3.7356864e+09
A11: b) Inversión y calendario de activo de trabajo: incrementos
A12: Disponibilidad mínima | B12: ='E-Cal Inv.'!C11 -> 63673280 | C12: ='E-Cal Inv.'!D11 -> 46685720 | D12: =SUM(B12:C12) -> 1.10359e+08
A13: Crédito por ventas (valor contable) | C13: ='E-InvAT'!C7 -> 3.2708877e+08 | D13: =SUM(B13:C13) -> 3.2708877e+08
A14: Bienes de cambio (valor contable) | B14: ='E-InvAT'!B10 -> 3.4547793e+08 | C14: ='E-InvAT'!C10+'E-InvAT'!C11+'E-InvAT'!C12+'E-InvAT'!C13 -> 5.775333e+08 | D14: =SUM(B14:C14) -> 9.2301123e+08
A15: Totales activo de trabajo, sin IVA | B15: =SUM(B12:B14) -> 4.0915121e+08 | C15: =SUM(C12:C14) -> 9.5130779e+08 | D15: =SUM(B15:C15) -> 1.360459e+09
A16: Menos:
A17: Amortizaciones en inventarios | C17: ='E-InvAT'!C17+'E-InvAT'!C18 -> 3981678.1 | D17: =SUM(B17:C17) -> 3981678.1
A18: Amortizaciones en crédito | C18: =('E-Inv AF y Am'!D59+'C. Aux. F-CRes'!B6-C17)*30/365 -> 17607342 | D18: =SUM(B18:C18) -> 17607342
A19: Utilidades en crédito | C19: =('F-CRes'!B14/'E-Costos'!B110)*'E-InvAT'!C7 -> 30059711 | D19: =SUM(B19:C19) -> 30059711
A20: Inversión activo de trabajo, s/IVA | B20: =B15 -> 4.0915121e+08 | C20: =C15-C17-C18-C19 -> 8.9965905e+08 | D20: =SUM(B20:C20) -> 1.3088103e+09
A21: IVA | B21: ='E-InvAT'!B34 -> 72550366 | C21: ='E-InvAT'!C34 -> 48731627 | D21: =SUM(B21:C21) -> 1.2128199e+08
A22: Totales activo de trabajo (v. contable), c/IVA | B22: =B15+B21 -> 4.8170158e+08 | C22: =C15+C21 -> 1.0000394e+09 | D22: =SUM(B22:C22) -> 1.481741e+09
A23: Inversión activo de trabajo, con IVA | B23: =B20+B21 -> 4.8170158e+08 | C23: =C20+C21 -> 9.4839068e+08 | D23: =SUM(B23:C23) -> 1.4300923e+09
A24: c) Inversión y calendario totales: incrementos
A25: Activo fijo, con IVA | B25: =B10 -> 3.3176737e+09 | C25: =C10 -> 4.1801269e+08 | D25: =SUM(B25:C25) -> 3.7356864e+09
A26: Inversión activo de trabajo, c/IVA | B26: =B23 -> 4.8170158e+08 | C26: =C23 -> 9.4839068e+08 | D26: =SUM(B26:C26) -> 1.4300923e+09
A27: Inversiones Totales, con IVA | B27: =B25+B26 -> 3.7993753e+09 | C27: =C25+C26 -> 1.3664034e+09 | D27: =SUM(B27:C27) -> 5.1657787e+09
A28: d) Financiación global (segunda y definitiva): | E28: Porcentaje
A29: Crédito renovable | C29: ='F-Cred'!D6 -> 9.5090266e+08 | D29: =SUM(B29:C29) -> 9.5090266e+08 | E29: =D29/$D$32 -> 0.18407731
A30: Crédito no renovable | B30: ='F-Cred'!D5 -> 1.3165647e+09 | D30: =SUM(B30:C30) -> 1.3165647e+09 | E30: =D30/$D$32 -> 0.25486277
A31: Capital propio | B31: =B27-B30 -> 2.4828106e+09 | C31: =C27-C29 -> 4.1550071e+08 | D31: =SUM(B31:C31) -> 2.8983114e+09 | E31: =D31/$D$32 -> 0.56105992
A32: Totales | B32: =SUM(B29:B31) -> 3.7993753e+09 | C32: =SUM(C29:C31) -> 1.3664034e+09 | D32: =SUM(B32:C32) -> 5.1657787e+09 | E32: =D32/$D$32 -> 1
A34: PUNTO DE EQUILIBRIO ECONOMICO FINANCIERO
A35: Rubros | B35: Año 1 | C35: Año 2 | D35: Año 3 | E35: Año 4 | F35: Año 5
A36: Costo Variable Sector de Producción | B36: {=_xlfn.XLOOKUP(A36,'E-Costos'!$A$150:$A$155,'E-Costos'!$B$150:$B$155,1,FALSE)} -> 1.630097e+09 | C36: {=_xlfn.XLOOKUP(A36,'E-Costos'!$A$150:$A$155,'E-Costos'!$C$150:$C$155,1,FALSE)} -> 1.7173012e+09 | D36: {=_xlfn.XLOOKUP(A36,'E-Costos'!$A$150:$A$155,'E-Costos'!$D$150:$D$155,1,FALSE)} -> 1.7179156e+09 | E36: {=_xlfn.XLOOKUP(A36,'E-Costos'!$A$150:$A$155,'E-Costos'!$E$150:$E$155,1,FALSE)} -> 1.7179156e+09 | F36: {=_xlfn.XLOOKUP(A36,'E-Costos'!$A$150:$A$155,'E-Costos'!$F$150:$F$155,1,FALSE)} -> 1.7179156e+09
A37: Costo Constante Sector de Producción | B37: {=_xlfn.XLOOKUP(A37,'E-Costos'!$A$150:$A$155,'E-Costos'!$B$150:$B$155,1,FALSE)} -> 6.600738e+08 | C37: {=_xlfn.XLOOKUP(A37,'E-Costos'!$A$150:$A$155,'E-Costos'!$C$150:$C$155,1,FALSE)} -> 5.3451093e+08 | D37: {=_xlfn.XLOOKUP(A37,'E-Costos'!$A$150:$A$155,'E-Costos'!$D$150:$D$155,1,FALSE)} -> 5.3451093e+08 | E37: {=_xlfn.XLOOKUP(A37,'E-Costos'!$A$150:$A$155,'E-Costos'!$E$150:$E$155,1,FALSE)} -> 5.3451093e+08 | F37: {=_xlfn.XLOOKUP(A37,'E-Costos'!$A$150:$A$155,'E-Costos'!$F$150:$F$155,1,FALSE)} -> 5.3451093e+08
A38: Costo Variable Sector de Administración | B38: {=_xlfn.XLOOKUP(A38,'E-Costos'!$A$150:$A$155,'E-Costos'!$B$150:$B$155,1,FALSE)} -> 0 | C38: {=_xlfn.XLOOKUP(A38,'E-Costos'!$A$150:$A$155,'E-Costos'!$C$150:$C$155,1,FALSE)} -> 0 | D38: {=_xlfn.XLOOKUP(A38,'E-Costos'!$A$150:$A$155,'E-Costos'!$D$150:$D$155,1,FALSE)} -> 0 | E38: {=_xlfn.XLOOKUP(A38,'E-Costos'!$A$150:$A$155,'E-Costos'!$E$150:$E$155,1,FALSE)} -> 0 | F38: {=_xlfn.XLOOKUP(A38,'E-Costos'!$A$150:$A$155,'E-Costos'!$F$150:$F$155,1,FALSE)} -> 0
A39: Costo Constante Sector de Administración | B39: {=_xlfn.XLOOKUP(A39,'E-Costos'!$A$150:$A$155,'E-Costos'!$B$150:$B$155,1,FALSE)} -> 1.842298e+08 | C39: {=_xlfn.XLOOKUP(A39,'E-Costos'!$A$150:$A$155,'E-Costos'!$C$150:$C$155,1,FALSE)} -> 1.5119044e+08 | D39: {=_xlfn.XLOOKUP(A39,'E-Costos'!$A$150:$A$155,'E-Costos'!$D$150:$D$155,1,FALSE)} -> 1.5119044e+08 | E39: {=_xlfn.XLOOKUP(A39,'E-Costos'!$A$150:$A$155,'E-Costos'!$E$150:$E$155,1,FALSE)} -> 1.5119044e+08 | F39: {=_xlfn.XLOOKUP(A39,'E-Costos'!$A$150:$A$155,'E-Costos'!$F$150:$F$155,1,FALSE)} -> 1.5119044e+08
A40: Costo Variable Sector de Comercialización | B40: {=_xlfn.XLOOKUP(A40,'E-Costos'!$A$150:$A$155,'E-Costos'!$B$150:$B$155,1,FALSE)} -> 1.899664e+08 | C40: {=_xlfn.XLOOKUP(A40,'E-Costos'!$A$150:$A$155,'E-Costos'!$C$150:$C$155,1,FALSE)} -> 2.3296e+08 | D40: {=_xlfn.XLOOKUP(A40,'E-Costos'!$A$150:$A$155,'E-Costos'!$D$150:$D$155,1,FALSE)} -> 2.3296e+08 | E40: {=_xlfn.XLOOKUP(A40,'E-Costos'!$A$150:$A$155,'E-Costos'!$E$150:$E$155,1,FALSE)} -> 2.3296e+08 | F40: {=_xlfn.XLOOKUP(A40,'E-Costos'!$A$150:$A$155,'E-Costos'!$F$150:$F$155,1,FALSE)} -> 2.3296e+08
A41: Costo Constante Sector de Comercialización | B41: {=_xlfn.XLOOKUP(A41,'E-Costos'!$A$150:$A$155,'E-Costos'!$B$150:$B$155,1,FALSE)} -> 1.738761e+08 | C41: {=_xlfn.XLOOKUP(A41,'E-Costos'!$A$150:$A$155,'E-Costos'!$C$150:$C$155,1,FALSE)} -> 1.8698712e+08 | D41: {=_xlfn.XLOOKUP(A41,'E-Costos'!$A$150:$A$155,'E-Costos'!$D$150:$D$155,1,FALSE)} -> 1.8698712e+08 | E41: {=_xlfn.XLOOKUP(A41,'E-Costos'!$A$150:$A$155,'E-Costos'!$E$150:$E$155,1,FALSE)} -> 1.8698712e+08 | F41: {=_xlfn.XLOOKUP(A41,'E-Costos'!$A$150:$A$155,'E-Costos'!$F$150:$F$155,1,FALSE)} -> 1.8698712e+08
A42: Gasto Financiero | B42: ='F-CRes'!B10 -> 1.2211289e+09 | C42: ='F-CRes'!C10 -> 9.3587317e+08 | D42: ='F-CRes'!D10 -> 6.506175e+08 | E42: ='F-CRes'!E10 -> 2.852708e+08 | F42: ='F-CRes'!F10 -> 2.852708e+08
A43: UTILIDAD MARGINAL | B43: ='E-Costos'!B156 -> 2.1769246e+09 | C43: ='E-Costos'!C156 -> 2.9777522e+09 | D43: ='E-Costos'!D156 -> 2.9771179e+09 | E43: ='E-Costos'!E156 -> 2.9771244e+09 | F43: ='E-Costos'!F156 -> 2.9771244e+09
A44: PUNTO DE EQUILIBRIO | B44: =(B41+B39+B37+B42)/B43 -> 1.0286569 | C44: =(C41+C39+C37+C42)/C43 -> 0.60735801 | D44: =(D41+D39+D37+D42)/D43 -> 0.51167137 | E44: =(E41+E39+E37+E42)/E43 -> 0.38895227 | F44: =(F41+F39+F37+F42)/F43 -> 0.38895227
A45: HACER DIAGRAMA DE PUNTO DE EQUILIBRIO PARA EL AÑO 1 Y PARA EL AÑO 10
A48: AÑO 1 | H48: AÑO 10
A49: Unidades a Vender por Año | B49: ='E-Costos'!B102 -> 36532 | H49: Unidades a Vender por Año | I49: ='E-Costos'!F102 -> 44800
A50: Precio de Venta Unitario | B50: ='E-Costos'!B103 -> 110000 | H50: Precio de Venta Unitario | I50: ='E-Costos'!F103 -> 110000
A51: Costo Variable Unitario | B51: =(B36+B39+B41)/B49 -> 54423.599 | H51: Costo Variable Unitario | I51: =(F36+F39+F41)/I49 -> 45894.937
A52: Costo Fijo Anual | B52: =B37+B39+B41 -> 1.0181797e+09 | H52: Costo Fijo Anual | I52: =F37+F39+F41 -> 8.7268849e+08
A53: Margen de Contribución | B53: =B50-B51 -> 55576.401 | H53: Margen de Contribución | I53: =I50-I51 -> 64105.063
A54: Punto de Equilibrio (Unidades a vender) | B54: =B49*B44 -> 37578.895 | H54: Punto de Equilibrio (Unidades a vender) | I54: =I49*F44 -> 17425.062
A55: Punto de Equilibrio Ingreso | B55: =B54*B50 -> 4.1336784e+09 | H55: Punto de Equilibrio Ingreso | I55: =I54*I50 -> 1.9167568e+09
B58: Año 1
B59: Unidades | C59: Costo Variable | D59: Costo Fijo | E59: Costo Total | F59: Ingreso Total
B60: 0 | C60: =$B$51*B60 -> 0 | D60: =$B$52 -> 1.0181797e+09 | E60: =D60+C60 -> 1.0181797e+09 | F60: =B60*$B$50 -> 0
B61: 1000 | C61: =$B$51*B61 -> 54423599 | D61: =$B$52 -> 1.0181797e+09 | E61: =D61+C61 -> 1.0726033e+09 | F61: =B61*$B$50 -> 110000000
B62: 2000 | C62: =$B$51*B62 -> 1.088472e+08 | D62: =$B$52 -> 1.0181797e+09 | E62: =D62+C62 -> 1.1270269e+09 | F62: =B62*$B$50 -> 220000000
B63: 3000 | C63: =$B$51*B63 -> 1.632708e+08 | D63: =$B$52 -> 1.0181797e+09 | E63: =D63+C63 -> 1.1814505e+09 | F63: =B63*$B$50 -> 330000000
B64: 4000 | C64: =$B$51*B64 -> 2.176944e+08 | D64: =$B$52 -> 1.0181797e+09 | E64: =D64+C64 -> 1.2358741e+09 | F64: =B64*$B$50 -> 440000000
B65: 5000 | C65: =$B$51*B65 -> 2.7211799e+08 | D65: =$B$52 -> 1.0181797e+09 | E65: =D65+C65 -> 1.2902977e+09 | F65: =B65*$B$50 -> 550000000
B66: 6000 | C66: =$B$51*B66 -> 3.2654159e+08 | D66: =$B$52 -> 1.0181797e+09 | E66: =D66+C66 -> 1.3447213e+09 | F66: =B66*$B$50 -> 660000000
B67: 7000 | C67: =$B$51*B67 -> 3.8096519e+08 | D67: =$B$52 -> 1.0181797e+09 | E67: =D67+C67 -> 1.3991449e+09 | F67: =B67*$B$50 -> 770000000
B68: 8000 | C68: =$B$51*B68 -> 4.3538879e+08 | D68: =$B$52 -> 1.0181797e+09 | E68: =D68+C68 -> 1.4535685e+09 | F68: =B68*$B$50 -> 880000000
B69: 9000 | C69: =$B$51*B69 -> 4.8981239e+08 | D69: =$B$52 -> 1.0181797e+09 | E69: =D69+C69 -> 1.5079921e+09 | F69: =B69*$B$50 -> 990000000
B70: 10000 | C70: =$B$51*B70 -> 5.4423599e+08 | D70: =$B$52 -> 1.0181797e+09 | E70: =D70+C70 -> 1.5624157e+09 | F70: =B70*$B$50 -> 1100000000
B71: 11000 | C71: =$B$51*B71 -> 5.9865959e+08 | D71: =$B$52 -> 1.0181797e+09 | E71: =D71+C71 -> 1.6168393e+09 | F71: =B71*$B$50 -> 1210000000
... B97: 36178 | C97: =$B$51*B97 -> 1.968937e+09 | D97: =$B$52 -> 1.0181797e+09 | E97: =D97+C97 -> 2.9871167e+09 | F97: =B97*$B$50 -> 3979580000
B100: Año 10
B101: Unidades | C101: Costo Variable | D101: Costo Fijo | E101: Costo Total | F101: Ingreso Total
B102: 0 | C102: =$I$51*B102 -> 0 | D102: =$I$52 -> 8.7268849e+08 | E102: =D102+C102 -> 8.7268849e+08 | F102: =B102*$I$50 -> 0
B103: 1000 | C103: =$I$51*B103 -> 45894937 | D103: =$I$52 -> 8.7268849e+08 | E103: =D103+C103 -> 9.1858342e+08 | F103: =B103*$I$50 -> 110000000
B104: 2000 | C104: =$I$51*B104 -> 91789873 | D104: =$I$52 -> 8.7268849e+08 | E104: =D104+C104 -> 9.6447836e+08 | F104: =B104*$I$50 -> 220000000
B105: 3000 | C105: =$I$51*B105 -> 1.3768481e+08 | D105: =$I$52 -> 8.7268849e+08 | E105: =D105+C105 -> 1.0103733e+09 | F105: =B105*$I$50 -> 330000000
B106: 4000 | C106: =$I$51*B106 -> 1.8357975e+08 | D106: =$I$52 -> 8.7268849e+08 | E106: =D106+C106 -> 1.0562682e+09 | F106: =B106*$I$50 -> 440000000
B107: 5000 | C107: =$I$51*B107 -> 2.2947468e+08 | D107: =$I$52 -> 8.7268849e+08 | E107: =D107+C107 -> 1.1021632e+09 | F107: =B107*$I$50 -> 550000000
B108: 6000 | C108: =$I$51*B108 -> 2.7536962e+08 | D108: =$I$52 -> 8.7268849e+08 | E108: =D108+C108 -> 1.1480581e+09 | F108: =B108*$I$50 -> 660000000
B109: 7000 | C109: =$I$51*B109 -> 3.2126456e+08 | D109: =$I$52 -> 8.7268849e+08 | E109: =D109+C109 -> 1.193953e+09 | F109: =B109*$I$50 -> 770000000
B110: 8000 | C110: =$I$51*B110 -> 3.6715949e+08 | D110: =$I$52 -> 8.7268849e+08 | E110: =D110+C110 -> 1.239848e+09 | F110: =B110*$I$50 -> 880000000
B111: 9000 | C111: =$I$51*B111 -> 4.1305443e+08 | D111: =$I$52 -> 8.7268849e+08 | E111: =D111+C111 -> 1.2857429e+09 | F111: =B111*$I$50 -> 990000000
B112: 10000 | C112: =$I$51*B112 -> 4.5894937e+08 | D112: =$I$52 -> 8.7268849e+08 | E112: =D112+C112 -> 1.3316379e+09 | F112: =B112*$I$50 -> 1100000000
B113: 11000 | C113: =$I$51*B113 -> 5.048443e+08 | D113: =$I$52 -> 8.7268849e+08 | E113: =D113+C113 -> 1.3775328e+09 | F113: =B113*$I$50 -> 1210000000
... B147: 44800 | C147: =$I$51*B147 -> 2.0560932e+09 | D147: =$I$52 -> 8.7268849e+08 | E147: =D147+C147 -> 2.9287817e+09 | F147: =B147*$I$50 -> 4928000000

Sheet F-IVA
A1: ESTA PLANILLA PUEDE SER UTILIZADA SOLAMENTE PARA EL TRABAJO PRACTICO: | E1: =InfoInicial!E1 -> 6
A2: IVA plan de Explotación, Cancelación del Credito Fiscal y pago al Fisco por IVA
B3: TOTALES PARA LAS TRES AREAS
A4: Rubros | B4: Año 0 | C4: Año 1 | D4: Año 2 | E4: Año 3 | F4: Año 4 | G4: Año 5
A5: a) IVA pagado en el Costo Total de lo Vendido:
A6: Total pagado en el Area de Producción | B6: ='E-IVA '!B17 -> 0 | C6: ='E-IVA '!C17 -> 2.5617046e+08 | D6: ='E-IVA '!D17 -> 3.3103596e+08 | E6: ='E-IVA '!E17 -> 3.3017263e+08 | F6: ='E-IVA '!F17 -> 3.3017263e+08 | G6: ='E-IVA '!G17 -> 3.3017263e+08
A7: Total pagado en el Area Administrativa | B7: ='E-IVA '!B18 -> 0 | C7: ='E-IVA '!C18 -> 1639418.4 | D7: ='E-IVA '!D18 -> 1614655.3 | E7: ='E-IVA '!E18 -> 1614655.3 | F7: ='E-IVA '!F18 -> 1614655.3 | G7: ='E-IVA '!G18 -> 1614655.3
A8: Total pagado en el Area Comercial | B8: ='E-IVA '!B19 -> 0 | C8: ='E-IVA '!C19 -> 9111207 | D8: ='E-IVA '!D19 -> 10822724 | E8: ='E-IVA '!E19 -> 10822724 | F8: ='E-IVA '!F19 -> 10822724 | G8: ='E-IVA '!G19 -> 10822724
A9: Total pagado por Financiación | C9: =('C. Aux. F-CRes'!C3+'C. Aux. F-CRes'!D3)*InfoInicial!B3 -> 2.2464202e+08 | D9: =('C. Aux. F-CRes'!C4+'C. Aux. F-CRes'!D4)*InfoInicial!B3 -> 1.6473833e+08 | E9: =('C. Aux. F-CRes'!C5+'C. Aux. F-CRes'!D5)*InfoInicial!B3 -> 1.0483464e+08 | F9: =('C. Aux. F-CRes'!C6+'C. Aux. F-CRes'!D6)*InfoInicial!B3 -> 59906868 | G9: =('C. Aux. F-CRes'!C7+'C. Aux. F-CRes'!D7)*InfoInicial!B3 -> 59906868
A10: IVA abonado en Costo Total de lo Vendido: | B10: =SUM(B6:B9) -> 0 | C10: =SUM(C6:C9) -> 4.915631e+08 | D10: =SUM(D6:D9) -> 5.0821167e+08 | E10: =SUM(E6:E9) -> 4.4744464e+08 | F10: =SUM(F6:F9) -> 4.0251687e+08 | G10: =SUM(G6:G9) -> 4.0251687e+08
A12: IVA total abonado por insumos | B12: =B10 -> 0 | C12: =C10 -> 4.915631e+08 | D12: =D10 -> 5.0821167e+08 | E12: =E10 -> 4.4744464e+08 | F12: =F10 -> 4.0251687e+08 | G12: =G10 -> 4.0251687e+08
A13: IVA total cobrado por ventas | B13: 0 | C13: ='F-CRes'!B4*InfoInicial!$B$3 -> 843889200 | D13: ='F-CRes'!C4*InfoInicial!$B$3 -> 1034880000 | E13: ='F-CRes'!D4*InfoInicial!$B$3 -> 1034880000 | F13: ='F-CRes'!E4*InfoInicial!$B$3 -> 1034880000 | G13: ='F-CRes'!F4*InfoInicial!$B$3 -> 1034880000
A14: b) IVA diferencia | B14: =B12-B13 -> 0 | C14: =C13-C12 -> 3.523261e+08 | D14: =D13-D12 -> 5.2666833e+08 | E14: =E13-E12 -> 5.8743536e+08 | F14: =F13-F12 -> 6.3236313e+08 | G14: =G13-G12 -> 6.3236313e+08
A16: c) Crédito Fiscal Anterior (incrementado) | B16: 0 | C16: =B17 -> 6.4834498e+08 | D16: =C18 -> 4.1729817e+08 | E16: =D18 -> 0 | F16: =E18 -> 0 | G16: =F18 -> 0
A17: d) Crédito Fiscal del Año (incrementado) | B17: ='F-2 Estructura'!B9+'F-2 Estructura'!B21 -> 6.4834498e+08 | C17: ='F-2 Estructura'!C9+'F-2 Estructura'!C21 -> 1.2127928e+08 | D17: ='E-IVA '!D26 -> -31566.622 | E17: ='E-IVA '!E26 -> -1373.6847 | F17: ='E-IVA '!F26 -> 0 | G17: ='E-IVA '!G26 -> 0
A18: e) Crédito Fiscal Final Año | B18: =B17 -> 6.4834498e+08 | C18: =IF(C16+C17>C14,C16+C17-C14,0) -> 4.1729817e+08 | D18: =IF(D16+D17>D14,D16+D17-D14,0) -> 0 | E18: =IF(E16+E17>E14,E16+E17-E14,0) -> 0 | F18: =IF(F16+F17>F14,F16+F17-F14,0) -> 0 | G18: =IF(G16+G17>G14,G16+G17-G14,0) -> 0
A19: f) Recupero Credito Fiscal | B19: 0 | C19: =C16+C17-C18 -> 3.523261e+08 | D19: =D16+D17-D18 -> 4.172666e+08 | E19: =E16+E17-E18 -> -1373.6847 | F19: =F16+F17-F18 -> 0 | G19: =G16+G17-G18 -> 0
A21: Pago al Fisco por IVA | B21: =IF((B14-B16-B17)<0,0,(B14-B16-B17)) -> 0 | C21: =IF((C14-C16-C17)<0,0,(C14-C16-C17)) -> 0 | D21: =IF((D14-D16-D17)<0,0,(D14-D16-D17)) -> 1.0940173e+08 | E21: =IF((E14-E16-E17)<0,0,(E14-E16-E17)) -> 5.8743673e+08 | F21: =IF((F14-F16-F17)<0,0,(F14-F16-F17)) -> 6.3236313e+08 | G21: =IF((G14-G16-G17)<0,0,(G14-G16-G17)) -> 6.3236313e+08

Sheet F- CFyU
A1: ESTA PLANILLA PUEDE SER UTILIZADA SOLAMENTE PARA EL TRABAJO PRACTICO: | E1: =InfoInicial!E1 -> 6
A3: CUADRO DE FUENTES Y USOS
B4: Año 0 | C4: Año 1 | D4: Año 2 | E4: Año 3 | F4: Año 4 | G4: Año 5 | H4: Totales
A5: FUENTES: Totales | B5: =SUM(B6:B11) -> 3.7993753e+09 | C5: =SUM(C6:C11) -> 5.7372495e+09 | D5: =SUM(D6:D11) -> 6.3222488e+09 | E5: =SUM(E6:E11) -> 7.039519e+09 | F5: =SUM(F6:F11) -> 7.9790894e+09 | G5: =SUM(G6:G11) -> 9.4250501e+09 | H5: =SUM(H6:H11) -> 4.0302532e+10
A6: Saldo ejercicio anterior | B6: 0 | C6: =B28 -> 0 | D6: =C27 -> 9.7698219e+08 | E6: =D27 -> 2.1115204e+09 | F6: =E27 -> 3.0510894e+09 | G6: =F27 -> 4.4970501e+09 | H6: =SUM(B6:G6) -> 1.0636642e+10
A7: Aporte de capital propio | B7: ='F-2 Estructura'!B31 -> 2.4828106e+09 | C7: ='F-2 Estructura'!C31 -> 4.1550071e+08 | D7: 0 | E7: 0 | F7: 0 | G7: 0 | H7: =SUM(B7:G7) -> 2.8983114e+09
A8: Créditos renovables | B8: 0 | C8: ='F-2 Estructura'!C29 -> 9.5090266e+08 | D8: 0 | E8: 0 | F8: 0 | G8: 0 | H8: =SUM(B8:G8) -> 9.5090266e+08
A9: Créditos no renovables | B9: ='F-2 Estructura'!B30 -> 1.3165647e+09 | C9: ='F-2 Estructura'!C30 -> 0 | D9: 0 | E9: 0 | F9: 0 | G9: 0 | H9: =SUM(B9:G9) -> 1.3165647e+09
A10: Ventas del ejercicio | B10: 0 | C10: ='F-CRes'!B4 -> 4018520000 | D10: ='F-CRes'!C4 -> 4928000000 | E10: ='F-CRes'!D4 -> 4928000000 | F10: ='F-CRes'!E4 -> 4928000000 | G10: ='F-CRes'!F4 -> 4928000000 | H10: =SUM(B10:G10) -> 23730520000
A11: Recupero Crédito Fiscal | B11: ='F-IVA'!B19 -> 0 | C11: ='F-IVA'!C19 -> 3.523261e+08 | D11: ='F-IVA'!D19 -> 4.172666e+08 | E11: ='F-IVA'!E19 -> -1373.6847 | F11: ='F-IVA'!F19 -> 0 | G11: ='F-IVA'!G19 -> 0 | H11: =SUM(B11:G11) -> 7.6959132e+08
A13: USOS: Totales | B13: =SUM(B14:B22) -> 3.7993753e+09 | C13: =SUM(C14:C22) -> 5.1298766e+09 | D13: =SUM(D14:D22) -> 4.5803377e+09 | E13: =SUM(E14:E22) -> 4.3580389e+09 | F13: =SUM(F14:F22) -> 3.7002436e+09 | G13: =SUM(G14:G22) -> 3.7002436e+09 | H13: =SUM(H14:H23) -> 2.5268116e+10
A14: Activo Fijo | B14: ='F-2 Estructura'!B8 -> 2.7418791e+09 | C14: ='F-2 Estructura'!C8 -> 3.4546504e+08 | D14: 0 | E14: 0 | F14: 0 | G14: 0 | H14: =SUM(B14:G14) -> 3.0873442e+09
A15: Activo de Trabajo | B15: ='E-InvAT'!B24 -> 4.0915121e+08 | C15: ='E-InvAT'!C24 -> 5.7506245e+08 | D15: ='E-InvAT'!D24 -> 50988494 | E15: ='E-InvAT'!E24 -> -6541.3555 | F15: ='E-InvAT'!F24 -> 0 | G15: ='E-InvAT'!G24 -> 0 | H15: =SUM(B15:G15) -> 1.0351956e+09
A16: Costo de lo Vendido | B16: 0 | C16: ='F-CRes'!B5+'F-CRes'!B8+'F-CRes'!B9+'F-CRes'!B10 -> 3.4022926e+09 | D16: ='F-CRes'!C5+'F-CRes'!C8+'F-CRes'!C9+'F-CRes'!C10 -> 3.5305794e+09 | E16: ='F-CRes'!D5+'F-CRes'!D8+'F-CRes'!D9+'F-CRes'!D10 -> 3.2446894e+09 | F16: ='F-CRes'!E5+'F-CRes'!E8+'F-CRes'!E9+'F-CRes'!E10 -> 2.8793492e+09 | G16: ='F-CRes'!F5+'F-CRes'!F8+'F-CRes'!F9+'F-CRes'!F10 -> 2.8793492e+09 | H16: =SUM(B16:G16) -> 1.593626e+10
A17: Impuesto a la Ganancia | B17: 0 | C17: ='F-CRes'!B13 -> 1.9885659e+08 | D17: ='F-CRes'!C13 -> 4.5094762e+08 | E17: ='F-CRes'!D13 -> 5.4320433e+08 | F17: ='F-CRes'!E13 -> 6.610996e+08 | G17: ='F-CRes'!F13 -> 6.610996e+08 | H17: =SUM(B17:G17) -> 2.5152077e+09
A18: Cancelación de deudas | B18: 0 | C18: ='F-Cred'!E24 -> 4.3885489e+08 | D18: ='F-Cred'!E26 -> 4.3885489e+08 | E18: ='F-Cred'!E28 -> 4.3885489e+08 | F18: ='F-Cred'!E30 -> 0 | H18: =SUM(B18:G18) -> 1.3165647e+09
A19: Honorarios del Directorio | B19: 0 | C19: ='F-CRes'!B12 -> 48065740 | D19: ='F-CRes'!C12 -> 1.0899881e+08 | E19: ='F-CRes'!D12 -> 1.3129823e+08 | F19: ='F-CRes'!E12 -> 1.5979476e+08 | G19: ='F-CRes'!F12 -> 1.5979476e+08 | H19: =SUM(B19:G19) -> 6.0795229e+08
A20: Dividendos en efectivo | B20: 0 | H20: =SUM(B20:G20) -> 0
A21: IVA inversión | B21: ='F-IVA'!B17 -> 6.4834498e+08 | C21: ='F-IVA'!C17 -> 1.2127928e+08 | D21: ='F-IVA'!D17 -> -31566.622 | E21: ='F-IVA'!E17 -> -1373.6847 | F21: ='F-IVA'!F17 -> 0 | G21: ='F-IVA'!G17 -> 0 | H21: =SUM(B21:G21) -> 7.6959132e+08
A22: Otros egresos
A24: FUENTES - USOS | B24: =B5-B13 -> 0 | C24: =C5-C13 -> 6.0737291e+08 | D24: =D5-D13 -> 1.7419111e+09 | E24: =E5-E13 -> 2.6814801e+09 | F24: =F5-F13 -> 4.2788458e+09 | G24: =G5-G13 -> 5.7248065e+09 | H24: =H5-H13 -> 1.5034416e+10
A25: Más: Amortizaciones del ejercicio | B25: 0 | C25: ='E-Inv AF y Am'!$D$59+'C. Aux. F-CRes'!B3 -> 3.6960928e+08 | D25: ='E-Inv AF y Am'!$D$59+'C. Aux. F-CRes'!B4 -> 3.6960928e+08 | E25: ='E-Inv AF y Am'!$D$59+'C. Aux. F-CRes'!B5 -> 3.6960928e+08 | F25: ='E-Inv AF y Am'!$D$59 -> 2.1820434e+08 | G25: ='E-Inv AF y Am'!$D$59 -> 2.1820434e+08 | H25: =SUM(B25:G25) -> 1.5452365e+09
A27: Saldo al ejercicio siguiente (acumulado) | B27: =B25+B24 -> 0 | C27: =C25+C24 -> 9.7698219e+08 | D27: =D25+D24 -> 2.1115204e+09 | E27: =E25+E24 -> 3.0510894e+09 | F27: =F25+F24 -> 4.4970501e+09 | G27: =G25+G24 -> 5.9430109e+09 | H27: =SUM(B27:G27) -> 1.6579653e+10
A28: Saldo Propio del Ejercicio | B28: =B27 -> 0 | C28: =C27-B27 -> 9.7698219e+08 | D28: =D27-C27 -> 1.1345382e+09 | E28: =E27-D27 -> 9.3956898e+08 | F28: =F27-E27 -> 1.4459607e+09 | G28: =G27-F27 -> 1.4459607e+09 | H28: =SUM(B28:G28) -> 5.9430109e+09

Sheet F-Balance
A1: ESTA PLANILLA PUEDE SER UTILIZADA SOLAMENTE PARA EL TRABAJO PRACTICO: | E1: =InfoInicial!E1 -> 6
A3: BALANCES PROFORMAS
B4: Año 0 | C4: Año 1 | D4: Año 2 | E4: Año 3 | F4: Año 4 | G4: Año 5
A5: ACTIVO CORRIENTE: Total | B5: =SUM(B7:B11) -> 7.6147731e+08 | C5: =SUM(C7:C11) -> 2.378494e+09 | D5: =SUM(D7:D11) -> 3.1467226e+09 | E5: =SUM(E7:E11) -> 4.086285e+09 | F5: =SUM(F7:F11) -> 5.5322457e+09 | G5: =SUM(G6:G11) -> 6.9782065e+09
A6: Caja y Bancos:
A7: - mínimo | B7: ='E-InvAT'!B6 -> 63673280 | C7: ='E-InvAT'!C6 -> 79591600 | D7: ='E-InvAT'!D6 -> 89600000 | E7: ='E-InvAT'!E6 -> 89600000 | F7: ='E-InvAT'!F6 -> 89600000 | G7: ='E-InvAT'!G6 -> 89600000
A8: - saldo acumulado de Fuentes y Usos | B8: ='F- CFyU'!B27 -> 0 | C8: ='F- CFyU'!C27 -> 9.7698219e+08 | D8: ='F- CFyU'!D27 -> 2.1115204e+09 | E8: ='F- CFyU'!E27 -> 3.0510894e+09 | F8: ='F- CFyU'!F27 -> 4.4970501e+09 | G8: ='F- CFyU'!G27 -> 5.9430109e+09
A9: Crédito por ventas | B9: ='E-InvAT'!B7 -> 0 | C9: ='E-InvAT'!C7 -> 3.2708877e+08 | D9: ='E-InvAT'!D7 -> 3.6821918e+08 | E9: ='E-InvAT'!E7 -> 3.6821918e+08 | F9: ='E-InvAT'!F7 -> 3.6821918e+08 | G9: ='E-InvAT'!G7 -> 3.6821918e+08
A10: Bienes de cambio | B10: =SUM('E-InvAT'!B10:B13) -> 3.4547793e+08 | C10: =SUM('E-InvAT'!C10:C13) -> 5.775333e+08 | D10: =SUM('E-InvAT'!D10:D13) -> 5.7738298e+08 | E10: =SUM('E-InvAT'!E10:E13) -> 5.7737644e+08 | F10: =SUM('E-InvAT'!F10:F13) -> 5.7737644e+08 | G10: =SUM('E-InvAT'!G10:G13) -> 5.7737644e+08
A11: Crédito Fiscal | B11: =IF('F-IVA'!B18>'F-IVA'!C14,'F-IVA'!C14,'F-IVA'!B18) -> 3.523261e+08 | C11: =IF('F-IVA'!C18>'F-IVA'!D14,'F-IVA'!D14,'F-IVA'!C18) -> 4.1729817e+08 | D11: =IF('F-IVA'!D18>'F-IVA'!E14,'F-IVA'!E14,'F-IVA'!D18) -> 0 | E11: =IF('F-IVA'!E18>'F-IVA'!F14,'F-IVA'!F14,'F-IVA'!E18) -> 0 | F11: =IF('F-IVA'!F18>'F-IVA'!G14,'F-IVA'!G14,'F-IVA'!F18) -> 0 | G11: =IF('F-IVA'!G18>'F-IVA'!H14,'F-IVA'!H14,'F-IVA'!G18) -> 0
A12: ACTIVO NO CORRIENTE: Total | B12: =B17+B22+B23 -> 3.037898e+09 | C12: =C17+C22+C23 -> 2.7177349e+09 | D12: =D17+D22+D23 -> 2.3481256e+09 | E12: =E17+E22+E23 -> 1.9785163e+09 | F12: =F17+F22+F23 -> 1.760312e+09 | G12: =G17+G22+G23 -> 1.5421076e+09
A13: Cargos Diferidos:
A14: - valor inicial | B14: ='F-2 Estructura'!B7 -> 5.1687464e+08 | C14: =B17 -> 5.1687464e+08 | D14: =C17 -> 6.2930977e+08 | E14: =D17 -> 3.9627986e+08 | F14: =E17 -> 1.6324995e+08 | G14: =F17 -> 81624973
A15: más inversiones del ejercicio | C15: ='F-2 Estructura'!C7 -> 3.4546504e+08 | D15: ='E-Cal Inv.'!E7 -> 0 | E15: ='F-2 Estructura'!E7 -> 0 | F15: ='F-2 Estructura'!F7 -> 0 | G15: ='F-2 Estructura'!G7 -> 0
A16: menos amortizaciones del ejerc. | C16: ='E-Inv AF y Am'!$D$56+'C. Aux. F-CRes'!$B$3 -> 2.3302991e+08 | D16: ='E-Inv AF y Am'!$D$56+'C. Aux. F-CRes'!$B$3 -> 2.3302991e+08 | E16: ='E-Inv AF y Am'!$D$56+'C. Aux. F-CRes'!$B$3 -> 2.3302991e+08 | F16: ='E-Inv AF y Am'!$E$56 -> 81624973 | G16: ='E-Inv AF y Am'!$E$56 -> 81624973
A17: - valor final del ejercicio | B17: =B14+B15-B16 -> 5.1687464e+08 | C17: =C14+C15-C16 -> 6.2930977e+08 | D17: =D14+D15-D16 -> 3.9627986e+08 | E17: =E14+E15-E16 -> 1.6324995e+08 | F17: =F14+F15-F16 -> 81624973 | G17: =G14+G15-G16 -> 0
A18: Bienes de Uso
A19: - valor inicial | B19: ='F-2 Estructura'!B6 -> 2.2250045e+09 | C19: =B22 -> 2.2250045e+09 | D19: =C22 -> 2.0884251e+09 | E19: =D22 -> 1.9518457e+09 | F19: =E22 -> 1.8152664e+09 | G19: =F22 -> 1.678687e+09
A20: más inversiones del ejercicio | C20: ='E-Cal Inv.'!D6 -> 0 | D20: ='E-Cal Inv.'!E6 -> 0 | E20: ='E-Cal Inv.'!F6 -> 0 | F20: ='E-Cal Inv.'!G6 -> 0 | G20: ='E-Cal Inv.'!H6 -> 0
A21: menos amortizaciones del ejerc | C21: ='E-Inv AF y Am'!$D$54 -> 1.3657937e+08 | D21: ='E-Inv AF y Am'!$D$54 -> 1.3657937e+08 | E21: ='E-Inv AF y Am'!$D$54 -> 1.3657937e+08 | F21: ='E-Inv AF y Am'!$E$54 -> 1.3657937e+08 | G21: ='E-Inv AF y Am'!$E$54 -> 1.3657937e+08
A22: - valor final del ejercicio | B22: =B19+B20-B21 -> 2.2250045e+09 | C22: =C19+C20-C21 -> 2.0884251e+09 | D22: =D19+D20-D21 -> 1.9518457e+09 | E22: =E19+E20-E21 -> 1.8152664e+09 | F22: =F19+F20-F21 -> 1.678687e+09 | G22: =G19+G20-G21 -> 1.5421076e+09
A23: Crédito Fiscal | B23: ='F-IVA'!B18-B11 -> 2.9601888e+08 | C23: ='F-IVA'!C18-C11 -> 0 | D23: ='F-IVA'!D18-D11 -> 0 | E23: ='F-IVA'!E18-E11 -> 0 | F23: ='F-IVA'!F18-F11 -> 0 | G23: ='F-IVA'!G18-G11 -> 0
A24: ACTIVO TOTAL: | B24: =B12+B5 -> 3.7993753e+09 | C24: =C12+C5 -> 5.0962289e+09 | D24: =D12+D5 -> 5.4948482e+09 | E24: =E12+E5 -> 6.0648013e+09 | F24: =F12+F5 -> 7.2925577e+09 | G24: =G12+G5 -> 8.5203141e+09
A25: PASIVO CORRIENTE: Total | B25: =SUM(B26:B27) -> 4.3885489e+08 | C25: =SUM(C26:C27) -> 1.3897576e+09 | D25: =SUM(D26:D27) -> 1.3897576e+09 | E25: =SUM(E26:E27) -> 9.5090266e+08 | F25: =SUM(F26:F27) -> 9.5090266e+08 | G25: =SUM(G26:G27) -> 9.5090266e+08
A26: Deudas comerciales | C26: ='F-Cred'!$D$6 -> 9.5090266e+08 | D26: ='F-Cred'!$D$6 -> 9.5090266e+08 | E26: ='F-Cred'!$D$6 -> 9.5090266e+08 | F26: ='F-Cred'!$D$6 -> 9.5090266e+08 | G26: ='F-Cred'!$D$6 -> 9.5090266e+08
A27: Deudas bancarias | B27: ='F-Cred'!E24 -> 4.3885489e+08 | C27: ='F-Cred'!E26 -> 4.3885489e+08 | D27: ='F-Cred'!E28 -> 4.3885489e+08 | E27: ='F-Cred'!E30 -> 0 | F27: ='F-Cred'!E32 -> 0 | G27: ='F-Cred'!E34 -> 0
A28: PASIVO NO CORRIENTE: Total | B28: =B29 -> 8.7770978e+08 | C28: =C29 -> 4.3885489e+08 | D28: =D29 -> 0 | E28: =E29 -> 0 | F28: =F29 -> 0 | G28: =G29 -> 0
A29: Deudas bancarias | B29: =SUM(C27:G27) -> 8.7770978e+08 | C29: =SUM(D27:G27) -> 4.3885489e+08 | D29: =SUM(E27:G27) -> 0 | E29: =SUM(F27:G27) -> 0 | F29: =SUM(G27) -> 0 | G29: =0 -> 0
A30: PASIVO TOTAL: | B30: =B28+B25 -> 1.3165647e+09 | C30: =C28+C25 -> 1.8286124e+09 | D30: =D28+D25 -> 1.3897576e+09 | E30: =E28+E25 -> 9.5090266e+08 | F30: =F28+F25 -> 9.5090266e+08 | G30: =G28+G25 -> 9.5090266e+08
A31: PATRIMONIO NETO: | B31: =B32+B33+B34 -> 2.4828106e+09 | C31: =C32+C33+C34 -> 3.2676165e+09 | D31: =D32+D33+D34 -> 4.1050906e+09 | E31: =E32+E33+E34 -> 5.1138987e+09 | F31: =F32+F33+F34 -> 6.3416551e+09 | G31: =G32+G33+G34 -> 7.5694115e+09
A32: Capital societario | B32: ='F-2 Estructura'!B31 -> 2.4828106e+09 | C32: ='F-2 Estructura'!$D$31 -> 2.8983114e+09 | D32: ='F-2 Estructura'!$D$31 -> 2.8983114e+09 | E32: ='F-2 Estructura'!$D$31 -> 2.8983114e+09 | F32: ='F-2 Estructura'!$D$31 -> 2.8983114e+09 | G32: ='F-2 Estructura'!$D$31 -> 2.8983114e+09
A33: Utilidad del ejercicio | C33: ='F-CRes'!B14 -> 3.693051e+08 | D33: ='F-CRes'!C14 -> 8.3747415e+08 | E33: ='F-CRes'!D14 -> 1.008808e+09 | F33: ='F-CRes'!E14 -> 1.2277564e+09 | G33: ='F-CRes'!F14 -> 1.2277564e+09
A34: Utilidad acumulada | C34: =B33+B34 -> 0 | D34: =C33+C34 -> 3.693051e+08 | E34: =D33+D34 -> 1.2067793e+09 | F34: =E33+E34 -> 2.2155873e+09 | G34: =F33+F34 -> 3.4433437e+09
A35: PASIVO + PATRIMONIO NETO | B35: =B30+B31 -> 3.7993753e+09 | C35: =C30+C31 -> 5.0962289e+09 | D35: =D30+D31 -> 5.4948482e+09 | E35: =E30+E31 -> 6.0648013e+09 | F35: =F30+F31 -> 7.2925577e+09 | G35: =G30+G31 -> 8.5203141e+09
A38: Verificación | B38: =IF(ROUND(B24,3)=ROUND(B35,3),"OK","MAL") -> OK | C38: =IF(ROUND(C24,3)=ROUND(C35,3),"OK","MAL") -> OK | D38: =IF(ROUND(D24,3)=ROUND(D35,3),"OK","MAL") -> OK | E38: =IF(ROUND(E24,3)=ROUND(E35,3),"OK","MAL") -> OK | F38: =IF(ROUND(F24,3)=ROUND(F35,3),"OK","MAL") -> OK | G38: =IF(ROUND(G24,3)=ROUND(G35,3),"OK","MAL") -> OK

Sheet F- Form
A1: ESTA PLANILLA PUEDE SER UTILIZADA SOLAMENTE PARA EL TRABAJO PRACTICO: | G1: =InfoInicial!E1 -> 6
A3: Formulación del Proyecto a Nivel Financiero
A4: Año | B4: Activo Fijo | C4: Activo de Trabajo | D4: Credito Fiscal | E4: Honorarios al Directorio | F4: Impuesto a las Ganancias | G4: Total Egresos | H4: Utilidad Antes HD e IG | I4: Intereses Pagados | J4: Amortizaciones | K4: Cobro Credito Fiscal | L4: Total Ingresos | M4: Saldo Anual | N4: Saldo Acumulado
A5: 0 | B5: ='F-2 Estructura'!B8 -> 2.7418791e+09 | C5: ='F- CFyU'!B15 -> 4.0915121e+08 | D5: ='F-IVA'!B17 -> 6.4834498e+08 | G5: =SUM(B5:F5) -> 3.7993753e+09 | I5: ='F-Cred'!I13+'F-Cred'!G13 -> 4.5421481e+08 | J5: ='F- CFyU'!B25 -> 0 | K5: ='F-IVA'!B19 -> 0 | L5: =SUM(H5:K5) -> 4.5421481e+08 | M5: =L5-G5 -> -3.3451605e+09 | N5: =M5 -> -3.3451605e+09
A6: 1 | B6: ='F-2 Estructura'!C8 -> 3.4546504e+08 | C6: ='F- CFyU'!C15 -> 5.7506245e+08 | D6: ='F-IVA'!C17 -> 1.2127928e+08 | E6: ='F-CRes'!B12 -> 48065740 | F6: ='F-CRes'!B13 -> 1.9885659e+08 | G6: =SUM(B6:F6) -> 1.2887291e+09 | H6: ='F-CRes'!B11 -> 6.1622743e+08 | I6: ='F-Cred'!G24 -> 1.0697239e+09 | J6: ='F- CFyU'!C25 -> 3.6960928e+08 | K6: ='F-IVA'!C19 -> 3.523261e+08 | L6: =SUM(H6:K6) -> 2.4078867e+09 | M6: =L6-G6 -> 1.1191576e+09 | N6: =N5+M6 -> -2.2260029e+09
A7: 2 | C7: ='F- CFyU'!D15 -> 50988494 | D7: ='F-IVA'!D17 -> -31566.622 | E7: ='F-CRes'!C12 -> 1.0899881e+08 | F7: ='F-CRes'!C13 -> 4.5094762e+08 | G7: =SUM(B7:F7) -> 6.1090335e+08 | H7: ='F-CRes'!C11 -> 1.3974206e+09 | I7: ='F-Cred'!F26 -> 7.8446824e+08 | J7: ='F- CFyU'!D25 -> 3.6960928e+08 | K7: ='F-IVA'!D19 -> 4.172666e+08 | L7: =SUM(H7:K7) -> 2.9687647e+09 | M7: =L7-G7 -> 2.3578613e+09 | N7: =N6+M7 -> 1.3185846e+08
A8: 3 | C8: ='F- CFyU'!E15 -> -6541.3555 | D8: ='F-IVA'!E17 -> -1373.6847 | E8: ='F-CRes'!D12 -> 1.3129823e+08 | F8: ='F-CRes'!D13 -> 5.4320433e+08 | G8: =SUM(B8:F8) -> 6.7449465e+08 | H8: ='F-CRes'!D11 -> 1.6833106e+09 | I8: ='F-Cred'!F28 -> 4.9921256e+08 | J8: ='F- CFyU'!E25 -> 3.6960928e+08 | K8: ='F-IVA'!E19 -> -1373.6847 | L8: =SUM(H8:K8) -> 2.5521311e+09 | M8: =L8-G8 -> 1.8776364e+09 | N8: =N7+M8 -> 2.0094949e+09
A9: 4 | C9: ='F- CFyU'!F15 -> 0 | D9: ='F-IVA'!F17 -> 0 | E9: ='F-CRes'!E12 -> 1.5979476e+08 | F9: ='F-CRes'!E13 -> 6.610996e+08 | G9: =SUM(B9:F9) -> 8.2089436e+08 | H9: ='F-CRes'!E11 -> 2.0486508e+09 | I9: ='F-Cred'!F30 -> 2.852708e+08 | J9: ='F- CFyU'!F25 -> 2.1820434e+08 | K9: ='F-IVA'!F19 -> 0 | L9: =SUM(H9:K9) -> 2.5521259e+09 | M9: =L9-G9 -> 1.7312315e+09 | N9: =N8+M9 -> 3.7407264e+09
A10: 5 | B10: ='E-Form'!B9 -> -1.5421076e+09 | C10: ='F- CFyU'!G15 -'F- CFyU'!H15 -> -1.0351956e+09 | D10: ='F-IVA'!G17 -> 0 | E10: ='F-CRes'!F12 -> 1.5979476e+08 | F10: ='F-CRes'!F13 -> 6.610996e+08 | G10: =SUM(B10:F10) -> -1.7564089e+09 | H10: ='F-CRes'!F11 -> 2.0486508e+09 | I10: ='F-Cred'!F32 -> 2.852708e+08 | J10: ='F- CFyU'!G25 -> 2.1820434e+08 | K10: ='F-IVA'!G19 -> 0 | L10: =SUM(H10:K10) -> 2.5521259e+09 | M10: =L10-G10 -> 4.3085348e+09 | N10: =N9+M10 -> 8.0492612e+09
A12: Suma. | B12: =SUM(B5:B10) -> 1.5452365e+09 | C12: =SUM(C5:C10) -> 0 | D12: =SUM(D5:D10) -> 7.6959132e+08 | E12: =SUM(E5:E10) -> 6.0795229e+08 | F12: =SUM(F5:F10) -> 2.5152077e+09 | G12: =SUM(G5:G10) -> 5.4379879e+09 | H12: =SUM(H5:H10) -> 7.7942601e+09 | I12: =SUM(I5:I10) -> 3.3781611e+09 | ... M12: =SUM(M5:M10) -> 8.0492612e+09
C14: Beneficio Neto | D14: =N10 -> 8.0492612e+09
C15: Periodo de Recupero de la Inversión | D15: =3+(-N7/M8) -> 2.9297742 | E15: en años
C16: TIR modificada | D16: =IRR(M5:M10) -> 0.48560675
A22: Formulación para el Inversor | K22: Verificaciones
A23: Año | B23: Aporte de Capital | C23: Total Egresos | D23: Dividendos en efectivo | E23: Saldo propio de Fuentes y Usos | F23: Total Ingresos | G23: Saldo Anual | H23: Saldo Acumulado | K23: Set A
A24: 0 | B24: ='F-2 Estructura'!B31 -> 2.4828106e+09 | C24: =B24 -> 2.4828106e+09 | D24: 0 | E24: ='F- CFyU'!B28 -> 0 | F24: =E24 -> 0 | G24: =F24-C24 -> -2.4828106e+09 | H24: =G24 -> -2.4828106e+09 | K24: Amortizaciones | L24: =IF(ROUND(B12,3)=ROUND(J12,3),"OK","MAL") -> OK
A25: 1 | B25: ='F-2 Estructura'!C31 -> 4.1550071e+08 | C25: =B25 -> 4.1550071e+08 | D25: 0 | E25: ='F- CFyU'!C28 -> 9.7698219e+08 | F25: =E25 -> 9.7698219e+08 | G25: =F25-C25 -> 5.6148148e+08 | H25: =G25+H24 -> -1.9213292e+09 | K25: IVA | L25: =IF(ROUND(D12,3)=ROUND(K12,3),"OK","MAL") -> OK
A26: 2 | D26: 0 | E26: ='F- CFyU'!D28 -> 1.1345382e+09 | F26: =E26 -> 1.1345382e+09 | G26: =F26-C26 -> 1.1345382e+09 | H26: =G26+H25 -> -7.8679095e+08 | K26: AT | L26: =IF(ROUND(C12,3)=0,"OK","MAL") -> OK
A27: 3 | D27: 0 | E27: ='F- CFyU'!E28 -> 9.3956898e+08 | F27: =E27 -> 9.3956898e+08 | G27: =F27-C27 -> 9.3956898e+08 | H27: =G27+H26 -> 1.5277803e+08 | K27: BN Proyecto | L27: =IF(ROUND((H12-F12-E12+I12),3)=ROUND(M12,3),IF(ROUND(M12,3)=ROUND(N10,3),"OK","MAL"),"MAL") -> OK
A28: 4 | D28: 0 | E28: ='F- CFyU'!F28 -> 1.4459607e+09 | F28: =E28 -> 1.4459607e+09 | G28: =F28-C28 -> 1.4459607e+09 | H28: =G28+H27 -> 1.5987388e+09 | K28: BN Proyecto | L28: =IF(ROUND(H12+I12,3)=ROUND('E-Form'!H11,3),"OK","MAL") -> OK
A29: 5 | B29: =B10+'F-Cred'!D6-'F- CFyU'!H15 -> -1.6264006e+09 | C29: =B29 -> -1.6264006e+09 | D29: 0 | E29: ='F- CFyU'!G28 -> 1.4459607e+09 | F29: =E29 -> 1.4459607e+09 | G29: =F29-C29 -> 3.0723613e+09 | H29: =G29+H28 -> 4.6711001e+09 | K29: Set B
K30: BN Inversor 1 | L30: =IF(ROUND((H12-E12-F12),3)=ROUND(G31,3),"OK","MAL") -> OK
A31: Suma. | B31: =SUM(B24:B29) -> 1.2719108e+09 | C31: =SUM(C24:C29) -> 1.2719108e+09 | D31: 0 | E31: =SUM(E24:E29) -> 5.9430109e+09 | F31: =SUM(F24:F29) -> 5.9430109e+09 | G31: =F31-C31 -> 4.6711001e+09 | K31: BN Inversor 2 | L31: =IF(ROUND(('F- CFyU'!H28-'F- CFyU'!H7-'F- CFyU'!H8+'F- CFyU'!H14-'F- CFyU'!H25+'F- CFyU'!H15),3)=ROUND('F- Form'!G31,3),"OK","MAL") -> OK
K32: BN Inversor 3 | L32: =IF(ROUND('F-CRes'!G14,3)=ROUND(G31,3),"OK","MAL") -> OK
K33: BN Inversor 4 | L33: =IF(ROUND(('F-Balance'!G33+'F-Balance'!G34),3)=ROUND('F- Form'!G31,3),"OK","MAL") -> OK
C34: Beneficio Neto | D34: =H29 -> 4.6711001e+09 | E34: para el inversor | K34: BN Inversor 5 | L34: =IF(ROUND(('F- CFyU'!H10-'F- CFyU'!H16-'F- CFyU'!H19-'F- CFyU'!H17),3)=ROUND(G31,3),"OK","MAL") -> OK
C35: Periodo de Recupero de la Inversión | D35: =4+(-H27/G28) -> 3.8943415 | E35: en años para el inversor | K35: Set C
C36: TOR | D36: =IRR(G24:G29) -> 0.35999704 | K36: Balance | L36: =IF(SUM('F-Balance'!B35:G35)=SUM('F-Balance'!B24:G24),"OK","MAL") -> OK
